{"data":[{"dv":"41.8","deal":"23374","ep":"9.95","net":"1.28","zcra12":"4.43","zcra1_12":"4.37","zch4":"14.58","zch1_4":"-11.33","type":"水泥","zcj1":"14.31","zcra22":"43.27","zca3":"28871","zcra1_3":"22.62","zcra3":"24.56","buyi":"-109","buyf":"-8312","moneyt":"8436","moneyy":"7275","stockt":"205","stocky":"174","zcra10":"12.54","zcra1_10":"12.94","id":"1101","name":"台泥","MA20":40.95,"MA5":41.37,"MA10":40.95,"MA60":42.325,"UB":42.0446,"LB":39.8554,"BLimitP":88.83,"UBSlopeP":-0.45,"signals":[],"candlestick":[],"bandWidthP":5.49,"VMA30":20076.5621,"VLimitP":63.33,"change":0.2,"changePercent":0.48,"link":"https://histock.tw/stock/tv/tvchart.aspx?no=1101","link2":"https://invest.cnyes.com/twstock/TWS/1101/technical","buyiDays":"","buyfDays":""},{"dv":"42.75","deal":"15577","ep":"10.01","net":"1.01","zcra12":"5.56","zcra1_12":"3.54","zch4":"42.72","zch1_4":"2.53","type":"水泥","zcj1":"28.87","zcra22":"43","zca3":"37272","zcra1_3":"21.94","zcra3":"23.22","buyi":"-11","buyf":"721","moneyt":"2483","moneyy":"2824","stockt":"32","stocky":"24","zcra10":"13.54","zcra1_10":"9.77","id":"1102","name":"亞泥","MA20":41.1075,"MA5":41.57,"MA10":41.085,"MA60":42.5725,"UB":42.4381,"LB":39.7769,"BLimitP":111.72,"UBSlopeP":0.14,"signals":["gt-UB","gt-MA60"],"candlestick":[],"bandWidthP":6.69,"VMA30":6162.9905,"VLimitP":136.34,"change":0.95,"changePercent":2.27,"link":"https://histock.tw/stock/tv/tvchart.aspx?no=1102","link2":"https://invest.cnyes.com/twstock/TWS/1102/technical","buyiDays":"","buyfDays":""},{"dv":"20.65","deal":"1341","ep":"27.53","net":"1.59","zcra12":"2.67","zcra1_12":"1.94","zch4":"1.31","zch1_4":"-1.78","type":"乳品","zcj1":"14.55","zcra22":"63.64","zca3":"1428","zcra1_3":"2.64","zcra3":"2.69","buyi":"0","buyf":"-49","moneyt":"5039","moneyy":"4867","stockt":"18","stocky":"18","zcra10":"20.55","zcra1_10":"12.41","id":"1201","name":"味全","MA20":20.3275,"MA5":20.39,"MA10":20.195,"MA60":21.0117,"UB":20.9271,"LB":19.7279,"BLimitP":76.89,"UBSlopeP":-0.47,"signals":[],"candlestick":[],"bandWidthP":6.08,"VMA30":1159.0472,"VLimitP":60.09,"change":0.2,"changePercent":0.98,"link":"https://histock.tw/stock/tv/tvchart.aspx?no=1201","link2":"https://invest.cnyes.com/twstock/TWS/1201/technical","buyiDays":"","buyfDays":""},{"dv":"50","deal":"4104","ep":"14.12","net":"2.08","zcra12":"2.93","zcra1_12":"2.75","zch4":"37.32","zch1_4":"10.5","type":"飼料","zcj1":"12.98","zcra22":"48.57","zca3":"5522","zcra1_3":"3.14","zcra3":"4.78","buyi":"0","buyf":"184","moneyt":"4141","moneyy":"4266","stockt":"83","stocky":"81","zcra10":"12.78","zcra1_10":"10.98","id":"1210","name":"大成","MA20":48.7175,"MA5":49.46,"MA10":48.79,"MA60":48.06,"UB":50.0799,"LB":47.3551,"BLimitP":97.07,"UBSlopeP":0.07,"signals":["lt-UB"],"candlestick":[],"bandWidthP":5.75,"VMA30":3252.5473,"VLimitP":61.94,"change":-0.3,"changePercent":-0.6,"link":"https://histock.tw/stock/tv/tvchart.aspx?no=1210","link2":"https://invest.cnyes.com/twstock/TWS/1210/technical","buyiDays":"","buyfDays":"+3"},{"dv":"68.5","deal":"6175","ep":"18.72","net":"3.52","zcra12":"3.35","zcra1_12":"3.07","zch4":"8.82","zch1_4":"3.46","type":"乳品","zcj1":"10.02","zcra22":"63.56","zca3":"58871","zcra1_3":"6.25","zcra3":"6.61","buyi":"62","buyf":"-1833","moneyt":"2366","moneyy":"2432","stockt":"69","stocky":"70","zcra10":"16.55","zcra1_10":"14.9","id":"1216","name":"統一","MA20":67.485,"MA5":68.62,"MA10":68.33,"MA60":66.8417,"UB":69.7052,"LB":65.2648,"BLimitP":72.86,"UBSlopeP":0.17,"signals":[],"candlestick":[],"bandWidthP":6.8,"VMA30":11617.0281,"VLimitP":18.85,"change":0.1,"changePercent":0.15,"link":"https://histock.tw/stock/tv/tvchart.aspx?no=1216","link2":"https://invest.cnyes.com/twstock/TWS/1216/technical","buyiDays":"+3","buyfDays":""},{"dv":"41.9","deal":"1828","ep":"19.86","net":"1.84","zcra12":"2.51","zcra1_12":"2.35","zch4":"26.38","zch1_4":"2.84","type":"大宗物資","zcj1":"25.04","zcra22":"19.15","zca3":"2821","zcra1_3":"5.89","zcra3":"11.55","buyi":"1","buyf":"-375","moneyt":"1030","moneyy":"1055","stockt":"2","stocky":"1","zcra10":"10.11","zcra1_10":"9.91","id":"1229","name":"聯華","MA20":40.9175,"MA5":41.69,"MA10":41.125,"MA60":41.395,"UB":42.0167,"LB":39.8183,"BLimitP":94.69,"UBSlopeP":0.13,"signals":["lt-UB"],"candlestick":[],"bandWidthP":5.52,"VMA30":2154.1292,"VLimitP":39.97,"change":-0.15,"changePercent":-0.36,"link":"https://histock.tw/stock/tv/tvchart.aspx?no=1229","link2":"https://invest.cnyes.com/twstock/TWS/1229/technical","buyiDays":"+2","buyfDays":""},{"dv":"97.1","deal":"13618","ep":"49.54","net":"2.11","zcra12":"5.86","zcra1_12":"7.78","zch4":"38.66","zch1_4":"25.95","type":"PVC","zcj1":"14.93","zcra22":"29.76","zca3":"46580","zcra1_3":"11","zcra3":"9.72","buyi":"175","buyf":"2078","moneyt":"1913","moneyy":"1867","stockt":"128","stocky":"149","zcra10":"10.59","zcra1_10":"14.15","id":"1301","name":"台塑","MA20":91.915,"MA5":94.86,"MA10":92.05,"MA60":91.7217,"UB":97.2996,"LB":86.5304,"BLimitP":98.15,"UBSlopeP":-0.08,"signals":[],"candlestick":[],"bandWidthP":12.45,"VMA30":10876.5574,"VLimitP":67.4,"change":1.8,"changePercent":1.89,"link":"https://histock.tw/stock/tv/tvchart.aspx?no=1301","link2":"https://invest.cnyes.com/twstock/TWS/1301/technical","buyiDays":"+6","buyfDays":"+4"},{"dv":"71.6","deal":"6801","ep":"32.11","net":"1.8","zcra12":"2.91","zcra1_12":"6.65","zch4":"31.51","zch1_4":"18.49","type":"塑膠加工","zcj1":"18.25","zcra22":"35.9","zca3":"52299","zcra1_3":"8.83","zcra3":"3.45","buyi":"15","buyf":"-478","moneyt":"1855","moneyy":"1506","stockt":"59","stocky":"61","zcra10":"6.25","zcra1_10":"13.97","id":"1303","name":"南亞","MA20":69.485,"MA5":70.2,"MA10":68.98,"MA60":69.0133,"UB":72.7366,"LB":66.2334,"BLimitP":82.52,"UBSlopeP":-0.86,"signals":[],"candlestick":[],"bandWidthP":9.82,"VMA30":7672.8551,"VLimitP":41.22,"change":1.4,"changePercent":1.99,"link":"https://histock.tw/stock/tv/tvchart.aspx?no=1303","link2":"https://invest.cnyes.com/twstock/TWS/1303/technical","buyiDays":"+5","buyfDays":""},{"dv":"27.15","deal":"13877","ep":"17.63","net":"1.73","zcra12":"1.22","zcra1_12":"2.52","zch4":"53.9","zch1_4":"36.29","type":"PVC","zcj1":"24.97","zcra22":"29.35","zca3":"2017","zcra1_3":"10.35","zcra3":"5.12","buyi":"-1970","buyf":"696","moneyt":"8316","moneyy":"7971","stockt":"204","stocky":"207","zcra10":"7.92","zcra1_10":"15.86","id":"1305","name":"華夏","MA20":24.305,"MA5":25.72,"MA10":24.615,"MA60":24.29,"UB":26.643,"LB":21.967,"BLimitP":110.84,"UBSlopeP":0.72,"signals":[],"candlestick":[],"bandWidthP":21.29,"VMA30":10381.2154,"VLimitP":59.57,"change":0.45,"changePercent":1.69,"link":"https://histock.tw/stock/tv/tvchart.aspx?no=1305","link2":"https://invest.cnyes.com/twstock/TWS/1305/technical","buyiDays":"","buyfDays":"+3"},{"dv":"36.4","deal":"1626","ep":"18.96","net":"1","zcra12":"3.36","zcra1_12":"3.26","zch4":"-4.67","zch1_4":"-17.25","type":"汽車零組件","zcj1":"25.67","zcra22":"38.72","zca3":"5227","zcra1_3":"8.04","zcra3":"10.01","buyi":"0","buyf":"242","moneyt":"2519","moneyy":"2554","stockt":"89","stocky":"96","zcra10":"8.32","zcra1_10":"8.94","id":"1319","name":"東陽","MA20":35.6575,"MA5":35.61,"MA10":35.515,"MA60":37.6267,"UB":36.9587,"LB":34.3563,"BLimitP":78.53,"UBSlopeP":-1.98,"signals":["gt-MA5","gt-MA10","gt-MA20"],"candlestick":[],"bandWidthP":7.57,"VMA30":1605.8054,"VLimitP":50.69,"change":1,"changePercent":2.82,"link":"https://histock.tw/stock/tv/tvchart.aspx?no=1319","link2":"https://invest.cnyes.com/twstock/TWS/1319/technical","buyiDays":"","buyfDays":""},{"dv":"27.45","deal":"5514","ep":"16.44","net":"0.73","zcra12":"2.15","zcra1_12":"2.41","zch4":"9.66","zch1_4":"1.51","type":"紡織用聚酯粒","zcj1":"26.9","zcra22":"52.9","zca3":"43949","zcra1_3":"6.47","zcra3":"5.5","buyi":"11","buyf":"-664","moneyt":"5384","moneyy":"5304","stockt":"198","stocky":"197","zcra10":"6.1","zcra1_10":"7.03","id":"1402","name":"遠東新","MA20":26.845,"MA5":27.3,"MA10":26.905,"MA60":27.63,"UB":27.7766,"LB":25.9134,"BLimitP":82.47,"UBSlopeP":-0.55,"signals":[],"candlestick":[],"bandWidthP":7.19,"VMA30":7973.0131,"VLimitP":26.83,"change":0.05,"changePercent":0.18,"link":"https://histock.tw/stock/tv/tvchart.aspx?no=1402","link2":"https://invest.cnyes.com/twstock/TWS/1402/technical","buyiDays":"+3","buyfDays":""},{"dv":"30.2","deal":"1870","ep":"13.67","net":"0.95","zcra12":"3.08","zcra1_12":"2.82","zch4":"-1.92","zch1_4":"-8.19","type":"尼龍","zcj1":"38.57","zcra22":"20.48","zca3":"6752","zcra1_3":"5.52","zcra3":"2.9","buyi":"0","buyf":"339","moneyt":"2275","moneyy":"2300","stockt":"18","stocky":"25","zcra10":"6.65","zcra1_10":"7.18","id":"1434","name":"福懋興","MA20":29.595,"MA5":29.84,"MA10":29.565,"MA60":30.3633,"UB":30.381,"LB":28.809,"BLimitP":88.49,"UBSlopeP":0.03,"signals":[],"candlestick":[],"bandWidthP":5.46,"VMA30":3124.4816,"VLimitP":27.87,"change":0.35,"changePercent":1.17,"link":"https://histock.tw/stock/tv/tvchart.aspx?no=1434","link2":"https://invest.cnyes.com/twstock/TWS/1434/technical","buyiDays":"","buyfDays":""},{"dv":"24.5","deal":"1188","ep":"15.51","net":"1.66","zcra12":"1.44","zcra1_12":"1.09","zch4":"4.01","zch1_4":"-0.53","type":"電機","zcj1":"15.59","zcra22":"46.53","zca3":"353","zcra1_3":"3.97","zcra3":"5.75","buyi":"0","buyf":"-51","moneyt":"2751","moneyy":"2762","stockt":"21","stocky":"25","zcra10":"9.93","zcra1_10":"7.47","id":"1514","name":"亞力","MA20":24.3075,"MA5":24.34,"MA10":24,"MA60":25.85,"UB":25.4979,"LB":23.1171,"BLimitP":58.09,"UBSlopeP":-1.1,"signals":[],"candlestick":[],"bandWidthP":10.3,"VMA30":1274.9973,"VLimitP":47.96,"change":0.05,"changePercent":0.2,"link":"https://histock.tw/stock/tv/tvchart.aspx?no=1514","link2":"https://invest.cnyes.com/twstock/TWS/1514/technical","buyiDays":"","buyfDays":""},{"dv":"10.6","deal":"1412","ep":"26.5","net":"0.8","zcra12":"0.84","zcra1_12":"1.09","zch4":"-0.09","zch1_4":"-17.46","type":"汽車鈑金","zcj1":"26.52","zcra22":"54.16","zca3":"375","zcra1_3":"9.71","zcra3":"9.01","buyi":"0","buyf":"-8","moneyt":"5132","moneyy":"5004","stockt":"0","stocky":"0","zcra10":"6.56","zcra1_10":"8.81","id":"1524","name":"耿鼎","MA20":10.79,"MA5":10.36,"MA10":10.41,"MA60":10.2963,"UB":11.7958,"LB":9.7842,"BLimitP":40.55,"UBSlopeP":-2.52,"signals":[],"candlestick":[],"bandWidthP":20.56,"VMA30":3995.5178,"VLimitP":39.74,"change":0.1,"changePercent":0.95,"link":"https://histock.tw/stock/tv/tvchart.aspx?no=1524","link2":"https://invest.cnyes.com/twstock/TWS/1524/technical","buyiDays":"","buyfDays":""},{"dv":"115","deal":"2749","ep":"49.15","net":"4.52","zcra12":"2.15","zcra1_12":"6.4","zch4":"66.04","zch1_4":"31.64","type":"微型線性滑軌廠","zcj1":"14.1","zcra22":"39.02","zca3":"165","zcra1_3":"29.1","zcra3":"18.57","buyi":"0","buyf":"154","moneyt":"2896","moneyy":"2981","stockt":"142","stocky":"152","zcra10":"8.82","zcra1_10":"27.2","id":"1597","name":"直得","MA20":104.705,"MA5":109.8,"MA10":106.26,"MA60":92.4267,"UB":120.0756,"LB":89.3344,"BLimitP":83.49,"UBSlopeP":0.99,"signals":[],"candlestick":[],"bandWidthP":34.41,"VMA30":4039510.1333,"VLimitP":41.59,"change":1.5,"changePercent":1.32,"link":"https://histock.tw/stock/tv/tvchart.aspx?no=1597","link2":"https://invest.cnyes.com/twstock/TWS/1597/technical","buyiDays":"","buyfDays":"+4"},{"dv":"35.2","deal":"2868","ep":"18.92","net":"2.04","zcra12":"1.99","zcra1_12":"1.25","zch4":"75.88","zch1_4":"18.08","type":"合成樹脂","zcj1":"17.69","zcra22":"59.25","zca3":"4946","zcra1_3":"4.19","zcra3":"5.79","buyi":"1","buyf":"-490","moneyt":"8499","moneyy":"8671","stockt":"179","stocky":"179","zcra10":"11.15","zcra1_10":"6.99","id":"1717","name":"長興","MA20":34.19,"MA5":34.66,"MA10":34.17,"MA60":35.4867,"UB":35.4122,"LB":32.9678,"BLimitP":91.32,"UBSlopeP":-0.81,"signals":[],"candlestick":[],"bandWidthP":7.41,"VMA30":4849.2468,"VLimitP":30.82,"change":0,"changePercent":0,"link":"https://histock.tw/stock/tv/tvchart.aspx?no=1717","link2":"https://invest.cnyes.com/twstock/TWS/1717/technical","buyiDays":"","buyfDays":""},{"dv":"31.1","deal":"3190","ep":"10.16","net":"1.42","zcra12":"2.08","zcra1_12":"3.38","zch4":"24.6","zch1_4":"-4.75","type":"工業用紙","zcj1":"12.09","zcra22":"56.93","zca3":"7322","zcra1_3":"6.94","zcra3":"8.7","buyi":"0","buyf":"-816","moneyt":"3396","moneyy":"3416","stockt":"207","stocky":"235","zcra10":"9.44","zcra1_10":"17.53","id":"1904","name":"正隆","MA20":29.965,"MA5":30.44,"MA10":29.755,"MA60":31.4042,"UB":31.5322,"LB":28.3978,"BLimitP":86.21,"UBSlopeP":-0.72,"signals":[],"candlestick":[],"bandWidthP":11.04,"VMA30":3961.7302,"VLimitP":39.64,"change":0.2,"changePercent":0.65,"link":"https://histock.tw/stock/tv/tvchart.aspx?no=1904","link2":"https://invest.cnyes.com/twstock/TWS/1904/technical","buyiDays":"","buyfDays":""},{"dv":"23.4","deal":"2430","ep":"22.08","net":"2.82","zcra12":"0.6","zcra1_12":"1.58","zch4":"62.31","zch1_4":"4","type":"鋼筋","zcj1":"13.22","zcra22":"60.07","zca3":"358","zcra1_3":"4.96","zcra3":"1.88","buyi":"0","buyf":"-59","moneyt":"0","moneyy":"0","stockt":"0","stocky":"0","zcra10":"8.35","zcra1_10":"24.6","id":"2028","name":"威致","MA20":20.8825,"MA5":21.87,"MA10":20.925,"MA60":20.8483,"UB":23.4153,"LB":18.3497,"BLimitP":99.7,"UBSlopeP":0.59,"signals":[],"candlestick":[],"bandWidthP":27.61,"VMA30":2841.2881,"VLimitP":46.4,"change":0.1,"changePercent":0.43,"link":"https://histock.tw/stock/tv/tvchart.aspx?no=2028","link2":"https://invest.cnyes.com/twstock/TWS/2028/technical","buyiDays":"","buyfDays":""},{"dv":"26.95","deal":"3255","ep":"24.95","net":"1.55","zcra12":"1.53","zcra1_12":"2.23","zch4":"-0.86","zch1_4":"-17.28","type":"不鏽鋼","zcj1":"16.91","zcra22":"38.66","zca3":"660","zcra1_3":"5.91","zcra3":"4.92","buyi":"0","buyf":"-346","moneyt":"5319","moneyy":"5659","stockt":"13","stocky":"14","zcra10":"8.14","zcra1_10":"11.79","id":"2034","name":"允強","MA20":25.425,"MA5":26.22,"MA10":25.695,"MA60":26.1892,"UB":26.6236,"LB":24.2264,"BLimitP":113.62,"UBSlopeP":0.77,"signals":[],"candlestick":[],"bandWidthP":9.89,"VMA30":4367.7009,"VLimitP":45.48,"change":0.3,"changePercent":1.13,"link":"https://histock.tw/stock/tv/tvchart.aspx?no=2034","link2":"https://invest.cnyes.com/twstock/TWS/2034/technical","buyiDays":"","buyfDays":""},{"dv":"62.6","deal":"9987","ep":"16.22","net":"3.49","zcra12":"2.9","zcra1_12":"3.12","zch4":"172.6","zch1_4":"131.64","type":"合成橡膠","zcj1":"39.25","zcra22":"18.04","zca3":"1982","zcra1_3":"14.05","zcra3":"15.97","buyi":"-2","buyf":"3778","moneyt":"6006","moneyy":"6157","stockt":"594","stocky":"495","zcra10":"17.39","zcra1_10":"20.56","id":"2108","name":"南帝","MA20":59.405,"MA5":59.58,"MA10":59.06,"MA60":60.015,"UB":62.4666,"LB":56.3434,"BLimitP":102.18,"UBSlopeP":0.76,"signals":["gt-UB","gt-MA5","gt-MA10","gt-MA20","gt-MA60"],"candlestick":[],"bandWidthP":10.87,"VMA30":4702.7843,"VLimitP":94.65,"change":3.8,"changePercent":6.46,"link":"https://histock.tw/stock/tv/tvchart.aspx?no=2108","link2":"https://invest.cnyes.com/twstock/TWS/2108/technical","buyiDays":"","buyfDays":""},{"dv":"47.85","deal":"4229","ep":"10.47","net":"1.59","zcra12":"4.09","zcra1_12":"3.96","zch4":"42.16","zch1_4":"13.43","type":"電腦通路商","zcj1":"19.18","zcra22":"64.83","zca3":"18812","zcra1_3":"1.41","zcra3":"1.76","buyi":"0","buyf":"599","moneyt":"1183","moneyy":"984","stockt":"7","stocky":"7","zcra10":"14.25","zcra1_10":"14.38","id":"2347","name":"聯強","MA20":46.8675,"MA5":47.32,"MA10":46.865,"MA60":46.0233,"UB":48.0613,"LB":45.6737,"BLimitP":91.15,"UBSlopeP":0.29,"signals":[],"candlestick":[],"bandWidthP":5.23,"VMA30":3442.3587,"VLimitP":70.16,"change":0.25,"changePercent":0.53,"link":"https://histock.tw/stock/tv/tvchart.aspx?no=2347","link2":"https://invest.cnyes.com/twstock/TWS/2347/technical","buyiDays":"","buyfDays":"+2"},{"dv":"29.3","deal":"13215","ep":"14.95","net":"1.66","zcra12":"1.82","zcra1_12":"2.05","zch4":"28.51","zch1_4":"33.66","type":"顯示器","zcj1":"17.59","zcra22":"64.69","zca3":"8475","zcra1_3":"2.94","zcra3":"3.67","buyi":"2","buyf":"205","moneyt":"20223","moneyy":"20005","stockt":"813","stocky":"830","zcra10":"10.03","zcra1_10":"11.5","id":"2352","name":"佳世達","MA20":28.25,"MA5":28.53,"MA10":28.705,"MA60":26.9325,"UB":30.1278,"LB":26.3722,"BLimitP":77.96,"UBSlopeP":0.38,"signals":["gt-MA10"],"candlestick":[],"bandWidthP":14.24,"VMA30":19367.3032,"VLimitP":32.63,"change":0.85,"changePercent":2.99,"link":"https://histock.tw/stock/tv/tvchart.aspx?no=2352","link2":"https://invest.cnyes.com/twstock/TWS/2352/technical","buyiDays":"+2","buyfDays":""},{"dv":"87.8","deal":"15782","ep":"15.24","net":"2.18","zcra12":"3.05","zcra1_12":"4.04","zch4":"66.05","zch1_4":"41.82","type":"主機板","zcj1":"10.8","zcra22":"35.42","zca3":"3886","zcra1_3":"3.74","zcra3":"2.34","buyi":"112","buyf":"600","moneyt":"10900","moneyy":"9685","stockt":"398","stocky":"362","zcra10":"7.86","zcra1_10":"10.31","id":"2376","name":"技嘉","MA20":80.04,"MA5":84.46,"MA10":81.22,"MA60":79.1033,"UB":86.3662,"LB":73.7138,"BLimitP":111.33,"UBSlopeP":1.7,"signals":["gt-UB"],"candlestick":[],"bandWidthP":17.16,"VMA30":7884.4435,"VLimitP":90.81,"change":2.8,"changePercent":3.29,"link":"https://histock.tw/stock/tv/tvchart.aspx?no=2376","link2":"https://invest.cnyes.com/twstock/TWS/2376/technical","buyiDays":"+4","buyfDays":""},{"dv":"147","deal":"12773","ep":"17.07","net":"3.73","zcra12":"6.61","zcra1_12":"7.15","zch4":"69.11","zch1_4":"37","type":"主機板","zcj1":"13.89","zcra22":"48.61","zca3":"9274","zcra1_3":"5.65","zcra3":"4.94","buyi":"10","buyf":"-124","moneyt":"3870","moneyy":"3372","stockt":"253","stocky":"187","zcra10":"18.33","zcra1_10":"20.92","id":"2377","name":"微星","MA20":134.925,"MA5":141,"MA10":136.9,"MA60":130.9,"UB":144.2216,"LB":125.6284,"BLimitP":114.94,"UBSlopeP":1.25,"signals":["gt-UB"],"candlestick":[],"bandWidthP":14.8,"VMA30":5370.1317,"VLimitP":108.77,"change":6,"changePercent":4.26,"link":"https://histock.tw/stock/tv/tvchart.aspx?no=2377","link2":"https://invest.cnyes.com/twstock/TWS/2377/technical","buyiDays":"+4","buyfDays":""},{"dv":"90.8","deal":"3621","ep":"11.66","net":"2.42","zcra12":"8.45","zcra1_12":"5.22","zch4":"47.88","zch1_4":"17.61","type":"中小尺吋面板","zcj1":"11.21","zcra22":"55.36","zca3":"11059","zcra1_3":"5.33","zcra3":"6.77","buyi":"-3","buyf":"548","moneyt":"1156","moneyy":"978","stockt":"23","stocky":"22","zcra10":"22.65","zcra1_10":"14.1","id":"2385","name":"群光","MA20":87.985,"MA5":88.62,"MA10":88.09,"MA60":86.82,"UB":90.1282,"LB":85.8418,"BLimitP":115.67,"UBSlopeP":0.61,"signals":["gt-UB"],"candlestick":[],"bandWidthP":4.99,"VMA30":2413.511,"VLimitP":89.11,"change":2.3,"changePercent":2.6,"link":"https://histock.tw/stock/tv/tvchart.aspx?no=2385","link2":"https://invest.cnyes.com/twstock/TWS/2385/technical","buyiDays":"","buyfDays":""},{"dv":"97.1","deal":"31073","ep":"37.06","net":"1.95","zcra12":"3.23","zcra1_12":"12.8","zch4":"22.93","zch1_4":"17.24","type":"DRAM","zcj1":"29.61","zcra22":"7.93","zca3":"17407","zcra1_3":"46.45","zcra3":"18.4","buyi":"1147","buyf":"2411","moneyt":"14642","moneyy":"15262","stockt":"3307","stocky":"3211","zcra10":"6.2","zcra1_10":"26.5","id":"2408","name":"南亞科","MA20":86.355,"MA5":91.32,"MA10":88.26,"MA60":84.58,"UB":94.2132,"LB":78.4968,"BLimitP":118.37,"UBSlopeP":2.01,"signals":[],"candlestick":[],"bandWidthP":20.02,"VMA30":20757.0014,"VLimitP":81.56,"change":4.1,"changePercent":4.41,"link":"https://histock.tw/stock/tv/tvchart.aspx?no=2408","link2":"https://invest.cnyes.com/twstock/TWS/2408/technical","buyiDays":"+10","buyfDays":"+2"},{"dv":"108.5","deal":"9460","ep":"25.53","net":"2.28","zcra12":"4.23","zcra1_12":"4.58","zch4":"2.53","zch1_4":"22.08","type":"電信數據服務","zcj1":"35.29","zcra22":"19.07","zca3":"72427","zcra1_3":"20.25","zcra3":"19.59","buyi":"12","buyf":"-3605","moneyt":"679","moneyy":"673","stockt":"2","stocky":"3","zcra10":"8.74","zcra1_10":"9.59","id":"2412","name":"中華電","MA20":109.025,"MA5":108.6,"MA10":108.6,"MA60":109.2583,"UB":110.7992,"LB":107.2508,"BLimitP":35.2,"UBSlopeP":-0.52,"signals":["lt-MA5","lt-MA10"],"candlestick":[],"bandWidthP":3.31,"VMA30":8931.1148,"VLimitP":55.11,"change":-0.5,"changePercent":-0.46,"link":"https://histock.tw/stock/tv/tvchart.aspx?no=2412","link2":"https://invest.cnyes.com/twstock/TWS/2412/technical","buyiDays":"+3","buyfDays":""},{"dv":"209.5","deal":"2590","ep":"21.55","net":"3.97","zcra12":"8.71","zcra1_12":"7.67","zch4":"54.53","zch1_4":"17.65","type":"熱敏電阻","zcj1":"21.26","zcra22":"25.55","zca3":"1647","zcra1_3":"23.01","zcra3":"24.92","buyi":"20","buyf":"-185","moneyt":"2228","moneyy":"2124","stockt":"132","stocky":"131","zcra10":"17.74","zcra1_10":"16.88","id":"2428","name":"興勤","MA20":187.575,"MA5":200.3,"MA10":189.9,"MA60":165.35,"UB":205.228,"LB":169.922,"BLimitP":112.1,"UBSlopeP":1.98,"signals":[],"candlestick":[],"bandWidthP":20.78,"VMA30":1847.6369,"VLimitP":70.99,"change":7.5,"changePercent":3.71,"link":"https://histock.tw/stock/tv/tvchart.aspx?no=2428","link2":"https://invest.cnyes.com/twstock/TWS/2428/technical","buyiDays":"","buyfDays":""},{"dv":"74.5","deal":"3632","ep":"17.61","net":"2.46","zcra12":"3.33","zcra1_12":"4.18","zch4":"37.97","zch1_4":"27.6","type":"IC封裝","zcj1":"43.93","zcra22":"14.66","zca3":"4161","zcra1_3":"22.81","zcra3":"19.44","buyi":"-10","buyf":"-1381","moneyt":"4527","moneyy":"4374","stockt":"77","stocky":"77","zcra10":"11.53","zcra1_10":"14.97","id":"2441","name":"超豐","MA20":68.105,"MA5":73.56,"MA10":69.47,"MA60":59.51,"UB":76.752,"LB":59.458,"BLimitP":86.98,"UBSlopeP":0.46,"signals":[],"candlestick":[],"bandWidthP":29.09,"VMA30":5239.0837,"VLimitP":41.19,"change":0.5,"changePercent":0.68,"link":"https://histock.tw/stock/tv/tvchart.aspx?no=2441","link2":"https://invest.cnyes.com/twstock/TWS/2441/technical","buyiDays":"","buyfDays":""},{"dv":"43.5","deal":"1372","ep":"17.61","net":"2.14","zcra12":"3.49","zcra1_12":"4.88","zch4":"8.61","zch1_4":"-10.87","type":"設備儀器廠商","zcj1":"13.52","zcra22":"64.49","zca3":"433","zcra1_3":"7.96","zcra3":"7.03","buyi":"0","buyf":"137","moneyt":"4608","moneyy":"4527","stockt":"14","stocky":"14","zcra10":"16.66","zcra1_10":"24.99","id":"2464","name":"盟立","MA20":42.505,"MA5":42.98,"MA10":42.205,"MA60":43.205,"UB":44.6094,"LB":40.4006,"BLimitP":73.64,"UBSlopeP":-0.77,"signals":[],"candlestick":[],"bandWidthP":10.42,"VMA30":2280.6793,"VLimitP":41.62,"change":0,"changePercent":0,"link":"https://histock.tw/stock/tv/tvchart.aspx?no=2464","link2":"https://invest.cnyes.com/twstock/TWS/2464/technical","buyiDays":"","buyfDays":"+9"},{"dv":"28","deal":"1189","ep":"13.59","net":"1.79","zcra12":"1.69","zcra1_12":"1.21","zch4":"39.51","zch1_4":"8.83","type":"軟體業","zcj1":"15.84","zcra22":"39.57","zca3":"167","zcra1_3":"6.38","zcra3":"11.94","buyi":"0","buyf":"122","moneyt":"1475","moneyy":"1518","stockt":"1","stocky":"1","zcra10":"10.91","zcra1_10":"7.92","id":"2471","name":"資通","MA20":26.845,"MA5":27.13,"MA10":26.55,"MA60":25.5083,"UB":29.0648,"LB":24.6252,"BLimitP":76.02,"UBSlopeP":0.47,"signals":[],"candlestick":[],"bandWidthP":18.03,"VMA30":1640.3694,"VLimitP":46.37,"change":0.3,"changePercent":1.08,"link":"https://histock.tw/stock/tv/tvchart.aspx?no=2471","link2":"https://invest.cnyes.com/twstock/TWS/2471/technical","buyiDays":"","buyfDays":"+4"},{"dv":"78.9","deal":"12280","ep":"15.78","net":"2.52","zcra12":"3.35","zcra1_12":"4.42","zch4":"54.59","zch1_4":"15.15","type":"鋁質電解電容","zcj1":"14.97","zcra22":"46","zca3":"1531","zcra1_3":"14.33","zcra3":"12.17","buyi":"0","buyf":"266","moneyt":"9177","moneyy":"7029","stockt":"769","stocky":"702","zcra10":"10.57","zcra1_10":"16.65","id":"2472","name":"立隆","MA20":69.675,"MA5":72.38,"MA10":69.72,"MA60":64.8467,"UB":75.1064,"LB":64.2436,"BLimitP":134.92,"UBSlopeP":3.14,"signals":["gt-UB"],"candlestick":[],"bandWidthP":16.91,"VMA30":6372.9854,"VLimitP":77.64,"change":7.1,"changePercent":9.89,"link":"https://histock.tw/stock/tv/tvchart.aspx?no=2472","link2":"https://invest.cnyes.com/twstock/TWS/2472/technical","buyiDays":"","buyfDays":""},{"dv":"86.4","deal":"6834","ep":"17.96","net":"2.2","zcra12":"2.3","zcra1_12":"7.26","zch4":"94.07","zch1_4":"27.97","type":"晶片電阻","zcj1":"14.19","zcra22":"31.24","zca3":"1322","zcra1_3":"26.38","zcra3":"12.23","buyi":"0","buyf":"-455","moneyt":"9402","moneyy":"9523","stockt":"608","stocky":"610","zcra10":"6.99","zcra1_10":"25.92","id":"2478","name":"大毅","MA20":82.195,"MA5":83.76,"MA10":81.08,"MA60":80.6517,"UB":88.2806,"LB":76.1094,"BLimitP":84.55,"UBSlopeP":-0.95,"signals":[],"candlestick":[],"bandWidthP":15.99,"VMA30":5223.1732,"VLimitP":58.81,"change":0.8,"changePercent":0.93,"link":"https://histock.tw/stock/tv/tvchart.aspx?no=2478","link2":"https://invest.cnyes.com/twstock/TWS/2478/technical","buyiDays":"","buyfDays":""},{"dv":"54.4","deal":"15503","ep":"21.42","net":"2.74","zcra12":"1.5","zcra1_12":"2.41","zch4":"48.02","zch1_4":"27.27","type":"二極體","zcj1":"18.17","zcra22":"58.67","zca3":"742","zcra1_3":"8.2","zcra3":"6.87","buyi":"0","buyf":"109","moneyt":"12192","moneyy":"11899","stockt":"1650","stocky":"1633","zcra10":"7.71","zcra1_10":"12.11","id":"2481","name":"強茂","MA20":51.8825,"MA5":52.12,"MA10":51.005,"MA60":49.06,"UB":55.5881,"LB":48.1769,"BLimitP":83.97,"UBSlopeP":0.16,"signals":[],"candlestick":[],"bandWidthP":15.38,"VMA30":15470.4097,"VLimitP":50.07,"change":1.3,"changePercent":2.45,"link":"https://histock.tw/stock/tv/tvchart.aspx?no=2481","link2":"https://invest.cnyes.com/twstock/TWS/2481/technical","buyiDays":"","buyfDays":"+4"},{"dv":"279","deal":"24139","ep":"22.2","net":"3.83","zcra12":"13.72","zcra1_12":"40.75","zch4":"84.22","zch1_4":"53.63","type":"MLCC","zcj1":"28.56","zcra22":"39.25","zca3":"13121","zcra1_3":"52.77","zcra3":"25.53","buyi":"20","buyf":"2361","moneyt":"13532","moneyy":"15041","stockt":"1843","stocky":"1655","zcra10":"19.17","zcra1_10":"72.81","id":"2492","name":"華新科","MA20":238.125,"MA5":259,"MA10":244.65,"MA60":224.7333,"UB":267.042,"LB":209.208,"BLimitP":120.68,"UBSlopeP":3.4,"signals":[],"candlestick":[],"bandWidthP":27.64,"VMA30":13529.6618,"VLimitP":84.84,"change":14,"changePercent":5.28,"link":"https://histock.tw/stock/tv/tvchart.aspx?no=2492","link2":"https://invest.cnyes.com/twstock/TWS/2492/technical","buyiDays":"+6","buyfDays":"+2"},{"dv":"35.15","deal":"5897","ep":"27.25","net":"1.3","zcra12":"1.92","zcra1_12":"1.97","zch4":"9.05","zch1_4":"-2.26","type":"散裝航運","zcj1":"40.44","zcra22":"56.88","zca3":"4518","zcra1_3":"11.57","zcra3":"14.46","buyi":"0","buyf":"651","moneyt":"7440","moneyy":"7725","stockt":"108","stocky":"111","zcra10":"6.18","zcra1_10":"7.03","id":"2606","name":"裕民","MA20":33.605,"MA5":34.24,"MA10":33.25,"MA60":33.5067,"UB":35.9806,"LB":31.2294,"BLimitP":82.52,"UBSlopeP":-0.99,"signals":[],"candlestick":[],"bandWidthP":15.21,"VMA30":8726.145,"VLimitP":37.42,"change":0,"changePercent":0,"link":"https://histock.tw/stock/tv/tvchart.aspx?no=2606","link2":"https://invest.cnyes.com/twstock/TWS/2606/technical","buyiDays":"","buyfDays":""},{"dv":"42.15","deal":"4779","ep":"11.87","net":"1.88","zcra12":"2.15","zcra1_12":"3.07","zch4":"126.13","zch1_4":"82.14","type":"倉儲貨櫃場","zcj1":"11.06","zcra22":"57.8","zca3":"802","zcra1_3":"3.26","zcra3":"2.64","buyi":"0","buyf":"1306","moneyt":"3083","moneyy":"3001","stockt":"53","stocky":"56","zcra10":"9.28","zcra1_10":"14.54","id":"2636","name":"台驊","MA20":38.975,"MA5":40.11,"MA10":39.15,"MA60":39.0575,"UB":41.062,"LB":36.888,"BLimitP":126.07,"UBSlopeP":1.51,"signals":[],"candlestick":[],"bandWidthP":11.32,"VMA30":1424.2771,"VLimitP":151.45,"change":2.2,"changePercent":5.51,"link":"https://histock.tw/stock/tv/tvchart.aspx?no=2636","link2":"https://invest.cnyes.com/twstock/TWS/2636/technical","buyiDays":"","buyfDays":"+5"},{"dv":"149.5","deal":"2740","ep":"32.43","net":"2.63","zcra12":"5.18","zcra1_12":"9.26","zch4":"-11.17","zch1_4":"-12.58","type":"85度C","zcj1":"45.74","zcra22":"54.82","zca3":"4546","zcra1_3":"9.48","zcra3":"7.37","buyi":"60","buyf":"357","moneyt":"1736","moneyy":"1665","stockt":"164","stocky":"153","zcra10":"9.03","zcra1_10":"16.27","id":"2723","name":"美食-KY","MA20":134.675,"MA5":139,"MA10":134,"MA60":143.3083,"UB":146.161,"LB":123.189,"BLimitP":114.54,"UBSlopeP":1.04,"signals":["gt-UB","gt-MA60"],"candlestick":[],"bandWidthP":18.65,"VMA30":1030.3375,"VLimitP":123.06,"change":11,"changePercent":7.94,"link":"https://histock.tw/stock/tv/tvchart.aspx?no=2723","link2":"https://invest.cnyes.com/twstock/TWS/2723/technical","buyiDays":"+2","buyfDays":""},{"dv":"51","deal":"3247","ep":"11.89","net":"1.96","zcra12":"3.67","zcra1_12":"3.83","zch4":"30.47","zch1_4":"23.44","type":"筆記型電腦製造","zcj1":"34.72","zcra22":"45.53","zca3":"3485","zcra1_3":"10.74","zcra3":"11.04","buyi":"0","buyf":"1060","moneyt":"3805","moneyy":"3730","stockt":"42","stocky":"26","zcra10":"14.37","zcra1_10":"15.43","id":"3005","name":"神基","MA20":48.3225,"MA5":49.18,"MA10":48.495,"MA60":48.4267,"UB":49.9333,"LB":46.7117,"BLimitP":133.11,"UBSlopeP":1.34,"signals":["gt-UB"],"candlestick":[],"bandWidthP":6.9,"VMA30":1211.95,"VLimitP":135.46,"change":1.5,"changePercent":3.03,"link":"https://histock.tw/stock/tv/tvchart.aspx?no=3005","link2":"https://invest.cnyes.com/twstock/TWS/3005/technical","buyiDays":"","buyfDays":"+4"},{"dv":"79.8","deal":"1572","ep":"10.68","net":"1.54","zcra12":"6.12","zcra1_12":"5.82","zch4":"36.8","zch1_4":"12.08","type":"IC零組件通路商","zcj1":"12.17","zcra22":"61.39","zca3":"1798","zcra1_3":"3.3","zcra3":"2.88","buyi":"0","buyf":"53","moneyt":"2031","moneyy":"2248","stockt":"21","stocky":"19","zcra10":"12.14","zcra1_10":"12.28","id":"3010","name":"華立","MA20":76.4,"MA5":78.46,"MA10":76.61,"MA60":76.205,"UB":81.528,"LB":71.272,"BLimitP":83.15,"UBSlopeP":0.46,"signals":[],"candlestick":[],"bandWidthP":14.39,"VMA30":1900.9328,"VLimitP":46.36,"change":0.5,"changePercent":0.63,"link":"https://histock.tw/stock/tv/tvchart.aspx?no=3010","link2":"https://invest.cnyes.com/twstock/TWS/3010/technical","buyiDays":"","buyfDays":""},{"dv":"91.5","deal":"16420","ep":"15.75","net":"3.06","zcra12":"3.38","zcra1_12":"3.08","zch4":"60.63","zch1_4":"54.31","type":"IO控制IC","zcj1":"10.46","zcra22":"24.67","zca3":"970","zcra1_3":"16.39","zcra3":"18.17","buyi":"0","buyf":"-479","moneyt":"9971","moneyy":"7756","stockt":"331","stocky":"175","zcra10":"13.62","zcra1_10":"12.61","id":"3014","name":"聯陽","MA20":76.42,"MA5":81.54,"MA10":76.92,"MA60":72.005,"UB":86.013,"LB":66.827,"BLimitP":128.6,"UBSlopeP":4.58,"signals":[],"candlestick":[],"bandWidthP":28.71,"VMA30":6127.3139,"VLimitP":97.37,"change":8.3,"changePercent":9.98,"link":"https://histock.tw/stock/tv/tvchart.aspx?no=3014","link2":"https://invest.cnyes.com/twstock/TWS/3014/technical","buyiDays":"","buyfDays":""},{"dv":"40.15","deal":"1574","ep":"10.82","net":"1.98","zcra12":"2.85","zcra1_12":"2.06","zch4":"24.84","zch1_4":"-6.54","type":"系統整合","zcj1":"11.14","zcra22":"53.57","zca3":"412","zcra1_3":"4.22","zcra3":"4.48","buyi":"0","buyf":"265","moneyt":"4457","moneyy":"4491","stockt":"19","stocky":"20","zcra10":"15.08","zcra1_10":"11.73","id":"3029","name":"零壹","MA20":38.6875,"MA5":39.13,"MA10":38.335,"MA60":38.725,"UB":40.6155,"LB":36.7595,"BLimitP":87.93,"UBSlopeP":0.33,"signals":[],"candlestick":[],"bandWidthP":10.49,"VMA30":1605.7179,"VLimitP":49.61,"change":0.2,"changePercent":0.5,"link":"https://histock.tw/stock/tv/tvchart.aspx?no=3029","link2":"https://invest.cnyes.com/twstock/TWS/3029/technical","buyiDays":"","buyfDays":""},{"dv":"19","deal":"1505","ep":"11.88","net":"1.5","zcra12":"1.73","zcra1_12":"0.71","zch4":"7.89","zch1_4":"6.92","type":"中小尺吋面板","zcj1":"19.11","zcra22":"46.33","zca3":"396","zcra1_3":"2.16","zcra3":"7.66","buyi":"1","buyf":"328","moneyt":"8460","moneyy":"8177","stockt":"35","stocky":"35","zcra10":"13.67","zcra1_10":"6.02","id":"3038","name":"全台","MA20":18.05,"MA5":18.6,"MA10":18.185,"MA60":18.5117,"UB":18.8362,"LB":17.2638,"BLimitP":110.42,"UBSlopeP":0.82,"signals":[],"candlestick":[],"bandWidthP":9.11,"VMA30":1226.6532,"VLimitP":54.83,"change":0.15,"changePercent":0.8,"link":"https://histock.tw/stock/tv/tvchart.aspx?no=3038","link2":"https://invest.cnyes.com/twstock/TWS/3038/technical","buyiDays":"","buyfDays":"+8"},{"dv":"131","deal":"1279","ep":"16.09","net":"1.67","zcra12":"7.25","zcra1_12":"6.67","zch4":"27.21","zch1_4":"9.92","type":"模具沖壓","zcj1":"14.21","zcra22":"31.14","zca3":"1730","zcra1_3":"15.63","zcra3":"16.31","buyi":"0","buyf":"-62","moneyt":"6450","moneyy":"6428","stockt":"33","stocky":"35","zcra10":"9.91","zcra1_10":"9.63","id":"3376","name":"新日興","MA20":126.975,"MA5":127.2,"MA10":125.65,"MA60":134.7667,"UB":131.53,"LB":122.42,"BLimitP":94.18,"UBSlopeP":-0.39,"signals":[],"candlestick":[],"bandWidthP":7.44,"VMA30":1044.443,"VLimitP":60.32,"change":3,"changePercent":2.34,"link":"https://histock.tw/stock/tv/tvchart.aspx?no=3376","link2":"https://invest.cnyes.com/twstock/TWS/3376/technical","buyiDays":"","buyfDays":""},{"dv":"120","deal":"1720","ep":"44.94","net":"4.46","zcra12":"2.01","zcra1_12":"2.17","zch4":"96.26","zch1_4":"49.05","type":"影像感測器廠","zcj1":"23.91","zcra22":"14.63","zca3":"129","zcra1_3":"8.85","zcra3":"6.8","buyi":"0","buyf":"-186","moneyt":"4647","moneyy":"4723","stockt":"120","stocky":"125","zcra10":"7.34","zcra1_10":"10.01","id":"3530","name":"晶相光","MA20":114.825,"MA5":116,"MA10":113.25,"MA60":123.1917,"UB":123.904,"LB":105.746,"BLimitP":78.5,"UBSlopeP":-1.83,"signals":[],"candlestick":[],"bandWidthP":17.17,"VMA30":3246.062,"VLimitP":39.22,"change":1,"changePercent":0.84,"link":"https://histock.tw/stock/tv/tvchart.aspx?no=3530","link2":"https://invest.cnyes.com/twstock/TWS/3530/technical","buyiDays":"","buyfDays":""},{"dv":"151","deal":"1686","ep":"49.35","net":"2.92","zcra12":"5.48","zcra1_12":"9.41","zch4":"10.73","zch1_4":"2.33","type":"矽晶圓","zcj1":"74.63","zcra22":"10.61","zca3":"4364","zcra1_3":"37.78","zcra3":"22.51","buyi":"0","buyf":"379","moneyt":"2418","moneyy":"2533","stockt":"95","stocky":"102","zcra10":"10.08","zcra1_10":"25.69","id":"3532","name":"台勝科","MA20":139.2,"MA5":143.2,"MA10":136.05,"MA60":138.4167,"UB":155.5566,"LB":122.8434,"BLimitP":86.07,"UBSlopeP":0.59,"signals":[],"candlestick":[],"bandWidthP":26.63,"VMA30":1619.3183,"VLimitP":51.52,"change":1,"changePercent":0.67,"link":"https://histock.tw/stock/tv/tvchart.aspx?no=3532","link2":"https://invest.cnyes.com/twstock/TWS/3532/technical","buyiDays":"","buyfDays":""},{"dv":"96.8","deal":"3381","ep":"13.87","net":"1.82","zcra12":"6.85","zcra1_12":"4.61","zch4":"22.31","zch1_4":"9.86","type":"無線網路設備系統","zcj1":"19.9","zcra22":"55.58","zca3":"2497","zcra1_3":"3.65","zcra3":"5.25","buyi":"-62","buyf":"-192","moneyt":"7852","moneyy":"7312","stockt":"439","stocky":"450","zcra10":"13.04","zcra1_10":"9.57","id":"3596","name":"智易","MA20":93.76,"MA5":95.86,"MA10":94.87,"MA60":95.3633,"UB":97.2232,"LB":90.2968,"BLimitP":93.89,"UBSlopeP":0.37,"signals":[],"candlestick":[],"bandWidthP":7.67,"VMA30":2353.4649,"VLimitP":69.57,"change":0.4,"changePercent":0.41,"link":"https://histock.tw/stock/tv/tvchart.aspx?no=3596","link2":"https://invest.cnyes.com/twstock/TWS/3596/technical","buyiDays":"","buyfDays":""},{"dv":"30.25","deal":"8865","ep":"12.2","net":"0.88","zcra12":"2.65","zcra1_12":"3.58","zch4":"13.38","zch1_4":"10.02","type":"雲端","zcj1":"18.14","zcra22":"28.61","zca3":"233","zcra1_3":"1.09","zcra3":"1.4","buyi":"1","buyf":"239","moneyt":"11760","moneyy":"10097","stockt":"23","stocky":"21","zcra10":"7.17","zcra1_10":"9.09","id":"3706","name":"神達","MA20":29.4525,"MA5":29.69,"MA10":29.425,"MA60":29.595,"UB":30.1001,"LB":28.8049,"BLimitP":111.57,"UBSlopeP":0.18,"signals":["gt-UB"],"candlestick":[],"bandWidthP":4.5,"VMA30":4973.2455,"VLimitP":94.72,"change":0.35,"changePercent":1.17,"link":"https://histock.tw/stock/tv/tvchart.aspx?no=3706","link2":"https://invest.cnyes.com/twstock/TWS/3706/technical","buyiDays":"+3","buyfDays":"+3"},{"dv":"155.5","deal":"3102","ep":"16.28","net":"2.81","zcra12":"8.97","zcra1_12":"11.22","zch4":"193.74","zch1_4":"58.22","type":"化工","zcj1":"14.46","zcra22":"42.46","zca3":"553","zcra1_3":"4.37","zcra3":"4.38","buyi":"100","buyf":"-38","moneyt":"5823","moneyy":"5482","stockt":"511","stocky":"589","zcra10":"7.45","zcra1_10":"20.94","id":"3708","name":"上緯投控","MA20":141.2,"MA5":147.7,"MA10":144.1,"MA60":150.25,"UB":152.0278,"LB":130.3722,"BLimitP":116.03,"UBSlopeP":1.97,"signals":["gt-UB"],"candlestick":[],"bandWidthP":16.61,"VMA30":2211.7704,"VLimitP":68.65,"change":6,"changePercent":4.01,"link":"https://histock.tw/stock/tv/tvchart.aspx?no=3708","link2":"https://invest.cnyes.com/twstock/TWS/3708/technical","buyiDays":"+2","buyfDays":""},{"dv":"112","deal":"44979","ep":"19.96","net":"2.32","zcra12":"3.96","zcra1_12":"5.95","zch4":"30.34","zch1_4":"29.69","type":"半導體","zcj1":"15.77","zcra22":"61.49","zca3":"72303","zcra1_3":"7.18","zcra3":"5.69","buyi":"-844","buyf":"-1276","moneyt":"26360","moneyy":"25485","stockt":"2029","stocky":"2229","zcra10":"8.3","zcra1_10":"8.42","id":"3711","name":"日月光投控","MA20":102.9,"MA5":112.9,"MA10":104.58,"MA60":88.13,"UB":117.05,"LB":88.75,"BLimitP":82.16,"UBSlopeP":1.03,"signals":["lt-MA5"],"candlestick":[],"bandWidthP":31.89,"VMA30":44853.2714,"VLimitP":50.18,"change":-1.5,"changePercent":-1.32,"link":"https://histock.tw/stock/tv/tvchart.aspx?no=3711","link2":"https://invest.cnyes.com/twstock/TWS/3711/technical","buyiDays":"","buyfDays":""},{"dv":"96","deal":"1267","ep":"10.48","net":"2.1","zcra12":"7.19","zcra1_12":"5.63","zch4":"-58.11","zch1_4":"-46.51","type":"西藥","zcj1":"31.75","zcra22":"14.87","zca3":"792","zcra1_3":"26.58","zcra3":"29.59","buyi":"0","buyf":"-83","moneyt":"1492","moneyy":"1524","stockt":"281","stocky":"280","zcra10":"17.09","zcra1_10":"14.57","id":"4119","name":"旭富","MA20":93.325,"MA5":92.34,"MA10":91.3,"MA60":104.1867,"UB":99.6352,"LB":87.0148,"BLimitP":71.2,"UBSlopeP":-2.81,"signals":[],"candlestick":[],"bandWidthP":14.5,"VMA30":1514.528,"VLimitP":44.78,"change":2.4,"changePercent":2.56,"link":"https://histock.tw/stock/tv/tvchart.aspx?no=4119","link2":"https://invest.cnyes.com/twstock/TWS/4119/technical","buyiDays":"","buyfDays":""},{"dv":"40.15","deal":"13962","ep":"28.68","net":"1.7","zcra12":"2.8","zcra1_12":"3.24","zch4":"75.46","zch1_4":"41.7","type":"汽車零組件","zcj1":"17.16","zcra22":"44.69","zca3":"846","zcra1_3":"24.38","zcra3":"24.37","buyi":"0","buyf":"-760","moneyt":"6404","moneyy":"4870","stockt":"37","stocky":"13","zcra10":"12.04","zcra1_10":"14.41","id":"4564","name":"元翎","MA20":32.3875,"MA5":34.84,"MA10":33.185,"MA60":31.0325,"UB":36.8449,"LB":27.9301,"BLimitP":137.07,"UBSlopeP":6.16,"signals":[],"candlestick":[],"bandWidthP":31.92,"VMA30":2022.2119,"VLimitP":155.43,"change":3.65,"changePercent":10,"link":"https://histock.tw/stock/tv/tvchart.aspx?no=4564","link2":"https://invest.cnyes.com/twstock/TWS/4564/technical","buyiDays":"","buyfDays":""},{"dv":"69.5","deal":"3507","ep":"50","net":"2.18","zcra12":"3.29","zcra1_12":"3.33","zch4":"39.12","zch1_4":"11.82","type":"精密機械加工","zcj1":"34.6","zcra22":"55.64","zca3":"485","zcra1_3":"4.23","zcra3":"5.38","buyi":"0","buyf":"-18","moneyt":"2634","moneyy":"2747","stockt":"1572","stocky":"1468","zcra10":"10.2","zcra1_10":"11.6","id":"4566","name":"時碩工業","MA20":61.55,"MA5":64.72,"MA10":62.45,"MA60":50.9633,"UB":70.694,"LB":52.406,"BLimitP":93.47,"UBSlopeP":1.77,"signals":["lt-UB"],"candlestick":[],"bandWidthP":34.9,"VMA30":2756.9393,"VLimitP":56.22,"change":0.2,"changePercent":0.29,"link":"https://histock.tw/stock/tv/tvchart.aspx?no=4566","link2":"https://invest.cnyes.com/twstock/TWS/4566/technical","buyiDays":"","buyfDays":""},{"dv":"60","deal":"4342","ep":"22.73","net":"2.99","zcra12":"2.68","zcra1_12":"2.88","zch4":"8.76","zch1_4":"14.1","type":"電信數據服務","zcj1":"32.94","zcra22":"47.37","zca3":"21474","zcra1_3":"14.28","zcra3":"14.22","buyi":"5","buyf":"-1343","moneyt":"910","moneyy":"880","stockt":"2","stocky":"0","zcra10":"12.18","zcra1_10":"13.05","id":"4904","name":"遠傳","MA20":60.365,"MA5":60.14,"MA10":60.07,"MA60":60.945,"UB":61.1952,"LB":59.5348,"BLimitP":28.02,"UBSlopeP":-0.67,"signals":[],"candlestick":[],"bandWidthP":2.79,"VMA30":3861.5984,"VLimitP":59.61,"change":0,"changePercent":0,"link":"https://histock.tw/stock/tv/tvchart.aspx?no=4904","link2":"https://invest.cnyes.com/twstock/TWS/4904/technical","buyiDays":"+2","buyfDays":""},{"dv":"47.45","deal":"17039","ep":"33.42","net":"1.55","zcra12":"2.53","zcra1_12":"3.42","zch4":"358.11","zch1_4":"263.18","type":"半導體","zcj1":"58.14","zcra22":"33.74","zca3":"775","zcra1_3":"7.52","zcra3":"5.64","buyi":"0","buyf":"-3020","moneyt":"11795","moneyy":"11042","stockt":"2691","stocky":"2472","zcra10":"10.04","zcra1_10":"19.21","id":"4919","name":"新唐","MA20":45.09,"MA5":46.42,"MA10":44.91,"MA60":45.9125,"UB":47.9456,"LB":42.2344,"BLimitP":91.32,"UBSlopeP":-0.37,"signals":["lt-UB"],"candlestick":[],"bandWidthP":13.52,"VMA30":6292.5093,"VLimitP":116.12,"change":0,"changePercent":0,"link":"https://histock.tw/stock/tv/tvchart.aspx?no=4919","link2":"https://invest.cnyes.com/twstock/TWS/4919/technical","buyiDays":"","buyfDays":""},{"dv":"47.9","deal":"3920","ep":"23.14","net":"2.59","zcra12":"2.05","zcra1_12":"2.61","zch4":"100.07","zch1_4":"57.97","type":"消費性IC設計","zcj1":"35.94","zcra22":"25.64","zca3":"334","zcra1_3":"10.56","zcra3":"8.46","buyi":"0","buyf":"-827","moneyt":"2346","moneyy":"2196","stockt":"16","stocky":"21","zcra10":"10.9","zcra1_10":"13.47","id":"4952","name":"凌通","MA20":42.28,"MA5":45.02,"MA10":43.265,"MA60":41.0267,"UB":46.4012,"LB":38.1588,"BLimitP":118.18,"UBSlopeP":2.45,"signals":[],"candlestick":[],"bandWidthP":21.6,"VMA30":2236.6927,"VLimitP":76.47,"change":0.7,"changePercent":1.48,"link":"https://histock.tw/stock/tv/tvchart.aspx?no=4952","link2":"https://invest.cnyes.com/twstock/TWS/4952/technical","buyiDays":"","buyfDays":""},{"dv":"120","deal":"5364","ep":"14.51","net":"1.61","zcra12":"9.93","zcra1_12":"10.5","zch4":"54.14","zch1_4":"68.76","type":"PCB","zcj1":"32.7","zcra22":"35.41","zca3":"16273","zcra1_3":"12.59","zcra3":"12.33","buyi":"-1","buyf":"-1165","moneyt":"12427","moneyy":"12627","stockt":"142","stocky":"140","zcra10":"14.72","zcra1_10":"17.3","id":"4958","name":"臻鼎-KY","MA20":116.725,"MA5":118,"MA10":116.05,"MA60":118.3083,"UB":121.7298,"LB":111.7202,"BLimitP":82.72,"UBSlopeP":-0.35,"signals":[],"candlestick":[],"bandWidthP":8.96,"VMA30":9199.1571,"VLimitP":25.07,"change":-0.5,"changePercent":-0.41,"link":"https://histock.tw/stock/tv/tvchart.aspx?no=4958","link2":"https://invest.cnyes.com/twstock/TWS/4958/technical","buyiDays":"","buyfDays":""},{"dv":"67.5","deal":"13656","ep":"25.86","net":"2.01","zcra12":"2.96","zcra1_12":"2.14","zch4":"26.11","zch1_4":"25","type":"電視機構件","zcj1":"35.6","zcra22":"34.48","zca3":"2022","zcra1_3":"4.14","zcra3":"6.47","buyi":"-165","buyf":"-188","moneyt":"9409","moneyy":"8944","stockt":"543","stocky":"501","zcra10":"8.53","zcra1_10":"6.36","id":"5243","name":"乙盛-KY","MA20":65.455,"MA5":64.72,"MA10":64.25,"MA60":56.1392,"UB":69.7708,"LB":61.1392,"BLimitP":73.69,"UBSlopeP":-1.28,"signals":[],"candlestick":[],"bandWidthP":14.12,"VMA30":17403.0024,"VLimitP":41.95,"change":1.3,"changePercent":1.96,"link":"https://histock.tw/stock/tv/tvchart.aspx?no=5243","link2":"https://invest.cnyes.com/twstock/TWS/5243/technical","buyiDays":"","buyfDays":""},{"dv":"44.8","deal":"8913","ep":"8.15","net":"0.99","zcra12":"6.05","zcra1_12":"3.55","zch4":"42.2","zch1_4":"18.47","type":"印刷電路板","zcj1":"25.96","zcra22":"49.54","zca3":"7542","zcra1_3":"5.3","zcra3":"8.2","buyi":"0","buyf":"-491","moneyt":"24389","moneyy":"23958","stockt":"194","stocky":"194","zcra10":"10.23","zcra1_10":"6.82","id":"5469","name":"瀚宇博","MA20":42.5275,"MA5":43.61,"MA10":42.765,"MA60":43.6767,"UB":44.4319,"LB":40.6231,"BLimitP":109.66,"UBSlopeP":0.19,"signals":[],"candlestick":[],"bandWidthP":9.38,"VMA30":3899.5845,"VLimitP":126.76,"change":0.6,"changePercent":1.36,"link":"https://histock.tw/stock/tv/tvchart.aspx?no=5469","link2":"https://invest.cnyes.com/twstock/TWS/5469/technical","buyiDays":"","buyfDays":""},{"dv":"87.6","deal":"34458","ep":"17.31","net":"4.2","zcra12":"2.03","zcra1_12":"2.02","zch4":"198","zch1_4":"81.86","type":"消費性IC","zcj1":"11.44","zcra22":"17.23","zca3":"364","zcra1_3":"8.95","zcra3":"11.2","buyi":"0","buyf":"-2975","moneyt":"11534","moneyy":"12461","stockt":"969","stocky":"1350","zcra10":"11.44","zcra1_10":"11.49","id":"5471","name":"松翰","MA20":71.49,"MA5":80.2,"MA10":73.93,"MA60":67.92,"UB":84.6484,"LB":58.3316,"BLimitP":111.22,"UBSlopeP":3.88,"signals":[],"candlestick":[],"bandWidthP":45.12,"VMA30":11417.4877,"VLimitP":94.26,"change":-0.2,"changePercent":-0.23,"link":"https://histock.tw/stock/tv/tvchart.aspx?no=5471","link2":"https://invest.cnyes.com/twstock/TWS/5471/technical","buyiDays":"","buyfDays":""},{"dv":"133.5","deal":"6099","ep":"27.81","net":"5.07","zcra12":"4.6","zcra1_12":"4.38","zch4":"59.08","zch1_4":"23.59","type":"熱敏電阻","zcj1":"22.6","zcra22":"27.24","zca3":"505","zcra1_3":"24.03","zcra3":"24.55","buyi":"200","buyf":"-614","moneyt":"4296","moneyy":"4349","stockt":"95","stocky":"117","zcra10":"17.17","zcra1_10":"16.84","id":"6224","name":"聚鼎","MA20":107.785,"MA5":122.3,"MA10":110.47,"MA60":99.1467,"UB":128.0078,"LB":87.5622,"BLimitP":113.58,"UBSlopeP":3.6,"signals":[],"candlestick":[],"bandWidthP":46.19,"VMA30":2330.5257,"VLimitP":101.08,"change":5,"changePercent":3.89,"link":"https://histock.tw/stock/tv/tvchart.aspx?no=6224","link2":"https://invest.cnyes.com/twstock/TWS/6224/technical","buyiDays":"","buyfDays":""},{"dv":"232","deal":"8233","ep":"34.37","net":"2","zcra12":"4.49","zcra1_12":"6.13","zch4":"60.29","zch1_4":"62.3","type":"IC封裝","zcj1":"12.05","zcra22":"18.08","zca3":"1882","zcra1_3":"15.36","zcra3":"12.27","buyi":"-25","buyf":"1","moneyt":"12661","moneyy":"12307","stockt":"239","stocky":"229","zcra10":"7.19","zcra1_10":"9.72","id":"6271","name":"同欣電","MA20":219.6,"MA5":222.7,"MA10":214.45,"MA60":195.1333,"UB":240.0856,"LB":199.1144,"BLimitP":80.27,"UBSlopeP":0.45,"signals":[],"candlestick":[],"bandWidthP":20.58,"VMA30":9457.3573,"VLimitP":44.7,"change":8,"changePercent":3.57,"link":"https://histock.tw/stock/tv/tvchart.aspx?no=6271","link2":"https://invest.cnyes.com/twstock/TWS/6271/technical","buyiDays":"","buyfDays":""},{"dv":"30.1","deal":"16924","ep":"10.79","net":"1.54","zcra12":"2.87","zcra1_12":"1.95","zch4":"-12.51","zch1_4":"19.86","type":"電源供應器","zcj1":"23.61","zcra22":"55.92","zca3":"957","zcra1_3":"0.13","zcra3":"0.42","buyi":"0","buyf":"-1620","moneyt":"10819","moneyy":"10966","stockt":"275","stocky":"265","zcra10":"17.73","zcra1_10":"12.55","id":"6282","name":"康舒","MA20":28.79,"MA5":29.36,"MA10":28.87,"MA60":28.845,"UB":29.898,"LB":27.682,"BLimitP":109.12,"UBSlopeP":0.46,"signals":[],"candlestick":[],"bandWidthP":8.01,"VMA30":8440.6975,"VLimitP":74.31,"change":0.35,"changePercent":1.18,"link":"https://histock.tw/stock/tv/tvchart.aspx?no=6282","link2":"https://invest.cnyes.com/twstock/TWS/6282/technical","buyiDays":"","buyfDays":""},{"dv":"78.6","deal":"2360","ep":"22.27","net":"1.92","zcra12":"3.76","zcra1_12":"5.21","zch4":"10.28","zch1_4":"8.93","type":"手機製造","zcj1":"24.66","zcra22":"53.06","zca3":"4602","zcra1_3":"3.6","zcra3":"2.56","buyi":"0","buyf":"203","moneyt":"9478","moneyy":"9579","stockt":"176","stocky":"178","zcra10":"9.13","zcra1_10":"12.83","id":"6285","name":"啟碁","MA20":76.45,"MA5":77.92,"MA10":76.72,"MA60":78.5617,"UB":79.0802,"LB":73.8198,"BLimitP":90.87,"UBSlopeP":0,"signals":["lt-UB"],"candlestick":[],"bandWidthP":7.13,"VMA30":3540.9737,"VLimitP":38.22,"change":-0.4,"changePercent":-0.51,"link":"https://histock.tw/stock/tv/tvchart.aspx?no=6285","link2":"https://invest.cnyes.com/twstock/TWS/6285/technical","buyiDays":"","buyfDays":""},{"dv":"33","deal":"4040","ep":"35.11","net":"2.38","zcra12":"1.21","zcra1_12":"0.91","zch4":"0.59","zch1_4":"-9.25","type":"汽車零組件","zcj1":"24.78","zcra22":"52.52","zca3":"589","zcra1_3":"5.05","zcra3":"5.94","buyi":"0","buyf":"24","moneyt":"8232","moneyy":"8374","stockt":"697","stocky":"706","zcra10":"9","zcra1_10":"7.45","id":"6288","name":"聯嘉","MA20":31.9175,"MA5":31.82,"MA10":31.525,"MA60":32.8217,"UB":33.3473,"LB":30.4877,"BLimitP":87.85,"UBSlopeP":-0.42,"signals":[],"candlestick":[],"bandWidthP":9.38,"VMA30":4701.7493,"VLimitP":47.37,"change":0.65,"changePercent":2.01,"link":"https://histock.tw/stock/tv/tvchart.aspx?no=6288","link2":"https://invest.cnyes.com/twstock/TWS/6288/technical","buyiDays":"","buyfDays":"+4"},{"dv":"58.8","deal":"1336","ep":"20.56","net":"2.43","zcra12":"1.66","zcra1_12":"2.24","zch4":"56.97","zch1_4":"21.98","type":"固態電容廠","zcj1":"22.77","zcra22":"46.23","zca3":"393","zcra1_3":"12.92","zcra3":"10.39","buyi":"40","buyf":"76","moneyt":"2671","moneyy":"2717","stockt":"72","stocky":"73","zcra10":"7.11","zcra1_10":"10.64","id":"6449","name":"鈺邦","MA20":54.725,"MA5":56.22,"MA10":54.39,"MA60":55.515,"UB":59.0004,"LB":50.4496,"BLimitP":97.66,"UBSlopeP":-0.39,"signals":[],"candlestick":[],"bandWidthP":16.95,"VMA30":1512.6249,"VLimitP":47.48,"change":1.2,"changePercent":2.08,"link":"https://histock.tw/stock/tv/tvchart.aspx?no=6449","link2":"https://invest.cnyes.com/twstock/TWS/6449/technical","buyiDays":"","buyfDays":"+5"},{"dv":"63","deal":"5195","ep":"24.42","net":"2.96","zcra12":"2.21","zcra1_12":"2.42","zch4":"-1.7","zch1_4":"-57.77","type":"太陽能","zcj1":"19.91","zcra22":"57.85","zca3":"84","zcra1_3":"17.33","zcra3":"17.32","buyi":"0","buyf":"144","moneyt":"17164","moneyy":"17499","stockt":"2114","stocky":"2089","zcra10":"11.45","zcra1_10":"14.42","id":"6477","name":"安集","MA20":60.08,"MA5":60.58,"MA10":58.86,"MA60":63.1233,"UB":64.387,"LB":55.773,"BLimitP":83.9,"UBSlopeP":-0.22,"signals":[],"candlestick":[],"bandWidthP":15.44,"VMA30":6511.4606,"VLimitP":42.77,"change":1.1,"changePercent":1.78,"link":"https://histock.tw/stock/tv/tvchart.aspx?no=6477","link2":"https://invest.cnyes.com/twstock/TWS/6477/technical","buyiDays":"","buyfDays":""},{"dv":"82","deal":"2939","ep":"16.08","net":"2.89","zcra12":"5.15","zcra1_12":"6.6","zch4":"61.17","zch1_4":"12.4","type":"封測廠","zcj1":"51.52","zcra22":"23.3","zca3":"1036","zcra1_3":"22.18","zcra3":"22.96","buyi":"79","buyf":"98","moneyt":"3895","moneyy":"3943","stockt":"12","stocky":"12","zcra10":"18.7","zcra1_10":"23.7","id":"6525","name":"捷敏-KY","MA20":71.06,"MA5":76.62,"MA10":72.05,"MA60":66.4383,"UB":80.4696,"LB":61.6504,"BLimitP":108.13,"UBSlopeP":2.58,"signals":[],"candlestick":[],"bandWidthP":30.53,"VMA30":1734.3294,"VLimitP":70.51,"change":-0.3,"changePercent":-0.36,"link":"https://histock.tw/stock/tv/tvchart.aspx?no=6525","link2":"https://invest.cnyes.com/twstock/TWS/6525/technical","buyiDays":"+4","buyfDays":""},{"dv":"88.4","deal":"2600","ep":"15.48","net":"2.74","zcra12":"6.85","zcra1_12":"6.75","zch4":"17.91","zch1_4":"-2.29","type":"利基型銅箔基板供應商","zcj1":"14.22","zcra22":"44.11","zca3":"670","zcra1_3":"9","zcra3":"11.4","buyi":"0","buyf":"121","moneyt":"3412","moneyy":"3518","stockt":"68","stocky":"61","zcra10":"22.92","zcra1_10":"27.9","id":"6672","name":"騰輝電子-KY","MA20":78.045,"MA5":85.74,"MA10":82.91,"MA60":71.905,"UB":92.4108,"LB":63.6792,"BLimitP":86.04,"UBSlopeP":1.3,"signals":[],"candlestick":[],"bandWidthP":45.12,"VMA30":2278.5121,"VLimitP":53.7,"change":1.4,"changePercent":1.61,"link":"https://histock.tw/stock/tv/tvchart.aspx?no=6672","link2":"https://invest.cnyes.com/twstock/TWS/6672/technical","buyiDays":"","buyfDays":"+3"},{"dv":"52.9","deal":"1253","ep":"15.24","net":"1.52","zcra12":"3.02","zcra1_12":"3.22","zch4":"44.22","zch1_4":"18.46","type":"軟板基板","zcj1":"10.8","zcra22":"35.36","zca3":"1994","zcra1_3":"10.05","zcra3":"9.77","buyi":"-556","buyf":"458","moneyt":"3773","moneyy":"3645","stockt":"72","stocky":"65","zcra10":"8.39","zcra1_10":"9.29","id":"8039","name":"台虹","MA20":52.665,"MA5":52.56,"MA10":52.05,"MA60":54.2467,"UB":54.7282,"LB":50.6018,"BLimitP":55.7,"UBSlopeP":-0.46,"signals":[],"candlestick":[],"bandWidthP":8.15,"VMA30":1010.9046,"VLimitP":60.24,"change":0.3,"changePercent":0.57,"link":"https://histock.tw/stock/tv/tvchart.aspx?no=8039","link2":"https://invest.cnyes.com/twstock/TWS/8039/technical","buyiDays":"","buyfDays":""},{"dv":"39","deal":"25472","ep":"25.32","net":"4.33","zcra12":"17.19","zcra1_12":"13.47","zch4":"36.63","zch1_4":"11.26","type":"IC零組件通路商","zcj1":"37.99","zcra22":"55.33","zca3":"2016","zcra1_3":"8.82","zcra3":"7.09","buyi":"0","buyf":"-1626","moneyt":"10688","moneyy":"11421","stockt":"10144","stocky":"8620","zcra10":"17.35","zcra1_10":"15.74","id":"8070","name":"長華","MA20":32.2775,"MA5":36.79,"MA10":33.545,"MA60":30.41,"UB":38.5865,"LB":25.9685,"BLimitP":103.28,"UBSlopeP":3.2,"signals":[],"candlestick":[],"bandWidthP":48.59,"VMA30":9732.0967,"VLimitP":87.18,"change":-1.7,"changePercent":-4.18,"link":"https://histock.tw/stock/tv/tvchart.aspx?no=8070","link2":"https://invest.cnyes.com/twstock/TWS/8070/technical","buyiDays":"","buyfDays":""},{"dv":"200","deal":"1642","ep":"17.86","net":"3.97","zcra12":"8.74","zcra1_12":"5.53","zch4":"68.02","zch1_4":"29.11","type":"類比IC","zcj1":"10.6","zcra22":"30.86","zca3":"1122","zcra1_3":"11.32","zcra3":"14.98","buyi":"0","buyf":"-194","moneyt":"2696","moneyy":"2685","stockt":"59","stocky":"54","zcra10":"16.85","zcra1_10":"12.16","id":"8081","name":"致新","MA20":181.725,"MA5":193.9,"MA10":184.4,"MA60":170.225,"UB":200.6234,"LB":162.8266,"BLimitP":98.35,"UBSlopeP":1.53,"signals":[],"candlestick":[],"bandWidthP":23.21,"VMA30":1970.1367,"VLimitP":45.11,"change":3,"changePercent":1.52,"link":"https://histock.tw/stock/tv/tvchart.aspx?no=8081","link2":"https://invest.cnyes.com/twstock/TWS/8081/technical","buyiDays":"","buyfDays":""},{"dv":"37.75","deal":"3410","ep":"15.22","net":"1.18","zcra12":"2.16","zcra1_12":"2.51","zch4":"99.92","zch1_4":"18.71","type":"連接器","zcj1":"11.71","zcra22":"41.44","zca3":"510","zcra1_3":"8.69","zcra3":"9.06","buyi":"0","buyf":"508","moneyt":"3860","moneyy":"3447","stockt":"70","stocky":"131","zcra10":"6.98","zcra1_10":"8.25","id":"8103","name":"瀚荃","MA20":34.085,"MA5":35.62,"MA10":34.035,"MA60":34.03,"UB":37.1654,"LB":31.0046,"BLimitP":109.49,"UBSlopeP":1.41,"signals":["gt-UB"],"candlestick":[],"bandWidthP":19.87,"VMA30":1686.9001,"VLimitP":71.89,"change":0.7,"changePercent":1.89,"link":"https://histock.tw/stock/tv/tvchart.aspx?no=8103","link2":"https://invest.cnyes.com/twstock/TWS/8103/technical","buyiDays":"","buyfDays":"+4"},{"dv":"37.25","deal":"13962","ep":"12.25","net":"1.35","zcra12":"3.55","zcra1_12":"1.37","zch4":"24.87","zch1_4":"20.12","type":"IC封測","zcj1":"11.75","zcra22":"42.72","zca3":"5993","zcra1_3":"11.36","zcra3":"12.08","buyi":"0","buyf":"-1612","moneyt":"12962","moneyy":"12925","stockt":"164","stocky":"169","zcra10":"13.7","zcra1_10":"6.05","id":"8150","name":"南茂","MA20":35.5525,"MA5":36.13,"MA10":35.1,"MA60":34.67,"UB":38.0231,"LB":33.0819,"BLimitP":84.35,"UBSlopeP":0.38,"signals":[],"candlestick":[],"bandWidthP":14.94,"VMA30":11819.4518,"VLimitP":57.64,"change":-0.1,"changePercent":-0.27,"link":"https://histock.tw/stock/tv/tvchart.aspx?no=8150","link2":"https://invest.cnyes.com/twstock/TWS/8150/technical","buyiDays":"","buyfDays":""},{"dv":"44.15","deal":"3665","ep":"14.33","net":"1.46","zcra12":"3.21","zcra1_12":"5.43","zch4":"50.8","zch1_4":"25.2","type":"鍵盤","zcj1":"22.9","zcra22":"53.24","zca3":"1708","zcra1_3":"9.43","zcra3":"5.56","buyi":"0","buyf":"291","moneyt":"5511","moneyy":"5558","stockt":"69","stocky":"73","zcra10":"10.09","zcra1_10":"17.48","id":"8163","name":"達方","MA20":42.035,"MA5":42.89,"MA10":41.965,"MA60":43.1158,"UB":44.1074,"LB":39.9626,"BLimitP":101.03,"UBSlopeP":-0.51,"signals":["gt-UB"],"candlestick":[],"bandWidthP":10.37,"VMA30":2362.8119,"VLimitP":79.76,"change":0.6,"changePercent":1.38,"link":"https://histock.tw/stock/tv/tvchart.aspx?no=8163","link2":"https://invest.cnyes.com/twstock/TWS/8163/technical","buyiDays":"","buyfDays":"+2"},{"dv":"31.75","deal":"6775","ep":"39.69","net":"2.44","zcra12":"0.8","zcra1_12":"1.02","zch4":"28.11","zch1_4":"21.86","type":"偏光片","zcj1":"40.65","zcra22":"60","zca3":"1132","zcra1_3":"3.44","zcra3":"2.54","buyi":"0","buyf":"842","moneyt":"5489","moneyy":"5615","stockt":"720","stocky":"713","zcra10":"6.18","zcra1_10":"7.83","id":"8215","name":"明基材","MA20":29.63,"MA5":30.98,"MA10":30.71,"MA60":27.6117,"UB":32.9274,"LB":26.3326,"BLimitP":82.15,"UBSlopeP":0.74,"signals":[],"candlestick":[],"bandWidthP":25.04,"VMA30":11515.5201,"VLimitP":38.65,"change":0.55,"changePercent":1.76,"link":"https://histock.tw/stock/tv/tvchart.aspx?no=8215","link2":"https://invest.cnyes.com/twstock/TWS/8215/technical","buyiDays":"","buyfDays":""},{"dv":"41.75","deal":"2057","ep":"12.54","net":"1.52","zcra12":"3.73","zcra1_12":"3.56","zch4":"12.88","zch1_4":"-0.81","type":"DRAM","zcj1":"18.81","zcra22":"34.39","zca3":"901","zcra1_3":"4.64","zcra3":"6.46","buyi":"0","buyf":"33","moneyt":"3340","moneyy":"3456","stockt":"11","stocky":"33","zcra10":"13.69","zcra1_10":"13.63","id":"8271","name":"宇瞻","MA20":39.19,"MA5":40.25,"MA10":39.05,"MA60":39.135,"UB":41.615,"LB":36.765,"BLimitP":102.78,"UBSlopeP":0.06,"signals":[],"candlestick":[],"bandWidthP":13.19,"VMA30":1977.7439,"VLimitP":50.58,"change":0,"changePercent":0,"link":"https://histock.tw/stock/tv/tvchart.aspx?no=8271","link2":"https://invest.cnyes.com/twstock/TWS/8271/technical","buyiDays":"","buyfDays":""},{"dv":"183","deal":"1055","ep":"32.5","net":"9.62","zcra12":"8.48","zcra1_12":"7.88","zch4":"15.72","zch1_4":"-1.46","type":"鞋業","zcj1":"17.26","zcra22":"54.6","zca3":"9391","zcra1_3":"11.36","zcra3":"11.33","buyi":"21","buyf":"-663","moneyt":"254","moneyy":"250","stockt":"11","stocky":"11","zcra10":"38.14","zcra1_10":"35.12","id":"9910","name":"豐泰","MA20":184.175,"MA5":183,"MA10":182.4,"MA60":190.6333,"UB":190.2928,"LB":178.0572,"BLimitP":40.4,"UBSlopeP":-0.15,"signals":["lt-MA5","lt-MA20"],"candlestick":[],"bandWidthP":6.87,"VMA30":1243.2414,"VLimitP":42.24,"change":-3,"changePercent":-1.61,"link":"https://histock.tw/stock/tv/tvchart.aspx?no=9910","link2":"https://invest.cnyes.com/twstock/TWS/9910/technical","buyiDays":"+3","buyfDays":""},{"dv":"283","deal":"1733","ep":"24.89","net":"4.49","zcra12":"9","zcra1_12":"7.64","zch4":"38.38","zch1_4":"19.63","type":"自行車","zcj1":"13.34","zcra22":"60.25","zca3":"1937","zcra1_3":"6.48","zcra3":"7.46","buyi":"0","buyf":"-572","moneyt":"639","moneyy":"614","stockt":"33","stocky":"34","zcra10":"15.72","zcra1_10":"13.72","id":"9921","name":"巨大","MA20":283.825,"MA5":283.8,"MA10":283.4,"MA60":278.7417,"UB":291.92,"LB":275.73,"BLimitP":44.9,"UBSlopeP":-0.02,"signals":[],"candlestick":[],"bandWidthP":5.87,"VMA30":1431.3134,"VLimitP":63.25,"change":0,"changePercent":0,"link":"https://histock.tw/stock/tv/tvchart.aspx?no=9921","link2":"https://invest.cnyes.com/twstock/TWS/9921/technical","buyiDays":"","buyfDays":""},{"dv":"41.2","deal":"6640","ep":"8.92","net":"0.64","zcra12":"9.35","zcra1_12":"7.22","zch4":"107.77","zch1_4":"40.16","type":"營建","zcj1":"27.81","zcra22":"43.12","zca3":"3095","zcra1_3":"13.26","zcra3":"11.01","buyi":"0","buyf":"190","moneyt":"8151","moneyy":"7956","stockt":"293","stocky":"525","zcra10":"15.89","zcra1_10":"23.76","id":"9945","name":"潤泰新","MA20":39.745,"MA5":40.54,"MA10":39.805,"MA60":40.4675,"UB":41.0728,"LB":38.4172,"BLimitP":104.79,"UBSlopeP":0.29,"signals":["gt-UB"],"candlestick":[],"bandWidthP":6.91,"VMA30":3900.9237,"VLimitP":95.79,"change":0.3,"changePercent":0.73,"link":"https://histock.tw/stock/tv/tvchart.aspx?no=9945","link2":"https://invest.cnyes.com/twstock/TWS/9945/technical","buyiDays":"","buyfDays":""},{"dv":"26.7","deal":"3672","ep":"14.2","net":"2.14","zcra12":"1.81","zcra1_12":"1.61","zch4":"16.77","zch1_4":"3.44","type":"散熱風扇馬達","zcj1":"37.6","zcra22":"45.93","zca3":"292","zcra1_3":"7.11","zcra3":"7.58","buyi":"0","buyf":"408","moneyt":"2965","moneyy":"2990","stockt":"99","stocky":"243","zcra10":"13.8","zcra1_10":"13.24","id":"3071","name":"協禧","MA20":25.2025,"MA5":25.47,"MA10":24.77,"MA60":24.5325,"UB":27.1571,"LB":23.2479,"BLimitP":88.31,"UBSlopeP":0.79,"signals":[],"candlestick":[],"bandWidthP":16.82,"VMA30":2892.9333,"VLimitP":56.2,"change":0.85,"changePercent":3.29,"link":"https://histock.tw/stock/tv/tvchart.aspx?no=3071","link2":"https://invest.cnyes.com/twstock/TWS/3071/technical","buyiDays":"","buyfDays":"+2"},{"dv":"57.6","deal":"15947","ep":"15.91","net":"2.66","zcra12":"2.49","zcra1_12":"2.77","zch4":"208.44","zch1_4":"68.42","type":"電源供應器","zcj1":"10.21","zcra22":"36.24","zca3":"662","zcra1_3":"11.08","zcra3":"12.68","buyi":"0","buyf":"1444","moneyt":"21398","moneyy":"20735","stockt":"657","stocky":"417","zcra10":"12.5","zcra1_10":"14.47","id":"3078","name":"僑威","MA20":44.1575,"MA5":49.41,"MA10":46,"MA60":44.4642,"UB":52.1591,"LB":36.1559,"BLimitP":134,"UBSlopeP":7.24,"signals":[],"candlestick":[],"bandWidthP":44.26,"VMA30":5189.2333,"VLimitP":85.22,"change":5.2,"changePercent":9.92,"link":"https://histock.tw/stock/tv/tvchart.aspx?no=3078","link2":"https://invest.cnyes.com/twstock/TWS/3078/technical","buyiDays":"","buyfDays":"+4"},{"dv":"127","deal":"2111","ep":"19.81","net":"3.66","zcra12":"5.34","zcra1_12":"3.6","zch4":"101.54","zch1_4":"15.21","type":"硬碟相關","zcj1":"12.73","zcra22":"27.81","zca3":"572","zcra1_3":"18.73","zcra3":"24.67","buyi":"-313","buyf":"-130","moneyt":"5445","moneyy":"5460","stockt":"94","stocky":"99","zcra10":"23","zcra1_10":"17.34","id":"3217","name":"優群","MA20":121.9,"MA5":129.1,"MA10":128.8,"MA60":115.5667,"UB":138.7808,"LB":105.0192,"BLimitP":65.11,"UBSlopeP":0.22,"signals":["lt-MA5","lt-MA10"],"candlestick":[],"bandWidthP":32.15,"VMA30":2418.0667,"VLimitP":46.41,"change":-4,"changePercent":-3.05,"link":"https://histock.tw/stock/tv/tvchart.aspx?no=3217","link2":"https://invest.cnyes.com/twstock/TWS/3217/technical","buyiDays":"","buyfDays":""},{"dv":"46.8","deal":"12546","ep":"14.81","net":"1.87","zcra12":"2.36","zcra1_12":"3.31","zch4":"39.77","zch1_4":"34.32","type":"IC測試","zcj1":"13.77","zcra22":"39.01","zca3":"3542","zcra1_3":"21.77","zcra3":"19.56","buyi":"-790","buyf":"618","moneyt":"14334","moneyy":"13830","stockt":"391","stocky":"351","zcra10":"9.94","zcra1_10":"14.62","id":"3264","name":"欣銓","MA20":43.945,"MA5":47.4,"MA10":45.735,"MA60":40.2692,"UB":49.3448,"LB":38.5452,"BLimitP":76.44,"UBSlopeP":0.61,"signals":[],"candlestick":[],"bandWidthP":28.02,"VMA30":14424,"VLimitP":46.13,"change":0.65,"changePercent":1.41,"link":"https://histock.tw/stock/tv/tvchart.aspx?no=3264","link2":"https://invest.cnyes.com/twstock/TWS/3264/technical","buyiDays":"","buyfDays":""},{"dv":"50.7","deal":"4870","ep":"14.49","net":"1.76","zcra12":"1.85","zcra1_12":"2.39","zch4":"62.05","zch1_4":"79.72","type":"電池相關","zcj1":"11.04","zcra22":"59.57","zca3":"553","zcra1_3":"2.31","zcra3":"2.13","buyi":"0","buyf":"361","moneyt":"6926","moneyy":"7128","stockt":"166","stocky":"184","zcra10":"6.76","zcra1_10":"8.8","id":"3323","name":"加百裕","MA20":47.77,"MA5":48.34,"MA10":47.555,"MA60":46.6267,"UB":51.6334,"LB":43.9066,"BLimitP":87.92,"UBSlopeP":0.71,"signals":[],"candlestick":[],"bandWidthP":17.6,"VMA30":6145.3667,"VLimitP":46.56,"change":1.5,"changePercent":3.05,"link":"https://histock.tw/stock/tv/tvchart.aspx?no=3323","link2":"https://invest.cnyes.com/twstock/TWS/3323/technical","buyiDays":"","buyfDays":"+4"},{"dv":"223","deal":"2084","ep":"18.79","net":"4.68","zcra12":"11.71","zcra1_12":"2.9","zch4":"81.26","zch1_4":"38.08","type":"散熱模組","zcj1":"18.98","zcra22":"53.17","zca3":"777","zcra1_3":"2.38","zcra3":"11.6","buyi":"-11","buyf":"-91","moneyt":"11346","moneyy":"11297","stockt":"761","stocky":"793","zcra10":"33.24","zcra1_10":"10.27","id":"3324","name":"雙鴻","MA20":221.8,"MA5":221.6,"MA10":216.2,"MA60":223.0417,"UB":242.3656,"LB":201.2344,"BLimitP":52.92,"UBSlopeP":-1.41,"signals":["lt-MA60"],"candlestick":["bear-engulfing"],"bandWidthP":20.44,"VMA30":4219.3667,"VLimitP":36.66,"change":-3.5,"changePercent":-1.55,"link":"https://histock.tw/stock/tv/tvchart.aspx?no=3324","link2":"https://invest.cnyes.com/twstock/TWS/3324/technical","buyiDays":"","buyfDays":""},{"dv":"103.5","deal":"2299","ep":"14.08","net":"3.59","zcra12":"6.13","zcra1_12":"5.23","zch4":"101.12","zch1_4":"3.54","type":"連接器","zcj1":"10.78","zcra22":"50.06","zca3":"537","zcra1_3":"18.66","zcra3":"21.89","buyi":"0","buyf":"-100","moneyt":"4373","moneyy":"4210","stockt":"558","stocky":"624","zcra10":"25.44","zcra1_10":"23.36","id":"3526","name":"凡甲","MA20":97.31,"MA5":102.4,"MA10":100.77,"MA60":88.525,"UB":106.9138,"LB":87.7062,"BLimitP":82.23,"UBSlopeP":0.71,"signals":[],"candlestick":[],"bandWidthP":21.9,"VMA30":2483.6333,"VLimitP":47.66,"change":0,"changePercent":0,"link":"https://histock.tw/stock/tv/tvchart.aspx?no=3526","link2":"https://invest.cnyes.com/twstock/TWS/3526/technical","buyiDays":"","buyfDays":""},{"dv":"103","deal":"1188","ep":"18.97","net":"2.3","zcra12":"3.95","zcra1_12":"4.13","zch4":"7.77","zch1_4":"28.47","type":"IC設計","zcj1":"22.12","zcra22":"36.36","zca3":"617","zcra1_3":"15.09","zcra3":"12.8","buyi":"0","buyf":"-113","moneyt":"2796","moneyy":"2768","stockt":"25","stocky":"24","zcra10":"9.06","zcra1_10":"9.62","id":"3587","name":"閎康","MA20":101.105,"MA5":101.02,"MA10":99.16,"MA60":92.1933,"UB":110.3124,"LB":91.8976,"BLimitP":60.29,"UBSlopeP":-0.35,"signals":[],"candlestick":[],"bandWidthP":20.04,"VMA30":2066.3,"VLimitP":38.7,"change":1,"changePercent":0.98,"link":"https://histock.tw/stock/tv/tvchart.aspx?no=3587","link2":"https://invest.cnyes.com/twstock/TWS/3587/technical","buyiDays":"","buyfDays":""},{"dv":"33.8","deal":"1359","ep":"29.65","net":"2.55","zcra12":"1.05","zcra1_12":"1.51","zch4":"87.69","zch1_4":"74.25","type":"連接器及線組加工","zcj1":"32.03","zcra22":"57.82","zca3":"58","zcra1_3":"7.09","zcra3":"4.59","buyi":"0","buyf":"60","moneyt":"1201","moneyy":"1038","stockt":"66","stocky":"62","zcra10":"7.77","zcra1_10":"11.25","id":"3597","name":"映興","MA20":28.7325,"MA5":31.75,"MA10":30.655,"MA60":23.1558,"UB":34.2581,"LB":23.2069,"BLimitP":95.85,"UBSlopeP":2.31,"signals":[],"candlestick":[],"bandWidthP":47.62,"VMA30":1545.6333,"VLimitP":46.75,"change":1.2,"changePercent":3.68,"link":"https://histock.tw/stock/tv/tvchart.aspx?no=3597","link2":"https://invest.cnyes.com/twstock/TWS/3597/technical","buyiDays":"","buyfDays":""},{"dv":"67.4","deal":"3884","ep":"24.16","net":"3.24","zcra12":"3.62","zcra1_12":"5.88","zch4":"3.46","zch1_4":"1.63","type":"西藥","zcj1":"11.69","zcra22":"35.42","zca3":"1210","zcra1_3":"26.25","zcra3":"27.51","buyi":"-2","buyf":"-319","moneyt":"2907","moneyy":"2789","stockt":"21","stocky":"22","zcra10":"14.45","zcra1_10":"23.39","id":"4105","name":"東洋","MA20":63.44,"MA5":64.86,"MA10":63.2,"MA60":67.1117,"UB":67.6914,"LB":59.1886,"BLimitP":96.57,"UBSlopeP":0.23,"signals":["lt-UB"],"candlestick":[],"bandWidthP":14.37,"VMA30":1252,"VLimitP":110.82,"change":-1.3,"changePercent":-1.89,"link":"https://histock.tw/stock/tv/tvchart.aspx?no=4105","link2":"https://invest.cnyes.com/twstock/TWS/4105/technical","buyiDays":"","buyfDays":""},{"dv":"129.5","deal":"3300","ep":"37.98","net":"6.86","zcra12":"1.03","zcra1_12":"2.2","zch4":"66.81","zch1_4":"69.46","type":"被動元件導電漿","zcj1":"21.27","zcra22":"40.75","zca3":"29","zcra1_3":"9.52","zcra3":"6.67","buyi":"0","buyf":"-4","moneyt":"3595","moneyy":"3382","stockt":"189","stocky":"185","zcra10":"6.54","zcra1_10":"13.67","id":"4760","name":"勤凱","MA20":119.775,"MA5":119.7,"MA10":115.6,"MA60":101.8633,"UB":133.723,"LB":105.827,"BLimitP":84.86,"UBSlopeP":-0.22,"signals":[],"candlestick":[],"bandWidthP":26.36,"VMA30":2790.6,"VLimitP":54.49,"change":9,"changePercent":7.47,"link":"https://histock.tw/stock/tv/tvchart.aspx?no=4760","link2":"https://invest.cnyes.com/twstock/TWS/4760/technical","buyiDays":"","buyfDays":""},{"dv":"91.8","deal":"6299","ep":"16.19","net":"2.43","zcra12":"3.57","zcra1_12":"4.4","zch4":"174.5","zch1_4":"67.59","type":"筆電散熱機構件","zcj1":"44.17","zcra22":"37.65","zca3":"338","zcra1_3":"13.78","zcra3":"12.39","buyi":"0","buyf":"-83","moneyt":"3766","moneyy":"2939","stockt":"132","stocky":"65","zcra10":"10.29","zcra1_10":"13.06","id":"5223","name":"安力-KY","MA20":75.855,"MA5":82.14,"MA10":78.07,"MA60":72.7133,"UB":86.6518,"LB":65.0582,"BLimitP":123.84,"UBSlopeP":4.52,"signals":["gt-UB"],"candlestick":[],"bandWidthP":33.19,"VMA30":2214.0333,"VLimitP":88.76,"change":8.3,"changePercent":9.94,"link":"https://histock.tw/stock/tv/tvchart.aspx?no=5223","link2":"https://invest.cnyes.com/twstock/TWS/5223/technical","buyiDays":"","buyfDays":""},{"dv":"130","deal":"3286","ep":"14.04","net":"3.76","zcra12":"7.96","zcra1_12":"7.3","zch4":"52.18","zch1_4":"56.7","type":"IC設計廠","zcj1":"10.83","zcra22":"25.63","zca3":"223","zcra1_3":"18.81","zcra3":"20.36","buyi":"0","buyf":"45","moneyt":"2125","moneyy":"2054","stockt":"54","stocky":"30","zcra10":"27.38","zcra1_10":"33.63","id":"5299","name":"杰力","MA20":119.35,"MA5":123.1,"MA10":118.2,"MA60":119.4917,"UB":128.6994,"LB":110.0006,"BLimitP":106.96,"UBSlopeP":0.77,"signals":["gt-UB"],"candlestick":[],"bandWidthP":17,"VMA30":963.6333,"VLimitP":124.03,"change":5.5,"changePercent":4.42,"link":"https://histock.tw/stock/tv/tvchart.aspx?no=5299","link2":"https://invest.cnyes.com/twstock/TWS/5299/technical","buyiDays":"","buyfDays":"+4"},{"dv":"125.5","deal":"5945","ep":"32.6","net":"6.96","zcra12":"3.58","zcra1_12":"3.76","zch4":"17.05","zch1_4":"15","type":"專業晶圓代工","zcj1":"45.04","zcra22":"30.99","zca3":"8445","zcra1_3":"24.73","zcra3":"24.43","buyi":"-210","buyf":"645","moneyt":"3225","moneyy":"3198","stockt":"430","stocky":"433","zcra10":"19.88","zcra1_10":"21.52","id":"5347","name":"世界","MA20":121.6,"MA5":125.2,"MA10":122.45,"MA60":116.0833,"UB":130.7466,"LB":112.4534,"BLimitP":71.32,"UBSlopeP":0.27,"signals":["gt-MA5"],"candlestick":[],"bandWidthP":16.27,"VMA30":9214,"VLimitP":32.43,"change":1,"changePercent":0.8,"link":"https://histock.tw/stock/tv/tvchart.aspx?no=5347","link2":"https://invest.cnyes.com/twstock/TWS/5347/technical","buyiDays":"","buyfDays":"+2"},{"dv":"59.5","deal":"14011","ep":"30.83","net":"2.55","zcra12":"2.29","zcra1_12":"3.53","zch4":"24.91","zch1_4":"24.6","type":"二極體","zcj1":"10.87","zcra22":"47.96","zca3":"2084","zcra1_3":"17.78","zcra3":"12.36","buyi":"452","buyf":"1650","moneyt":"9730","moneyy":"9960","stockt":"4895","stocky":"3802","zcra10":"13.69","zcra1_10":"17.57","id":"5425","name":"台半","MA20":54.755,"MA5":56.84,"MA10":55.13,"MA60":55.9817,"UB":58.9528,"LB":50.5572,"BLimitP":106.52,"UBSlopeP":0.09,"signals":[],"candlestick":[],"bandWidthP":16.61,"VMA30":7727.9333,"VLimitP":86.1,"change":0.1,"changePercent":0.17,"link":"https://histock.tw/stock/tv/tvchart.aspx?no=5425","link2":"https://invest.cnyes.com/twstock/TWS/5425/technical","buyiDays":"","buyfDays":"+5"},{"dv":"61.9","deal":"7331","ep":"20.23","net":"3.19","zcra12":"2.58","zcra1_12":"3.41","zch4":"36.95","zch1_4":"26.09","type":"印刷電路板","zcj1":"13.83","zcra22":"29.87","zca3":"374","zcra1_3":"14.19","zcra3":"12.98","buyi":"0","buyf":"-352","moneyt":"9965","moneyy":"9986","stockt":"148","stocky":"138","zcra10":"13.3","zcra1_10":"18.13","id":"5439","name":"高技","MA20":55.135,"MA5":59.04,"MA10":56.84,"MA60":52.6642,"UB":61.4232,"LB":48.8468,"BLimitP":103.79,"UBSlopeP":2.01,"signals":[],"candlestick":[],"bandWidthP":25.75,"VMA30":3380.1667,"VLimitP":82.14,"change":1,"changePercent":1.64,"link":"https://histock.tw/stock/tv/tvchart.aspx?no=5439","link2":"https://invest.cnyes.com/twstock/TWS/5439/technical","buyiDays":"","buyfDays":""},{"dv":"92.8","deal":"1319","ep":"25.22","net":"5.47","zcra12":"2.19","zcra1_12":"1","zch4":"88.12","zch1_4":"-11.28","type":"連接器","zcj1":"35.44","zcra22":"63.48","zca3":"446","zcra1_3":"6.29","zcra3":"7.53","buyi":"0","buyf":"88","moneyt":"6768","moneyy":"6652","stockt":"256","stocky":"255","zcra10":"20.23","zcra1_10":"12.31","id":"5457","name":"宣德","MA20":90.59,"MA5":89.4,"MA10":86.79,"MA60":97.1117,"UB":100.8694,"LB":80.3106,"BLimitP":60.75,"UBSlopeP":-2.03,"signals":[],"candlestick":[],"bandWidthP":25.6,"VMA30":2375.4333,"VLimitP":37.13,"change":1.9,"changePercent":2.09,"link":"https://histock.tw/stock/tv/tvchart.aspx?no=5457","link2":"https://invest.cnyes.com/twstock/TWS/5457/technical","buyiDays":"","buyfDays":"+3"},{"dv":"64","deal":"1268","ep":"8.63","net":"3.04","zcra12":"3.2","zcra1_12":"2.09","zch4":"94.14","zch1_4":"42.46","type":"空運","zcj1":"11.74","zcra22":"57.25","zca3":"922","zcra1_3":"1.55","zcra3":"2.83","buyi":"0","buyf":"337","moneyt":"2579","moneyy":"2651","stockt":"291","stocky":"390","zcra10":"18.77","zcra1_10":"13.48","id":"5609","name":"中菲行","MA20":59.76,"MA5":62.7,"MA10":61.4,"MA60":63.66,"UB":64.2822,"LB":55.2378,"BLimitP":96.88,"UBSlopeP":0.85,"signals":["gt-MA60"],"candlestick":[],"bandWidthP":16.37,"VMA30":1289.6333,"VLimitP":49.39,"change":1,"changePercent":1.59,"link":"https://histock.tw/stock/tv/tvchart.aspx?no=5609","link2":"https://invest.cnyes.com/twstock/TWS/5609/technical","buyiDays":"","buyfDays":""},{"dv":"69","deal":"7712","ep":"15.61","net":"2.48","zcra12":"4.49","zcra1_12":"8.62","zch4":"49.76","zch1_4":"40.4","type":"被動元件上游","zcj1":"43.76","zcra22":"28.28","zca3":"963","zcra1_3":"33.67","zcra3":"20.52","buyi":"0","buyf":"60","moneyt":"9131","moneyy":"9206","stockt":"500","stocky":"466","zcra10":"17.23","zcra1_10":"38.58","id":"6173","name":"信昌電","MA20":63.37,"MA5":65.38,"MA10":62.94,"MA60":65.39,"UB":68.4474,"LB":58.2926,"BLimitP":105.44,"UBSlopeP":0,"signals":["gt-UB"],"candlestick":[],"bandWidthP":17.42,"VMA30":3352.6667,"VLimitP":87.18,"change":2,"changePercent":2.99,"link":"https://histock.tw/stock/tv/tvchart.aspx?no=6173","link2":"https://invest.cnyes.com/twstock/TWS/6173/technical","buyiDays":"","buyfDays":""},{"dv":"40.3","deal":"9160","ep":"24.13","net":"2.55","zcra12":"0.89","zcra1_12":"2.23","zch4":"31.13","zch1_4":"21.14","type":"被動元件上游","zcj1":"33.67","zcra22":"44.32","zca3":"816","zcra1_3":"13.34","zcra3":"8.89","buyi":"0","buyf":"18","moneyt":"4522","moneyy":"3967","stockt":"795","stocky":"367","zcra10":"6.02","zcra1_10":"14.38","id":"6175","name":"立敦","MA20":35.01,"MA5":36.29,"MA10":34.695,"MA60":32.6533,"UB":38.8816,"LB":31.1384,"BLimitP":118.32,"UBSlopeP":0.98,"signals":["gt-UB"],"candlestick":[],"bandWidthP":24.87,"VMA30":3850.6,"VLimitP":80.95,"change":2.5,"changePercent":6.61,"link":"https://histock.tw/stock/tv/tvchart.aspx?no=6175","link2":"https://invest.cnyes.com/twstock/TWS/6175/technical","buyiDays":"","buyfDays":""},{"dv":"19.1","deal":"2779","ep":"30.32","net":"1.63","zcra12":"1.06","zcra1_12":"1.41","zch4":"47.95","zch1_4":"24.32","type":"連接線材","zcj1":"10.18","zcra22":"51.34","zca3":"154","zcra1_3":"5.48","zcra3":"5.57","buyi":"0","buyf":"127","moneyt":"8274","moneyy":"7257","stockt":"23","stocky":"6","zcra10":"8.52","zcra1_10":"12.01","id":"6190","name":"萬泰科","MA20":17.6725,"MA5":18.36,"MA10":17.82,"MA60":17.3792,"UB":18.7037,"LB":16.6413,"BLimitP":119.22,"UBSlopeP":1.7,"signals":[],"candlestick":[],"bandWidthP":12.39,"VMA30":1619.4667,"VLimitP":63.1,"change":0.4,"changePercent":2.14,"link":"https://histock.tw/stock/tv/tvchart.aspx?no=6190","link2":"https://invest.cnyes.com/twstock/TWS/6190/technical","buyiDays":"","buyfDays":"+6"},{"dv":"96.3","deal":"2926","ep":"15.89","net":"3.93","zcra12":"3.7","zcra1_12":"3.76","zch4":"117.45","zch1_4":"145.87","type":"電源供應器","zcj1":"31.04","zcra22":"33.83","zca3":"601","zcra1_3":"15.89","zcra3":"17.03","buyi":"0","buyf":"-87","moneyt":"2884","moneyy":"2555","stockt":"53","stocky":"48","zcra10":"17.53","zcra1_10":"19.52","id":"6203","name":"海韻電","MA20":81.3,"MA5":88.76,"MA10":83.67,"MA60":80.455,"UB":92.21,"LB":70.39,"BLimitP":118.74,"UBSlopeP":3.63,"signals":[],"candlestick":[],"bandWidthP":31,"VMA30":1127.5667,"VLimitP":88.46,"change":1.6,"changePercent":1.69,"link":"https://histock.tw/stock/tv/tvchart.aspx?no=6203","link2":"https://invest.cnyes.com/twstock/TWS/6203/technical","buyiDays":"","buyfDays":""},{"dv":"43.8","deal":"4349","ep":"16.98","net":"2.19","zcra12":"2.3","zcra1_12":"2.11","zch4":"91.19","zch1_4":"20.78","type":"設備儀器廠商","zcj1":"16.37","zcra22":"34.01","zca3":"563","zcra1_3":"9.95","zcra3":"12.03","buyi":"0","buyf":"153","moneyt":"6731","moneyy":"7432","stockt":"275","stocky":"296","zcra10":"13","zcra1_10":"11.44","id":"6208","name":"日揚","MA20":41.61,"MA5":43.58,"MA10":43.33,"MA60":39.33,"UB":45.48,"LB":37.74,"BLimitP":78.29,"UBSlopeP":0.51,"signals":[],"candlestick":[],"bandWidthP":20.51,"VMA30":4830.1333,"VLimitP":47.17,"change":-0.65,"changePercent":-1.46,"link":"https://histock.tw/stock/tv/tvchart.aspx?no=6208","link2":"https://invest.cnyes.com/twstock/TWS/6208/technical","buyiDays":"","buyfDays":""},{"dv":"123","deal":"5123","ep":"15.24","net":"2.06","zcra12":"5.36","zcra1_12":"4.19","zch4":"22.8","zch1_4":"10.17","type":"探針探針卡","zcj1":"10.3","zcra22":"46.45","zca3":"672","zcra1_3":"6","zcra3":"8.65","buyi":"0","buyf":"-304","moneyt":"9960","moneyy":"10090","stockt":"310","stocky":"299","zcra10":"10.07","zcra1_10":"8.55","id":"6223","name":"旺矽","MA20":116.725,"MA5":116.4,"MA10":111.9,"MA60":114.4,"UB":132.1602,"LB":101.2898,"BLimitP":70.33,"UBSlopeP":0.22,"signals":[],"candlestick":[],"bandWidthP":30.48,"VMA30":7171.1,"VLimitP":41.77,"change":3,"changePercent":2.5,"link":"https://histock.tw/stock/tv/tvchart.aspx?no=6223","link2":"https://invest.cnyes.com/twstock/TWS/6223/technical","buyiDays":"","buyfDays":""},{"dv":"117","deal":"1534","ep":"24.84","net":"2.75","zcra12":"4.78","zcra1_12":"6","zch4":"45.85","zch1_4":"14.13","type":"車用電子","zcj1":"18.4","zcra22":"36.73","zca3":"1043","zcra1_3":"18.23","zcra3":"15.6","buyi":"-92","buyf":"74","moneyt":"3281","moneyy":"3202","stockt":"99","stocky":"102","zcra10":"10.77","zcra1_10":"13.16","id":"6279","name":"胡連","MA20":116.025,"MA5":115.5,"MA10":113.85,"MA60":112.5533,"UB":124.4362,"LB":107.6138,"BLimitP":55.8,"UBSlopeP":0.08,"signals":[],"candlestick":[],"bandWidthP":15.63,"VMA30":4734.7667,"VLimitP":35.54,"change":-0.5,"changePercent":-0.43,"link":"https://histock.tw/stock/tv/tvchart.aspx?no=6279","link2":"https://invest.cnyes.com/twstock/TWS/6279/technical","buyiDays":"","buyfDays":"+6"},{"dv":"112","deal":"3714","ep":"18.76","net":"3.28","zcra12":"6.37","zcra1_12":"7.58","zch4":"70.16","zch1_4":"6.3","type":"靜電防護IC設計","zcj1":"10.45","zcra22":"24.53","zca3":"710","zcra1_3":"20.69","zcra3":"21.29","buyi":"39","buyf":"36","moneyt":"8630","moneyy":"8287","stockt":"65","stocky":"74","zcra10":"19.2","zcra1_10":"24.9","id":"6411","name":"晶焱","MA20":103.11,"MA5":107.3,"MA10":102.82,"MA60":101.4783,"UB":110.9404,"LB":95.2796,"BLimitP":106.77,"UBSlopeP":1.24,"signals":[],"candlestick":[],"bandWidthP":16.44,"VMA30":2471.0667,"VLimitP":71.78,"change":2.5,"changePercent":2.28,"link":"https://histock.tw/stock/tv/tvchart.aspx?no=6411","link2":"https://invest.cnyes.com/twstock/TWS/6411/technical","buyiDays":"","buyfDays":"+2"},{"dv":"40","deal":"1006","ep":"15.56","net":"1.69","zcra12":"2.36","zcra1_12":"2.92","zch4":"41.56","zch1_4":"30.71","type":"繞線功率電感廠","zcj1":"18.16","zcra22":"47.53","zca3":"144","zcra1_3":"5.61","zcra3":"6.28","buyi":"0","buyf":"22","moneyt":"0","moneyy":"0","stockt":"0","stocky":"0","zcra10":"10.2","zcra1_10":"13.76","id":"6432","name":"今展科","MA20":37.64,"MA5":39.09,"MA10":37.93,"MA60":37.8317,"UB":40.4262,"LB":34.8538,"BLimitP":92.35,"UBSlopeP":0.18,"signals":[],"candlestick":[],"bandWidthP":15.99,"VMA30":1097.2,"VLimitP":48.12,"change":0.55,"changePercent":1.39,"link":"https://histock.tw/stock/tv/tvchart.aspx?no=6432","link2":"https://invest.cnyes.com/twstock/TWS/6432/technical","buyiDays":"","buyfDays":"+6"},{"dv":"67.8","deal":"3370","ep":"32.6","net":"4.63","zcra12":"1.72","zcra1_12":"23.6","zch4":"36.32","zch1_4":"15.47","type":"LED導線架","zcj1":"60.89","zcra22":"52.71","zca3":"1466","zcra1_3":"11.18","zcra3":"8.94","buyi":"-183","buyf":"146","moneyt":"7184","moneyy":"7152","stockt":"100","stocky":"105","zcra10":"12.19","zcra1_10":"16.54","id":"6548","name":"長華科","MA20":64.295,"MA5":67.26,"MA10":65.69,"MA60":58.785,"UB":70.1286,"LB":58.4614,"BLimitP":80.04,"UBSlopeP":0.37,"signals":[],"candlestick":[],"bandWidthP":19.96,"VMA30":6214.4333,"VLimitP":36.37,"change":0.8,"changePercent":1.19,"link":"https://histock.tw/stock/tv/tvchart.aspx?no=6548","link2":"https://invest.cnyes.com/twstock/TWS/6548/technical","buyiDays":"","buyfDays":"+2"},{"dv":"29.9","deal":"26617","ep":"27.94","net":"1.86","zcra12":"1.35","zcra1_12":"1.19","zch4":"67.87","zch1_4":"23.55","type":"專業代工","zcj1":"33.71","zcra22":"43.06","zca3":"449","zcra1_3":"5","zcra3":"5.98","buyi":"0","buyf":"-37","moneyt":"6411","moneyy":"6041","stockt":"724","stocky":"693","zcra10":"8.56","zcra1_10":"7.95","id":"8183","name":"精星","MA20":24.06,"MA5":26.57,"MA10":24.875,"MA60":21.2567,"UB":28.1184,"LB":20.0016,"BLimitP":121.95,"UBSlopeP":4.99,"signals":[],"candlestick":[],"bandWidthP":40.58,"VMA30":9498.4667,"VLimitP":107,"change":1.4,"changePercent":4.91,"link":"https://histock.tw/stock/tv/tvchart.aspx?no=8183","link2":"https://invest.cnyes.com/twstock/TWS/8183/technical","buyiDays":"","buyfDays":""},{"dv":"124.5","deal":"1502","ep":"48.07","net":"2.46","zcra12":"4.11","zcra1_12":"7.08","zch4":"23.58","zch1_4":"9.68","type":"二極體","zcj1":"34.12","zcra22":"27.3","zca3":"382","zcra1_3":"17.27","zcra3":"11.02","buyi":"0","buyf":"4","moneyt":"2717","moneyy":"2612","stockt":"20","stocky":"18","zcra10":"6.06","zcra1_10":"15.3","id":"8255","name":"朋程","MA20":119.325,"MA5":120.7,"MA10":117.5,"MA60":114.36,"UB":126.9492,"LB":111.7008,"BLimitP":83.94,"UBSlopeP":-0.33,"signals":[],"candlestick":[],"bandWidthP":13.65,"VMA30":1191.3333,"VLimitP":58.99,"change":1,"changePercent":0.81,"link":"https://histock.tw/stock/tv/tvchart.aspx?no=8255","link2":"https://invest.cnyes.com/twstock/TWS/8255/technical","buyiDays":"","buyfDays":""},{"dv":"61.5","deal":"28381","ep":"28.74","net":"3.01","zcra12":"1.57","zcra1_12":"2.93","zch4":"20.22","zch1_4":"0.03","type":"銅箔基板","zcj1":"10.93","zcra22":"25.17","zca3":"618","zcra1_3":"15.6","zcra3":"11.2","buyi":"873","buyf":"-1842","moneyt":"22001","moneyy":"21033","stockt":"1954","stocky":"1968","zcra10":"7.42","zcra1_10":"13.81","id":"8358","name":"金居","MA20":54.1325,"MA5":60.78,"MA10":57.23,"MA60":49.8633,"UB":63.1009,"LB":45.1641,"BLimitP":91.07,"UBSlopeP":1.76,"signals":[],"candlestick":["shooting-star"],"bandWidthP":39.71,"VMA30":21363.2667,"VLimitP":60.25,"change":0.1,"changePercent":0.16,"link":"https://histock.tw/stock/tv/tvchart.aspx?no=8358","link2":"https://invest.cnyes.com/twstock/TWS/8358/technical","buyiDays":"","buyfDays":""},{"dv":"208","deal":"1328","ep":"13.59","net":"3.53","zcra12":"17.02","zcra1_12":"17.79","zch4":"19.89","zch1_4":"-9.34","type":"生技","zcj1":"13.72","zcra22":"33.44","zca3":"1466","zcra1_3":"25.15","zcra3":"23.02","buyi":"0","buyf":"164","moneyt":"3617","moneyy":"3597","stockt":"38","stocky":"52","zcra10":"31.41","zcra1_10":"39.35","id":"8436","name":"大江","MA20":197.9,"MA5":198.4,"MA10":201.05,"MA60":206.2667,"UB":212.22,"LB":183.58,"BLimitP":85.27,"UBSlopeP":0.64,"signals":["gt-MA60"],"candlestick":[],"bandWidthP":15.6,"VMA30":999.6,"VLimitP":66.71,"change":5,"changePercent":2.46,"link":"https://histock.tw/stock/tv/tvchart.aspx?no=8436","link2":"https://invest.cnyes.com/twstock/TWS/8436/technical","buyiDays":"","buyfDays":"+3"}],"date":"20210222","length":130}