{"data":[{"dv":"40.75","deal":"19228","ep":"9.7","net":"1.25","zcra12":"4.43","zcra1_12":"4.37","zch4":"-11.33","zch1_4":"-6.75","type":"水泥","zcj1":"14.31","zcra22":"43.27","zca3":"28871","zcra1_3":"22.62","zcra3":"24.56","buyi":"-88","buyf":"-2581","moneyt":"7041","moneyy":"7227","stockt":"247","stocky":"264","zcra10":"12.54","zcra1_10":"12.94","id":"1101","name":"台泥","MA20":41.55,"MA5":40.46,"MA10":40.59,"MA60":42.4725,"UB":43.64,"LB":39.46,"BLimitP":30.86,"UBSlopeP":-0.43,"signals":[],"candlestick":[],"bandWidthP":10.59,"VMA30":17929.1109,"VLimitP":54.52,"change":-0.05,"changePercent":-0.12,"link":"https://histock.tw/stock/tv/tvchart.aspx?no=1101","link2":"https://invest.cnyes.com/twstock/TWS/1101/technical","buyiDays":"","buyfDays":""},{"dv":"40.8","deal":"5507","ep":"9.56","net":"0.96","zcra12":"5.56","zcra1_12":"3.54","zch4":"2.53","zch1_4":"-0.96","type":"水泥","zcj1":"28.87","zcra22":"43","zca3":"37272","zcra1_3":"21.94","zcra3":"23.22","buyi":"-162","buyf":"958","moneyt":"2610","moneyy":"2642","stockt":"26","stocky":"27","zcra10":"13.54","zcra1_10":"9.77","id":"1102","name":"亞泥","MA20":41.7,"MA5":40.42,"MA10":40.675,"MA60":42.8483,"UB":43.97,"LB":39.43,"BLimitP":30.18,"UBSlopeP":-0.31,"signals":["gt-MA10"],"candlestick":[],"bandWidthP":11.51,"VMA30":5550.6653,"VLimitP":49.44,"change":0.35,"changePercent":0.87,"link":"https://histock.tw/stock/tv/tvchart.aspx?no=1102","link2":"https://invest.cnyes.com/twstock/TWS/1102/technical","buyiDays":"","buyfDays":"+2"},{"dv":"19.9","deal":"1346","ep":"26.53","net":"1.54","zcra12":"2.67","zcra1_12":"1.94","zch4":"-1.78","zch1_4":"2.01","type":"乳品","zcj1":"14.55","zcra22":"63.64","zca3":"1428","zcra1_3":"2.64","zcra3":"2.69","buyi":"0","buyf":"-220","moneyt":"6089","moneyy":"6173","stockt":"24","stocky":"20","zcra10":"20.55","zcra1_10":"12.41","id":"1201","name":"味全","MA20":20.655,"MA5":20.09,"MA10":20.185,"MA60":21.0492,"UB":21.656,"LB":19.654,"BLimitP":12.29,"UBSlopeP":-0.8,"signals":[],"candlestick":[],"bandWidthP":10.19,"VMA30":1814.284,"VLimitP":42.23,"change":-0.05,"changePercent":-0.25,"link":"https://histock.tw/stock/tv/tvchart.aspx?no=1201","link2":"https://invest.cnyes.com/twstock/TWS/1201/technical","buyiDays":"","buyfDays":""},{"dv":"47.85","deal":"2722","ep":"13.52","net":"1.99","zcra12":"2.93","zcra1_12":"2.75","zch4":"10.5","zch1_4":"0.7","type":"飼料","zcj1":"12.98","zcra22":"48.57","zca3":"5522","zcra1_3":"3.14","zcra3":"4.78","buyi":"0","buyf":"-837","moneyt":"4449","moneyy":"4462","stockt":"65","stocky":"67","zcra10":"12.78","zcra1_10":"10.98","id":"1210","name":"大成","MA20":49.0575,"MA5":48.28,"MA10":48.41,"MA60":47.75,"UB":50.8419,"LB":47.2731,"BLimitP":16.17,"UBSlopeP":-0.18,"signals":[],"candlestick":[],"bandWidthP":7.55,"VMA30":4028.9573,"VLimitP":38.81,"change":-0.05,"changePercent":-0.1,"link":"https://histock.tw/stock/tv/tvchart.aspx?no=1210","link2":"https://invest.cnyes.com/twstock/TWS/1210/technical","buyiDays":"","buyfDays":""},{"dv":"40.65","deal":"1475","ep":"19.27","net":"1.79","zcra12":"2.51","zcra1_12":"2.35","zch4":"2.84","zch1_4":"8.04","type":"大宗物資","zcj1":"25.04","zcra22":"19.15","zca3":"2821","zcra1_3":"5.89","zcra3":"11.55","buyi":"0","buyf":"84","moneyt":"1081","moneyy":"1117","stockt":"75","stocky":"75","zcra10":"10.11","zcra1_10":"9.91","id":"1229","name":"聯華","MA20":41.11,"MA5":40.5,"MA10":40.525,"MA60":41.4258,"UB":42.4282,"LB":39.7918,"BLimitP":32.55,"UBSlopeP":-0.57,"signals":["gt-MA10"],"candlestick":[],"bandWidthP":6.63,"VMA30":2271.665,"VLimitP":29.23,"change":0.2,"changePercent":0.49,"link":"https://histock.tw/stock/tv/tvchart.aspx?no=1229","link2":"https://invest.cnyes.com/twstock/TWS/1229/technical","buyiDays":"","buyfDays":""},{"dv":"90.1","deal":"7957","ep":"45.97","net":"1.96","zcra12":"5.86","zcra1_12":"7.78","zch4":"25.95","zch1_4":"11.59","type":"PVC","zcj1":"14.93","zcra22":"29.76","zca3":"46580","zcra1_3":"11","zcra3":"9.72","buyi":"6","buyf":"-1104","moneyt":"1694","moneyy":"1707","stockt":"139","stocky":"132","zcra10":"10.59","zcra1_10":"14.15","id":"1301","name":"台塑","MA20":93.225,"MA5":89.02,"MA10":90.22,"MA60":91.0167,"UB":100.2862,"LB":86.1638,"BLimitP":27.87,"UBSlopeP":-0.13,"signals":["gt-MA5"],"candlestick":[],"bandWidthP":16.39,"VMA30":9866.715,"VLimitP":36.59,"change":2,"changePercent":2.27,"link":"https://histock.tw/stock/tv/tvchart.aspx?no=1301","link2":"https://invest.cnyes.com/twstock/TWS/1301/technical","buyiDays":"+2","buyfDays":""},{"dv":"68.8","deal":"7807","ep":"30.85","net":"1.73","zcra12":"2.91","zcra1_12":"6.65","zch4":"18.49","zch1_4":"11.77","type":"塑膠加工","zcj1":"18.25","zcra22":"35.9","zca3":"52299","zcra1_3":"8.83","zcra3":"3.45","buyi":"8","buyf":"-736","moneyt":"1529","moneyy":"1476","stockt":"66","stocky":"49","zcra10":"6.25","zcra1_10":"13.97","id":"1303","name":"南亞","MA20":70.605,"MA5":67.58,"MA10":68.55,"MA60":68.39,"UB":75.4804,"LB":65.7296,"BLimitP":31.49,"UBSlopeP":-0.05,"signals":["gt-MA5","gt-MA10","gt-MA60"],"candlestick":[],"bandWidthP":14.83,"VMA30":7194.109,"VLimitP":55.34,"change":2.1,"changePercent":3.15,"link":"https://histock.tw/stock/tv/tvchart.aspx?no=1303","link2":"https://invest.cnyes.com/twstock/TWS/1303/technical","buyiDays":"+6","buyfDays":""},{"dv":"23.65","deal":"2907","ep":"15.36","net":"1.51","zcra12":"1.22","zcra1_12":"2.52","zch4":"36.29","zch1_4":"24.06","type":"PVC","zcj1":"24.97","zcra22":"29.35","zca3":"2017","zcra1_3":"10.35","zcra3":"5.12","buyi":"-200","buyf":"-383","moneyt":"8395","moneyy":"8425","stockt":"112","stocky":"127","zcra10":"7.92","zcra1_10":"15.86","id":"1305","name":"華夏","MA20":24.905,"MA5":23.33,"MA10":23.51,"MA60":24.0592,"UB":28.145,"LB":21.665,"BLimitP":30.63,"UBSlopeP":-0.15,"signals":["gt-MA5","gt-MA10"],"candlestick":[],"bandWidthP":29.91,"VMA30":12155.1723,"VLimitP":29.73,"change":0.25,"changePercent":1.07,"link":"https://histock.tw/stock/tv/tvchart.aspx?no=1305","link2":"https://invest.cnyes.com/twstock/TWS/1305/technical","buyiDays":"","buyfDays":""},{"dv":"26.75","deal":"8361","ep":"16.02","net":"0.71","zcra12":"2.15","zcra1_12":"2.41","zch4":"1.51","zch1_4":"-3.02","type":"紡織用聚酯粒","zcj1":"26.9","zcra22":"52.9","zca3":"43949","zcra1_3":"6.47","zcra3":"5.5","buyi":"-60","buyf":"-740","moneyt":"5148","moneyy":"5220","stockt":"200","stocky":"196","zcra10":"6.1","zcra1_10":"7.03","id":"1402","name":"遠東新","MA20":27.27,"MA5":26.39,"MA10":26.455,"MA60":27.6875,"UB":29.0584,"LB":25.4816,"BLimitP":35.46,"UBSlopeP":-0.73,"signals":["gt-MA5","gt-MA10"],"candlestick":[],"bandWidthP":14.04,"VMA30":8063.8491,"VLimitP":52.91,"change":0.5,"changePercent":1.9,"link":"https://histock.tw/stock/tv/tvchart.aspx?no=1402","link2":"https://invest.cnyes.com/twstock/TWS/1402/technical","buyiDays":"","buyfDays":""},{"dv":"29.3","deal":"1198","ep":"13.26","net":"0.92","zcra12":"3.08","zcra1_12":"2.82","zch4":"-8.19","zch1_4":"-15.67","type":"尼龍","zcj1":"38.57","zcra22":"20.48","zca3":"6752","zcra1_3":"5.52","zcra3":"2.9","buyi":"0","buyf":"-48","moneyt":"2364","moneyy":"2389","stockt":"41","stocky":"36","zcra10":"6.65","zcra1_10":"7.18","id":"1434","name":"福懋興","MA20":29.81,"MA5":29.16,"MA10":29.32,"MA60":30.6383,"UB":30.8718,"LB":28.7482,"BLimitP":25.98,"UBSlopeP":-0.46,"signals":["gt-MA5"],"candlestick":[],"bandWidthP":7.39,"VMA30":3232.9508,"VLimitP":12.33,"change":0.15,"changePercent":0.51,"link":"https://histock.tw/stock/tv/tvchart.aspx?no=1434","link2":"https://invest.cnyes.com/twstock/TWS/1434/technical","buyiDays":"","buyfDays":""},{"dv":"46.7","deal":"13097","ep":"23","net":"2.11","zcra12":"1.55","zcra1_12":"1.33","zch4":"104.55","zch1_4":"15.9","type":"電機","zcj1":"10.41","zcra22":"61.35","zca3":"1666","zcra1_3":"4.75","zcra3":"5.29","buyi":"0","buyf":"-292","moneyt":"42027","moneyy":"45585","stockt":"1097","stocky":"1319","zcra10":"8.28","zcra1_10":"7.42","id":"1513","name":"中興電","MA20":47.365,"MA5":47.12,"MA10":46.8,"MA60":51.7825,"UB":49.3108,"LB":45.4192,"BLimitP":32.91,"UBSlopeP":-0.3,"signals":["lt-MA10"],"candlestick":[],"bandWidthP":8.57,"VMA30":17986.6542,"VLimitP":39.56,"change":-0.05,"changePercent":-0.11,"link":"https://histock.tw/stock/tv/tvchart.aspx?no=1513","link2":"https://invest.cnyes.com/twstock/TWS/1513/technical","buyiDays":"","buyfDays":""},{"dv":"103.5","deal":"2971","ep":"44.23","net":"4.07","zcra12":"2.15","zcra1_12":"6.4","zch4":"31.64","zch1_4":"17.04","type":"微型線性滑軌廠","zcj1":"14.1","zcra22":"39.02","zca3":"165","zcra1_3":"29.1","zcra3":"18.57","buyi":"0","buyf":"-22","moneyt":"2437","moneyy":"3038","stockt":"180","stocky":"228","zcra10":"8.82","zcra1_10":"27.2","id":"1597","name":"直得","MA20":100.415,"MA5":107.7,"MA10":106.96,"MA60":89.005,"UB":117.0894,"LB":83.7406,"BLimitP":59.25,"UBSlopeP":-0.2,"signals":[],"candlestick":[],"bandWidthP":39.82,"VMA30":3511209.9667,"VLimitP":46.66,"change":2.5,"changePercent":2.48,"link":"https://histock.tw/stock/tv/tvchart.aspx?no=1597","link2":"https://invest.cnyes.com/twstock/TWS/1597/technical","buyiDays":"","buyfDays":""},{"dv":"33.9","deal":"1939","ep":"18.23","net":"1.97","zcra12":"1.99","zcra1_12":"1.25","zch4":"18.08","zch1_4":"18.77","type":"合成樹脂","zcj1":"17.69","zcra22":"59.25","zca3":"4946","zcra1_3":"4.19","zcra3":"5.79","buyi":"80","buyf":"-26","moneyt":"8861","moneyy":"8987","stockt":"213","stocky":"190","zcra10":"11.15","zcra1_10":"6.99","id":"1717","name":"長興","MA20":35.1275,"MA5":33.88,"MA10":33.875,"MA60":35.4808,"UB":38.1863,"LB":32.0687,"BLimitP":29.93,"UBSlopeP":-0.91,"signals":[],"candlestick":["shooting-star"],"bandWidthP":19.08,"VMA30":6665.4297,"VLimitP":25.32,"change":-0.15,"changePercent":-0.44,"link":"https://histock.tw/stock/tv/tvchart.aspx?no=1717","link2":"https://invest.cnyes.com/twstock/TWS/1717/technical","buyiDays":"","buyfDays":""},{"dv":"29.3","deal":"1572","ep":"9.58","net":"1.33","zcra12":"2.08","zcra1_12":"3.38","zch4":"-4.75","zch1_4":"0.39","type":"工業用紙","zcj1":"12.09","zcra22":"56.93","zca3":"7322","zcra1_3":"6.94","zcra3":"8.7","buyi":"0","buyf":"-456","moneyt":"3128","moneyy":"3234","stockt":"296","stocky":"312","zcra10":"9.44","zcra1_10":"17.53","id":"1904","name":"正隆","MA20":30.915,"MA5":29.18,"MA10":29.53,"MA60":31.6825,"UB":34.0368,"LB":27.7932,"BLimitP":24.13,"UBSlopeP":-1.05,"signals":["gt-MA5"],"candlestick":[],"bandWidthP":22.46,"VMA30":6093.5447,"VLimitP":29.63,"change":0.4,"changePercent":1.38,"link":"https://histock.tw/stock/tv/tvchart.aspx?no=1904","link2":"https://invest.cnyes.com/twstock/TWS/1904/technical","buyiDays":"","buyfDays":""},{"dv":"25.35","deal":"1032","ep":"23.47","net":"1.45","zcra12":"1.53","zcra1_12":"2.23","zch4":"-17.28","zch1_4":"-16.93","type":"不鏽鋼","zcj1":"16.91","zcra22":"38.66","zca3":"660","zcra1_3":"5.91","zcra3":"4.92","buyi":"0","buyf":"325","moneyt":"5950","moneyy":"5989","stockt":"37","stocky":"39","zcra10":"8.14","zcra1_10":"11.79","id":"2034","name":"允強","MA20":25.9375,"MA5":25.12,"MA10":25.045,"MA60":25.9267,"UB":28.5557,"LB":23.3193,"BLimitP":38.78,"UBSlopeP":-1.93,"signals":["gt-MA5"],"candlestick":[],"bandWidthP":22.46,"VMA30":7102.7998,"VLimitP":28.96,"change":0.25,"changePercent":1,"link":"https://histock.tw/stock/tv/tvchart.aspx?no=2034","link2":"https://invest.cnyes.com/twstock/TWS/2034/technical","buyiDays":"","buyfDays":"+4"},{"dv":"59.2","deal":"2667","ep":"15.34","net":"3.3","zcra12":"2.9","zcra1_12":"3.12","zch4":"131.64","zch1_4":"85.52","type":"合成橡膠","zcj1":"39.25","zcra22":"18.04","zca3":"1982","zcra1_3":"14.05","zcra3":"15.97","buyi":"0","buyf":"-1120","moneyt":"5272","moneyy":"5671","stockt":"630","stocky":"603","zcra10":"17.39","zcra1_10":"20.56","id":"2108","name":"南帝","MA20":59.62,"MA5":59.78,"MA10":59.94,"MA60":60.4,"UB":62.404,"LB":56.836,"BLimitP":42.46,"UBSlopeP":-0.08,"signals":["lt-MA20"],"candlestick":[],"bandWidthP":9.8,"VMA30":5302.4721,"VLimitP":32.63,"change":-1.2,"changePercent":-1.99,"link":"https://histock.tw/stock/tv/tvchart.aspx?no=2108","link2":"https://invest.cnyes.com/twstock/TWS/2108/technical","buyiDays":"","buyfDays":""},{"dv":"46.65","deal":"3248","ep":"10.21","net":"1.55","zcra12":"4.09","zcra1_12":"3.96","zch4":"13.43","zch1_4":"14.89","type":"電腦通路商","zcj1":"19.18","zcra22":"64.83","zca3":"18812","zcra1_3":"1.41","zcra3":"1.76","buyi":"0","buyf":"-457","moneyt":"1065","moneyy":"1092","stockt":"9","stocky":"8","zcra10":"14.25","zcra1_10":"14.38","id":"2347","name":"聯強","MA20":46.8575,"MA5":46.33,"MA10":46.505,"MA60":45.5333,"UB":48.0437,"LB":45.6713,"BLimitP":41.25,"UBSlopeP":-0.21,"signals":["gt-MA5","gt-MA10","gt-MA60","gt-LB"],"candlestick":[],"bandWidthP":5.19,"VMA30":3812.7649,"VLimitP":40.59,"change":0.8,"changePercent":1.74,"link":"https://histock.tw/stock/tv/tvchart.aspx?no=2347","link2":"https://invest.cnyes.com/twstock/TWS/2347/technical","buyiDays":"","buyfDays":""},{"dv":"28.45","deal":"15956","ep":"14.52","net":"1.61","zcra12":"1.82","zcra1_12":"2.05","zch4":"33.66","zch1_4":"31.2","type":"顯示器","zcj1":"17.59","zcra22":"64.69","zca3":"8475","zcra1_3":"2.94","zcra3":"3.67","buyi":"50","buyf":"2434","moneyt":"19303","moneyy":"19035","stockt":"851","stocky":"910","zcra10":"10.03","zcra1_10":"11.5","id":"2352","name":"佳世達","MA20":28.07,"MA5":28.77,"MA10":28.07,"MA60":25.9858,"UB":29.7248,"LB":26.4152,"BLimitP":61.48,"UBSlopeP":-0.34,"signals":[],"candlestick":[],"bandWidthP":12.53,"VMA30":19922.8032,"VLimitP":39.49,"change":0.2,"changePercent":0.71,"link":"https://histock.tw/stock/tv/tvchart.aspx?no=2352","link2":"https://invest.cnyes.com/twstock/TWS/2352/technical","buyiDays":"","buyfDays":"+2"},{"dv":"78.1","deal":"3864","ep":"13.56","net":"1.94","zcra12":"3.05","zcra1_12":"4.04","zch4":"41.82","zch1_4":"78.32","type":"主機板","zcj1":"10.8","zcra22":"35.42","zca3":"3886","zcra1_3":"3.74","zcra3":"2.34","buyi":"0","buyf":"-58","moneyt":"9691","moneyy":"9372","stockt":"324","stocky":"384","zcra10":"7.86","zcra1_10":"10.31","id":"2376","name":"技嘉","MA20":78.9,"MA5":78.66,"MA10":78.42,"MA60":78.07,"UB":81.6232,"LB":76.1768,"BLimitP":35.31,"UBSlopeP":-0.02,"signals":[],"candlestick":[],"bandWidthP":7.15,"VMA30":6114.4839,"VLimitP":27.08,"change":0.9,"changePercent":1.17,"link":"https://histock.tw/stock/tv/tvchart.aspx?no=2376","link2":"https://invest.cnyes.com/twstock/TWS/2376/technical","buyiDays":"","buyfDays":""},{"dv":"134.5","deal":"4443","ep":"15.62","net":"3.41","zcra12":"6.61","zcra1_12":"7.15","zch4":"37","zch1_4":"40.09","type":"主機板","zcj1":"13.89","zcra22":"48.61","zca3":"9274","zcra1_3":"5.65","zcra3":"4.94","buyi":"-361","buyf":"-221","moneyt":"3032","moneyy":"3102","stockt":"144","stocky":"139","zcra10":"18.33","zcra1_10":"20.92","id":"2377","name":"微星","MA20":132.575,"MA5":133.5,"MA10":132.8,"MA60":128.4083,"UB":139.3446,"LB":125.8054,"BLimitP":64.22,"UBSlopeP":0.14,"signals":["gt-MA5","gt-MA10","gt-MA20"],"candlestick":[],"bandWidthP":10.76,"VMA30":4266.2287,"VLimitP":53.43,"change":3.5,"changePercent":2.67,"link":"https://histock.tw/stock/tv/tvchart.aspx?no=2377","link2":"https://invest.cnyes.com/twstock/TWS/2377/technical","buyiDays":"","buyfDays":""},{"dv":"88.4","deal":"2206","ep":"11.35","net":"2.36","zcra12":"8.45","zcra1_12":"5.22","zch4":"17.61","zch1_4":"1.48","type":"中小尺吋面板","zcj1":"10.32","zcra22":"55.36","zca3":"11059","zcra1_3":"5.33","zcra3":"6.77","buyi":"0","buyf":"371","moneyt":"914","moneyy":"949","stockt":"22","stocky":"21","zcra10":"22.65","zcra1_10":"14.1","id":"2385","name":"群光","MA20":87.355,"MA5":88.26,"MA10":87.92,"MA60":86.5667,"UB":89.4388,"LB":85.2712,"BLimitP":75.07,"UBSlopeP":0.08,"signals":["gt-MA5","gt-MA10","gt-MA20"],"candlestick":[],"bandWidthP":4.89,"VMA30":1901.0966,"VLimitP":57.92,"change":1.2,"changePercent":1.38,"link":"https://histock.tw/stock/tv/tvchart.aspx?no=2385","link2":"https://invest.cnyes.com/twstock/TWS/2385/technical","buyiDays":"","buyfDays":""},{"dv":"86.9","deal":"39431","ep":"33.17","net":"1.74","zcra12":"3.23","zcra1_12":"12.8","zch4":"17.24","zch1_4":"14.9","type":"DRAM","zcj1":"29.62","zcra22":"7.93","zca3":"17407","zcra1_3":"46.45","zcra3":"18.4","buyi":"1384","buyf":"3681","moneyt":"13554","moneyy":"13351","stockt":"3551","stocky":"2924","zcra10":"6.2","zcra1_10":"26.5","id":"2408","name":"南亞科","MA20":86.8,"MA5":83,"MA10":83.86,"MA60":81.4733,"UB":95.0164,"LB":78.5836,"BLimitP":50.61,"UBSlopeP":-0.35,"signals":[],"candlestick":[],"bandWidthP":20.91,"VMA30":19864.4145,"VLimitP":111.68,"change":0.6,"changePercent":0.7,"link":"https://histock.tw/stock/tv/tvchart.aspx?no=2408","link2":"https://invest.cnyes.com/twstock/TWS/2408/technical","buyiDays":"+3","buyfDays":"+3"},{"dv":"109","deal":"5437","ep":"25.65","net":"2.29","zcra12":"4.23","zcra1_12":"4.58","zch4":"22.08","zch1_4":"3.6","type":"電信數據服務","zcj1":"35.29","zcra22":"19.07","zca3":"72427","zcra1_3":"20.25","zcra3":"19.59","buyi":"411","buyf":"-1903","moneyt":"553","moneyy":"565","stockt":"4","stocky":"4","zcra10":"8.74","zcra1_10":"9.59","id":"2412","name":"中華電","MA20":109.725,"MA5":108.8,"MA10":108.75,"MA60":109.4167,"UB":112.0804,"LB":107.3696,"BLimitP":34.61,"UBSlopeP":0,"signals":["gt-MA5","gt-MA10"],"candlestick":[],"bandWidthP":4.39,"VMA30":8499.286,"VLimitP":21.09,"change":0,"changePercent":0,"link":"https://histock.tw/stock/tv/tvchart.aspx?no=2412","link2":"https://invest.cnyes.com/twstock/TWS/2412/technical","buyiDays":"+8","buyfDays":""},{"dv":"22.8","deal":"1200","ep":"29.61","net":"1.51","zcra12":"0.98","zcra1_12":"0.81","zch4":"42.24","zch1_4":"82.68","type":"電信設備","zcj1":"87.67","zcra22":"44.09","zca3":"1700","zcra1_3":"3.6","zcra3":"4.65","buyi":"0","buyf":"393","moneyt":"5428","moneyy":"5409","stockt":"12","stocky":"6","zcra10":"7.43","zcra1_10":"7.38","id":"2419","name":"仲琦","MA20":23.595,"MA5":22.59,"MA10":22.545,"MA60":23.8042,"UB":25.9768,"LB":21.2132,"BLimitP":33.31,"UBSlopeP":-0.63,"signals":["gt-MA5","gt-MA10"],"candlestick":[],"bandWidthP":22.46,"VMA30":2057.413,"VLimitP":40.59,"change":0.6,"changePercent":2.7,"link":"https://histock.tw/stock/tv/tvchart.aspx?no=2419","link2":"https://invest.cnyes.com/twstock/TWS/2419/technical","buyiDays":"","buyfDays":""},{"dv":"66.3","deal":"2109","ep":"15.67","net":"2.19","zcra12":"3.33","zcra1_12":"4.18","zch4":"27.6","zch1_4":"25.81","type":"IC封裝","zcj1":"43.93","zcra22":"14.66","zca3":"4161","zcra1_3":"22.81","zcra3":"19.44","buyi":"0","buyf":"439","moneyt":"4336","moneyy":"4152","stockt":"62","stocky":"76","zcra10":"11.53","zcra1_10":"14.97","id":"2441","name":"超豐","MA20":62.805,"MA5":65.92,"MA10":67.68,"MA60":57.2467,"UB":73.9362,"LB":51.6738,"BLimitP":65.7,"UBSlopeP":0.3,"signals":["gt-MA5"],"candlestick":[],"bandWidthP":43.08,"VMA30":4182.385,"VLimitP":38.78,"change":1.5,"changePercent":2.31,"link":"https://histock.tw/stock/tv/tvchart.aspx?no=2441","link2":"https://invest.cnyes.com/twstock/TWS/2441/technical","buyiDays":"","buyfDays":"+6"},{"dv":"67.3","deal":"1597","ep":"13.46","net":"2.15","zcra12":"3.35","zcra1_12":"4.42","zch4":"15.15","zch1_4":"20.51","type":"鋁質電解電容","zcj1":"14.98","zcra22":"46","zca3":"1531","zcra1_3":"14.33","zcra3":"12.17","buyi":"0","buyf":"45","moneyt":"7306","moneyy":"7504","stockt":"761","stocky":"759","zcra10":"10.57","zcra1_10":"16.65","id":"2472","name":"立隆","MA20":69.19,"MA5":68.58,"MA10":68.77,"MA60":63.14,"UB":73.7414,"LB":64.6386,"BLimitP":29.24,"UBSlopeP":-0.48,"signals":[],"candlestick":[],"bandWidthP":14.08,"VMA30":6075.0548,"VLimitP":29.09,"change":1.2,"changePercent":1.82,"link":"https://histock.tw/stock/tv/tvchart.aspx?no=2472","link2":"https://invest.cnyes.com/twstock/TWS/2472/technical","buyiDays":"","buyfDays":""},{"dv":"78.8","deal":"1013","ep":"16.38","net":"2.01","zcra12":"2.3","zcra1_12":"7.26","zch4":"27.97","zch1_4":"16.05","type":"晶片電阻","zcj1":"14.19","zcra22":"31.24","zca3":"1322","zcra1_3":"26.38","zcra3":"12.23","buyi":"0","buyf":"51","moneyt":"9983","moneyy":"10084","stockt":"527","stocky":"536","zcra10":"6.99","zcra1_10":"25.92","id":"2478","name":"大毅","MA20":83.81,"MA5":79.54,"MA10":80.82,"MA60":79.2717,"UB":90.6762,"LB":76.9438,"BLimitP":13.52,"UBSlopeP":-0.59,"signals":[],"candlestick":[],"bandWidthP":17.85,"VMA30":7557.8564,"VLimitP":27.09,"change":1.3,"changePercent":1.68,"link":"https://histock.tw/stock/tv/tvchart.aspx?no=2478","link2":"https://invest.cnyes.com/twstock/TWS/2478/technical","buyiDays":"","buyfDays":"+2"},{"dv":"50","deal":"5506","ep":"19.69","net":"2.52","zcra12":"1.5","zcra1_12":"2.41","zch4":"27.27","zch1_4":"29.93","type":"二極體","zcj1":"18.17","zcra22":"58.67","zca3":"742","zcra1_3":"8.2","zcra3":"6.87","buyi":"0","buyf":"892","moneyt":"13536","moneyy":"14054","stockt":"1705","stocky":"2249","zcra10":"7.71","zcra1_10":"12.11","id":"2481","name":"強茂","MA20":52.89,"MA5":50.64,"MA10":51.28,"MA60":47.645,"UB":56.831,"LB":48.949,"BLimitP":13.33,"UBSlopeP":-0.13,"signals":[],"candlestick":[],"bandWidthP":16.1,"VMA30":23519.6873,"VLimitP":25.36,"change":1,"changePercent":2.04,"link":"https://histock.tw/stock/tv/tvchart.aspx?no=2481","link2":"https://invest.cnyes.com/twstock/TWS/2481/technical","buyiDays":"","buyfDays":"+2"},{"dv":"232.5","deal":"6738","ep":"18.5","net":"3.19","zcra12":"13.72","zcra1_12":"40.75","zch4":"53.63","zch1_4":"54.28","type":"MLCC","zcj1":"28.56","zcra22":"39.25","zca3":"13121","zcra1_3":"52.77","zcra3":"25.53","buyi":"324","buyf":"1198","moneyt":"14008","moneyy":"14551","stockt":"1194","stocky":"1175","zcra10":"19.17","zcra1_10":"72.81","id":"2492","name":"華新科","MA20":232.2,"MA5":228.4,"MA10":229.8,"MA60":217.0333,"UB":243.1334,"LB":221.2666,"BLimitP":51.37,"UBSlopeP":-0.01,"signals":["gt-MA10","gt-MA20"],"candlestick":[],"bandWidthP":9.88,"VMA30":12719.5043,"VLimitP":28.16,"change":3.5,"changePercent":1.53,"link":"https://histock.tw/stock/tv/tvchart.aspx?no=2492","link2":"https://invest.cnyes.com/twstock/TWS/2492/technical","buyiDays":"+6","buyfDays":"+2"},{"dv":"33","deal":"3536","ep":"25.58","net":"1.22","zcra12":"1.92","zcra1_12":"1.97","zch4":"-2.26","zch1_4":"-2.68","type":"散裝航運","zcj1":"40.44","zcra22":"56.88","zca3":"4518","zcra1_3":"11.57","zcra3":"14.46","buyi":"0","buyf":"-23","moneyt":"7999","moneyy":"8249","stockt":"145","stocky":"164","zcra10":"6.18","zcra1_10":"7.03","id":"2606","name":"裕民","MA20":34.395,"MA5":32.35,"MA10":33.1,"MA60":33.0125,"UB":37.5168,"LB":31.2732,"BLimitP":27.66,"UBSlopeP":-0.94,"signals":["gt-MA5"],"candlestick":[],"bandWidthP":19.96,"VMA30":13551.0618,"VLimitP":28.2,"change":0.95,"changePercent":2.96,"link":"https://histock.tw/stock/tv/tvchart.aspx?no=2606","link2":"https://invest.cnyes.com/twstock/TWS/2606/technical","buyiDays":"","buyfDays":""},{"dv":"38.75","deal":"1505","ep":"10.92","net":"1.73","zcra12":"2.15","zcra1_12":"3.07","zch4":"82.14","zch1_4":"60.36","type":"倉儲貨櫃場","zcj1":"10.79","zcra22":"57.8","zca3":"802","zcra1_3":"3.26","zcra3":"2.64","buyi":"0","buyf":"493","moneyt":"3024","moneyy":"2942","stockt":"43","stocky":"52","zcra10":"9.28","zcra1_10":"14.54","id":"2636","name":"台驊","MA20":38.97,"MA5":38.47,"MA10":38.695,"MA60":38.835,"UB":40.483,"LB":37.457,"BLimitP":42.73,"UBSlopeP":-0.75,"signals":["gt-MA5","gt-MA10"],"candlestick":[],"bandWidthP":8.08,"VMA30":1881.9034,"VLimitP":43.96,"change":1.35,"changePercent":3.61,"link":"https://histock.tw/stock/tv/tvchart.aspx?no=2636","link2":"https://invest.cnyes.com/twstock/TWS/2636/technical","buyiDays":"","buyfDays":""},{"dv":"71.3","deal":"1596","ep":"13.87","net":"2.65","zcra12":"3.38","zcra1_12":"3.08","zch4":"54.31","zch1_4":"24.58","type":"IO控制IC","zcj1":"10.46","zcra22":"24.67","zca3":"970","zcra1_3":"16.39","zcra3":"18.17","buyi":"0","buyf":"-248","moneyt":"6187","moneyy":"6384","stockt":"89","stocky":"70","zcra10":"13.62","zcra1_10":"12.61","id":"3014","name":"聯陽","MA20":73.46,"MA5":72.18,"MA10":73.51,"MA60":70.775,"UB":80.1724,"LB":66.7476,"BLimitP":33.91,"UBSlopeP":-0.24,"signals":[],"candlestick":[],"bandWidthP":20.11,"VMA30":4640.0423,"VLimitP":35.48,"change":-0.2,"changePercent":-0.28,"link":"https://histock.tw/stock/tv/tvchart.aspx?no=3014","link2":"https://invest.cnyes.com/twstock/TWS/3014/technical","buyiDays":"","buyfDays":""},{"dv":"94.8","deal":"2059","ep":"13.58","net":"1.78","zcra12":"6.85","zcra1_12":"4.61","zch4":"9.86","zch1_4":"15.16","type":"無線網路設備系統","zcj1":"19.9","zcra22":"55.58","zca3":"2497","zcra1_3":"3.65","zcra3":"5.25","buyi":"0","buyf":"822","moneyt":"7404","moneyy":"7683","stockt":"474","stocky":"465","zcra10":"13.04","zcra1_10":"9.57","id":"3596","name":"智易","MA20":93.975,"MA5":93.9,"MA10":92.81,"MA60":95.8183,"UB":97.9286,"LB":90.0214,"BLimitP":60.43,"UBSlopeP":-0.53,"signals":[],"candlestick":[],"bandWidthP":8.78,"VMA30":2132.9403,"VLimitP":48.6,"change":0.4,"changePercent":0.42,"link":"https://histock.tw/stock/tv/tvchart.aspx?no=3596","link2":"https://invest.cnyes.com/twstock/TWS/3596/technical","buyiDays":"","buyfDays":"+2"},{"dv":"294.5","deal":"1353","ep":"38.65","net":"5.93","zcra12":"6.55","zcra1_12":"4.61","zch4":"29.04","zch1_4":"11.1","type":"散熱模組","zcj1":"28.77","zcra22":"19.64","zca3":"998","zcra1_3":"10.84","zcra3":"17.54","buyi":"-112","buyf":"-38","moneyt":"4650","moneyy":"4614","stockt":"239","stocky":"242","zcra10":"14.42","zcra1_10":"10.68","id":"3653","name":"健策","MA20":301.775,"MA5":297.5,"MA10":306.3,"MA60":279.0167,"UB":335.3226,"LB":268.2274,"BLimitP":39.16,"UBSlopeP":-0.77,"signals":[],"candlestick":[],"bandWidthP":25.01,"VMA30":2468.4027,"VLimitP":34.88,"change":4.5,"changePercent":1.55,"link":"https://histock.tw/stock/tv/tvchart.aspx?no=3653","link2":"https://invest.cnyes.com/twstock/TWS/3653/technical","buyiDays":"","buyfDays":""},{"dv":"29.25","deal":"2607","ep":"11.79","net":"0.85","zcra12":"2.65","zcra1_12":"3.58","zch4":"10.02","zch1_4":"-29.22","type":"雲端","zcj1":"18.14","zcra22":"28.61","zca3":"233","zcra1_3":"1.09","zcra3":"1.4","buyi":"0","buyf":"307","moneyt":"10382","moneyy":"10783","stockt":"46","stocky":"41","zcra10":"7.17","zcra1_10":"9.09","id":"3706","name":"神達","MA20":29.51,"MA5":29.22,"MA10":29.26,"MA60":29.5483,"UB":30.1624,"LB":28.8576,"BLimitP":30.07,"UBSlopeP":-0.02,"signals":["gt-MA5"],"candlestick":[],"bandWidthP":4.52,"VMA30":4936.3338,"VLimitP":20.81,"change":0.25,"changePercent":0.86,"link":"https://histock.tw/stock/tv/tvchart.aspx?no=3706","link2":"https://invest.cnyes.com/twstock/TWS/3706/technical","buyiDays":"","buyfDays":""},{"dv":"139.5","deal":"2119","ep":"14.61","net":"2.52","zcra12":"8.97","zcra1_12":"11.22","zch4":"58.22","zch1_4":"151.96","type":"化工","zcj1":"14.46","zcra22":"42.46","zca3":"553","zcra1_3":"4.37","zcra3":"4.38","buyi":"-157","buyf":"-753","moneyt":"5268","moneyy":"5372","stockt":"700","stocky":"662","zcra10":"7.45","zcra1_10":"20.94","id":"3708","name":"上緯投控","MA20":141.7,"MA5":141,"MA10":139.2,"MA60":152.55,"UB":152.6928,"LB":130.7072,"BLimitP":39.99,"UBSlopeP":-1.81,"signals":["lt-MA5","lt-MA20"],"candlestick":[],"bandWidthP":16.82,"VMA30":2457.8656,"VLimitP":42.98,"change":-3.5,"changePercent":-2.45,"link":"https://histock.tw/stock/tv/tvchart.aspx?no=3708","link2":"https://invest.cnyes.com/twstock/TWS/3708/technical","buyiDays":"","buyfDays":""},{"dv":"98.6","deal":"42997","ep":"17.58","net":"2.05","zcra12":"3.96","zcra1_12":"5.95","zch4":"29.69","zch1_4":"31.74","type":"半導體","zcj1":"15.81","zcra22":"61.49","zca3":"72303","zcra1_3":"7.18","zcra3":"5.69","buyi":"2336","buyf":"-1076","moneyt":"23590","moneyy":"23229","stockt":"1823","stocky":"1683","zcra10":"8.3","zcra1_10":"8.42","id":"3711","name":"日月光投控","MA20":97.24,"MA5":95.66,"MA10":99.37,"MA60":83.8317,"UB":108.4836,"LB":85.9964,"BLimitP":56.05,"UBSlopeP":-0.27,"signals":["gt-MA20"],"candlestick":[],"bandWidthP":26.15,"VMA30":39002.3934,"VLimitP":63.42,"change":3.7,"changePercent":3.9,"link":"https://histock.tw/stock/tv/tvchart.aspx?no=3711","link2":"https://invest.cnyes.com/twstock/TWS/3711/technical","buyiDays":"","buyfDays":""},{"dv":"61.5","deal":"1600","ep":"44.24","net":"1.93","zcra12":"3.29","zcra1_12":"3.33","zch4":"11.82","zch1_4":"3.1","type":"精密機械加工","zcj1":"34.6","zcra22":"55.64","zca3":"485","zcra1_3":"4.23","zcra3":"5.38","buyi":"0","buyf":"-59","moneyt":"1746","moneyy":"2103","stockt":"1436","stocky":"1290","zcra10":"10.2","zcra1_10":"11.6","id":"4566","name":"時碩工業","MA20":58.52,"MA5":64.46,"MA10":61.91,"MA60":48.0775,"UB":68.1124,"LB":48.9276,"BLimitP":65.53,"UBSlopeP":0.47,"signals":[],"candlestick":[],"bandWidthP":39.21,"VMA30":2391.4084,"VLimitP":43.26,"change":1.1,"changePercent":1.82,"link":"https://histock.tw/stock/tv/tvchart.aspx?no=4566","link2":"https://invest.cnyes.com/twstock/TWS/4566/technical","buyiDays":"","buyfDays":""},{"dv":"60.1","deal":"4023","ep":"22.77","net":"2.99","zcra12":"2.68","zcra1_12":"2.88","zch4":"14.1","zch1_4":"17.02","type":"電信數據服務","zcj1":"32.94","zcra22":"47.37","zca3":"21474","zcra1_3":"14.28","zcra3":"14.22","buyi":"-9","buyf":"-549","moneyt":"760","moneyy":"759","stockt":"0","stocky":"0","zcra10":"12.18","zcra1_10":"13.05","id":"4904","name":"遠傳","MA20":61.02,"MA5":60.12,"MA10":60.31,"MA60":61.065,"UB":62.6602,"LB":59.3798,"BLimitP":21.95,"UBSlopeP":-0.03,"signals":[],"candlestick":[],"bandWidthP":5.52,"VMA30":3508.2959,"VLimitP":60.13,"change":0.1,"changePercent":0.17,"link":"https://histock.tw/stock/tv/tvchart.aspx?no=4904","link2":"https://invest.cnyes.com/twstock/TWS/4904/technical","buyiDays":"","buyfDays":""},{"dv":"43.75","deal":"3008","ep":"19.89","net":"1.64","zcra12":"2.53","zcra1_12":"3.42","zch4":"263.18","zch1_4":"261.95","type":"半導體","zcj1":"58.14","zcra22":"33.74","zca3":"775","zcra1_3":"7.52","zcra3":"5.64","buyi":"0","buyf":"460","moneyt":"10289","moneyy":"10245","stockt":"1267","stocky":"1289","zcra10":"10.04","zcra1_10":"19.21","id":"4919","name":"新唐","MA20":45.365,"MA5":43.84,"MA10":44.26,"MA60":45.5308,"UB":48.1714,"LB":42.5586,"BLimitP":21.23,"UBSlopeP":-0.26,"signals":[],"candlestick":[],"bandWidthP":13.19,"VMA30":6235.9311,"VLimitP":26.66,"change":1.2,"changePercent":2.82,"link":"https://histock.tw/stock/tv/tvchart.aspx?no=4919","link2":"https://invest.cnyes.com/twstock/TWS/4919/technical","buyiDays":"","buyfDays":""},{"dv":"42.95","deal":"4605","ep":"20.75","net":"2.32","zcra12":"2.05","zcra1_12":"2.61","zch4":"57.97","zch1_4":"35.49","type":"消費性IC設計","zcj1":"35.92","zcra22":"25.64","zca3":"334","zcra1_3":"10.56","zcra3":"8.46","buyi":"0","buyf":"1853","moneyt":"1719","moneyy":"1725","stockt":"22","stocky":"9","zcra10":"10.9","zcra1_10":"13.47","id":"4952","name":"凌通","MA20":41.7025,"MA5":41.55,"MA10":41.205,"MA60":40.095,"UB":43.6989,"LB":39.7061,"BLimitP":81.24,"UBSlopeP":0.31,"signals":["gt-MA5","gt-MA10","gt-MA20"],"candlestick":[],"bandWidthP":10.06,"VMA30":2234.7287,"VLimitP":84.91,"change":2.55,"changePercent":6.31,"link":"https://histock.tw/stock/tv/tvchart.aspx?no=4952","link2":"https://invest.cnyes.com/twstock/TWS/4952/technical","buyiDays":"","buyfDays":"+2"},{"dv":"113.5","deal":"6917","ep":"13.72","net":"1.52","zcra12":"9.93","zcra1_12":"10.5","zch4":"68.76","zch1_4":"46.39","type":"PCB","zcj1":"32.7","zcra22":"35.41","zca3":"16273","zcra1_3":"12.59","zcra3":"12.33","buyi":"-16","buyf":"-2372","moneyt":"14472","moneyy":"14743","stockt":"153","stocky":"154","zcra10":"14.72","zcra1_10":"17.3","id":"4958","name":"臻鼎-KY","MA20":117.65,"MA5":115.6,"MA10":116.25,"MA60":119.05,"UB":122.9046,"LB":112.3954,"BLimitP":10.51,"UBSlopeP":0.05,"signals":[],"candlestick":[],"bandWidthP":9.35,"VMA30":8794.4061,"VLimitP":38.94,"change":-0.5,"changePercent":-0.44,"link":"https://histock.tw/stock/tv/tvchart.aspx?no=4958","link2":"https://invest.cnyes.com/twstock/TWS/4958/technical","buyiDays":"","buyfDays":""},{"dv":"65.4","deal":"9709","ep":"25.06","net":"1.95","zcra12":"2.96","zcra1_12":"2.14","zch4":"25","zch1_4":"32.83","type":"電視機構件","zcj1":"35.6","zcra22":"34.48","zca3":"2022","zcra1_3":"4.14","zcra3":"6.47","buyi":"0","buyf":"339","moneyt":"9287","moneyy":"9501","stockt":"1428","stocky":"2013","zcra10":"8.53","zcra1_10":"6.36","id":"5243","name":"乙盛-KY","MA20":66.97,"MA5":65.96,"MA10":65.44,"MA60":52.9758,"UB":72.1364,"LB":61.8036,"BLimitP":34.81,"UBSlopeP":-0.39,"signals":[],"candlestick":[],"bandWidthP":16.72,"VMA30":20918.4359,"VLimitP":25.77,"change":3.5,"changePercent":5.65,"link":"https://histock.tw/stock/tv/tvchart.aspx?no=5243","link2":"https://invest.cnyes.com/twstock/TWS/5243/technical","buyiDays":"","buyfDays":""},{"dv":"42.1","deal":"2559","ep":"7.65","net":"0.93","zcra12":"6.05","zcra1_12":"3.55","zch4":"18.47","zch1_4":"17.55","type":"印刷電路板","zcj1":"25.96","zcra22":"49.54","zca3":"7542","zcra1_3":"5.3","zcra3":"8.2","buyi":"0","buyf":"197","moneyt":"24697","moneyy":"24762","stockt":"171","stocky":"176","zcra10":"10.23","zcra1_10":"6.82","id":"5469","name":"瀚宇博","MA20":42.7275,"MA5":41.89,"MA10":41.825,"MA60":43.665,"UB":44.7299,"LB":40.7251,"BLimitP":34.33,"UBSlopeP":-0.38,"signals":["gt-MA5","gt-MA10"],"candlestick":[],"bandWidthP":9.83,"VMA30":3811.1175,"VLimitP":25.84,"change":0.55,"changePercent":1.32,"link":"https://histock.tw/stock/tv/tvchart.aspx?no=5469","link2":"https://invest.cnyes.com/twstock/TWS/5469/technical","buyiDays":"","buyfDays":"+2"},{"dv":"67.9","deal":"4804","ep":"13.42","net":"3.26","zcra12":"2.03","zcra1_12":"2.02","zch4":"81.86","zch1_4":"83.39","type":"消費性IC","zcj1":"11.44","zcra22":"17.23","zca3":"364","zcra1_3":"8.95","zcra3":"11.2","buyi":"0","buyf":"-224","moneyt":"11847","moneyy":"11756","stockt":"493","stocky":"513","zcra10":"11.44","zcra1_10":"11.49","id":"5471","name":"松翰","MA20":68.125,"MA5":68.48,"MA10":68.54,"MA60":66.54,"UB":73.2758,"LB":62.9742,"BLimitP":47.82,"UBSlopeP":0.03,"signals":[],"candlestick":[],"bandWidthP":16.36,"VMA30":7255.7163,"VLimitP":44.13,"change":1.1,"changePercent":1.65,"link":"https://histock.tw/stock/tv/tvchart.aspx?no=5471","link2":"https://invest.cnyes.com/twstock/TWS/5471/technical","buyiDays":"","buyfDays":""},{"dv":"207.5","deal":"5250","ep":"30.74","net":"1.79","zcra12":"4.49","zcra1_12":"6.13","zch4":"62.3","zch1_4":"58.9","type":"IC封裝","zcj1":"12.04","zcra22":"18.08","zca3":"1882","zcra1_3":"15.36","zcra3":"12.27","buyi":"-380","buyf":"-431","moneyt":"11102","moneyy":"11346","stockt":"241","stocky":"258","zcra10":"7.19","zcra1_10":"9.72","id":"6271","name":"同欣電","MA20":212.65,"MA5":211.8,"MA10":217.4,"MA60":185.0333,"UB":243.3422,"LB":181.9578,"BLimitP":41.61,"UBSlopeP":-0.16,"signals":[],"candlestick":[],"bandWidthP":33.74,"VMA30":8758.8662,"VLimitP":35.67,"change":2,"changePercent":0.97,"link":"https://histock.tw/stock/tv/tvchart.aspx?no=6271","link2":"https://invest.cnyes.com/twstock/TWS/6271/technical","buyiDays":"","buyfDays":""},{"dv":"28.2","deal":"3540","ep":"10.11","net":"1.44","zcra12":"2.87","zcra1_12":"1.95","zch4":"19.86","zch1_4":"2.05","type":"電源供應器","zcj1":"23.61","zcra22":"55.92","zca3":"957","zcra1_3":"0.13","zcra3":"0.42","buyi":"0","buyf":"443","moneyt":"10564","moneyy":"10862","stockt":"281","stocky":"317","zcra10":"17.73","zcra1_10":"12.55","id":"6282","name":"康舒","MA20":28.9775,"MA5":28.45,"MA10":28.425,"MA60":28.5417,"UB":30.5499,"LB":27.4051,"BLimitP":25.28,"UBSlopeP":-0.13,"signals":[],"candlestick":[],"bandWidthP":11.48,"VMA30":8173.8412,"VLimitP":36.55,"change":0.3,"changePercent":1.08,"link":"https://histock.tw/stock/tv/tvchart.aspx?no=6282","link2":"https://invest.cnyes.com/twstock/TWS/6282/technical","buyiDays":"","buyfDays":""},{"dv":"75.2","deal":"1977","ep":"21.3","net":"1.83","zcra12":"3.76","zcra1_12":"5.21","zch4":"8.93","zch1_4":"7.62","type":"手機製造","zcj1":"24.66","zcra22":"53.06","zca3":"4602","zcra1_3":"3.6","zcra3":"2.56","buyi":"-6","buyf":"281","moneyt":"9187","moneyy":"9157","stockt":"268","stocky":"290","zcra10":"9.13","zcra1_10":"12.83","id":"6285","name":"啟碁","MA20":77.025,"MA5":75.7,"MA10":75.75,"MA60":78.99,"UB":80.371,"LB":73.679,"BLimitP":22.73,"UBSlopeP":-0.56,"signals":[],"candlestick":[],"bandWidthP":9.08,"VMA30":3519.3581,"VLimitP":34.57,"change":0.2,"changePercent":0.27,"link":"https://histock.tw/stock/tv/tvchart.aspx?no=6285","link2":"https://invest.cnyes.com/twstock/TWS/6285/technical","buyiDays":"","buyfDays":""},{"dv":"31.5","deal":"1119","ep":"33.51","net":"2.27","zcra12":"1.21","zcra1_12":"0.91","zch4":"-9.25","zch1_4":"14.88","type":"汽車零組件","zcj1":"24.78","zcra22":"52.52","zca3":"589","zcra1_3":"5.05","zcra3":"5.94","buyi":"0","buyf":"334","moneyt":"9396","moneyy":"9415","stockt":"917","stocky":"953","zcra10":"9","zcra1_10":"7.45","id":"6288","name":"聯嘉","MA20":32.585,"MA5":31.7,"MA10":31.76,"MA60":33.1067,"UB":34.5248,"LB":30.6452,"BLimitP":22.03,"UBSlopeP":-1.46,"signals":[],"candlestick":[],"bandWidthP":12.66,"VMA30":4834.3818,"VLimitP":35.1,"change":0.6,"changePercent":1.94,"link":"https://histock.tw/stock/tv/tvchart.aspx?no=6288","link2":"https://invest.cnyes.com/twstock/TWS/6288/technical","buyiDays":"","buyfDays":"+2"},{"dv":"56","deal":"3628","ep":"21.71","net":"2.63","zcra12":"2.21","zcra1_12":"2.42","zch4":"-57.77","zch1_4":"28.53","type":"太陽能","zcj1":"19.81","zcra22":"57.85","zca3":"84","zcra1_3":"17.33","zcra3":"17.32","buyi":"0","buyf":"-295","moneyt":"17141","moneyy":"17476","stockt":"7952","stocky":"8038","zcra10":"11.45","zcra1_10":"14.42","id":"6477","name":"安集","MA20":62.02,"MA5":58.28,"MA10":59.81,"MA60":63.0267,"UB":68.3694,"LB":55.6706,"BLimitP":2.59,"UBSlopeP":-0.86,"signals":[],"candlestick":["bear-engulfing"],"bandWidthP":22.81,"VMA30":12361.0404,"VLimitP":36.06,"change":-1.3,"changePercent":-2.27,"link":"https://histock.tw/stock/tv/tvchart.aspx?no=6477","link2":"https://invest.cnyes.com/twstock/TWS/6477/technical","buyiDays":"","buyfDays":""},{"dv":"80.2","deal":"2348","ep":"14.05","net":"2.48","zcra12":"6.85","zcra1_12":"6.75","zch4":"-2.29","zch1_4":"-19.64","type":"利基型銅箔基板供應商","zcj1":"14.22","zcra22":"44.11","zca3":"670","zcra1_3":"9","zcra3":"11.4","buyi":"0","buyf":"71","moneyt":"3224","moneyy":"3145","stockt":"74","stocky":"80","zcra10":"22.92","zcra1_10":"27.9","id":"6672","name":"騰輝電子-KY","MA20":72.31,"MA5":80.42,"MA10":77.41,"MA60":70.3867,"UB":84.536,"LB":60.084,"BLimitP":82.27,"UBSlopeP":1.23,"signals":[],"candlestick":[],"bandWidthP":40.7,"VMA30":1659.8016,"VLimitP":57.94,"change":1.7,"changePercent":2.17,"link":"https://histock.tw/stock/tv/tvchart.aspx?no=6672","link2":"https://invest.cnyes.com/twstock/TWS/6672/technical","buyiDays":"","buyfDays":"+2"},{"dv":"30","deal":"1396","ep":"19.48","net":"3.33","zcra12":"17.19","zcra1_12":"13.47","zch4":"11.26","zch1_4":"16.41","type":"IC零組件通路商","zcj1":"37.99","zcra22":"55.33","zca3":"2016","zcra1_3":"8.82","zcra3":"7.09","buyi":"0","buyf":"-155","moneyt":"8290","moneyy":"8494","stockt":"6817","stocky":"6757","zcra10":"17.35","zcra1_10":"15.74","id":"8070","name":"長華","MA20":30.85,"MA5":30.4,"MA10":30.97,"MA60":28.9725,"UB":32.3886,"LB":29.3114,"BLimitP":22.38,"UBSlopeP":-0.06,"signals":[],"candlestick":[],"bandWidthP":10.5,"VMA30":6428.6363,"VLimitP":26.42,"change":0.05,"changePercent":0.17,"link":"https://histock.tw/stock/tv/tvchart.aspx?no=8070","link2":"https://invest.cnyes.com/twstock/TWS/8070/technical","buyiDays":"","buyfDays":""},{"dv":"34.7","deal":"11731","ep":"11.41","net":"1.26","zcra12":"3.55","zcra1_12":"1.37","zch4":"20.12","zch1_4":"10.92","type":"IC封測","zcj1":"11.75","zcra22":"42.72","zca3":"5993","zcra1_3":"11.36","zcra3":"12.08","buyi":"0","buyf":"-1540","moneyt":"13104","moneyy":"13361","stockt":"128","stocky":"149","zcra10":"13.7","zcra1_10":"6.05","id":"8150","name":"南茂","MA20":35.55,"MA5":34.35,"MA10":35.31,"MA60":34.0058,"UB":37.6026,"LB":33.4974,"BLimitP":29.29,"UBSlopeP":0.01,"signals":["gt-MA5"],"candlestick":[],"bandWidthP":12.26,"VMA30":11101.6792,"VLimitP":52.29,"change":1.05,"changePercent":3.12,"link":"https://histock.tw/stock/tv/tvchart.aspx?no=8150","link2":"https://invest.cnyes.com/twstock/TWS/8150/technical","buyiDays":"","buyfDays":""},{"dv":"41","deal":"2982","ep":"13.31","net":"1.36","zcra12":"3.21","zcra1_12":"5.43","zch4":"25.2","zch1_4":"26.85","type":"鍵盤","zcj1":"22.9","zcra22":"53.24","zca3":"1708","zcra1_3":"9.43","zcra3":"5.56","buyi":"0","buyf":"-643","moneyt":"5510","moneyy":"5470","stockt":"84","stocky":"85","zcra10":"10.09","zcra1_10":"17.48","id":"8163","name":"達方","MA20":42.6725,"MA5":41.24,"MA10":41.34,"MA60":43.05,"UB":45.5509,"LB":39.7941,"BLimitP":20.95,"UBSlopeP":-0.4,"signals":["lt-MA5"],"candlestick":[],"bandWidthP":14.47,"VMA30":2221.7542,"VLimitP":67.47,"change":0.45,"changePercent":1.11,"link":"https://histock.tw/stock/tv/tvchart.aspx?no=8163","link2":"https://invest.cnyes.com/twstock/TWS/8163/technical","buyiDays":"","buyfDays":""},{"dv":"30","deal":"5298","ep":"37.5","net":"2.31","zcra12":"0.8","zcra1_12":"1.02","zch4":"21.86","zch1_4":"22.14","type":"偏光片","zcj1":"40.65","zcra22":"60","zca3":"1132","zcra1_3":"3.44","zcra3":"2.54","buyi":"0","buyf":"2215","moneyt":"5104","moneyy":"5206","stockt":"845","stocky":"844","zcra10":"6.18","zcra1_10":"7.83","id":"8215","name":"明基材","MA20":28.475,"MA5":29.93,"MA10":29.06,"MA60":26.78,"UB":30.8482,"LB":26.1018,"BLimitP":82.13,"UBSlopeP":-0.46,"signals":["gt-MA5"],"candlestick":[],"bandWidthP":18.18,"VMA30":10559.2237,"VLimitP":36.63,"change":1,"changePercent":3.45,"link":"https://histock.tw/stock/tv/tvchart.aspx?no=8215","link2":"https://invest.cnyes.com/twstock/TWS/8215/technical","buyiDays":"","buyfDays":""},{"dv":"283.5","deal":"1484","ep":"24.17","net":"5.66","zcra12":"8.37","zcra1_12":"5.72","zch4":"0.55","zch1_4":"12.85","type":"自行車","zcj1":"25.4","zcra22":"43.91","zca3":"1210","zcra1_3":"5.23","zcra3":"6.06","buyi":"426","buyf":"69","moneyt":"673","moneyy":"679","stockt":"46","stocky":"54","zcra10":"18.07","zcra1_10":"13.77","id":"9914","name":"美利達","MA20":266.975,"MA5":274.9,"MA10":276,"MA60":252.05,"UB":294.21,"LB":239.74,"BLimitP":80.34,"UBSlopeP":0.38,"signals":["gt-MA5","gt-MA10"],"candlestick":[],"bandWidthP":22.72,"VMA30":1570.961,"VLimitP":47.1,"change":13,"changePercent":4.81,"link":"https://histock.tw/stock/tv/tvchart.aspx?no=9914","link2":"https://invest.cnyes.com/twstock/TWS/9914/technical","buyiDays":"+15","buyfDays":"+2"},{"dv":"286","deal":"1146","ep":"25.15","net":"4.54","zcra12":"9","zcra1_12":"7.64","zch4":"19.63","zch1_4":"12.01","type":"自行車","zcj1":"13.34","zcra22":"60.25","zca3":"1937","zcra1_3":"6.48","zcra3":"7.46","buyi":"42","buyf":"372","moneyt":"387","moneyy":"414","stockt":"31","stocky":"31","zcra10":"15.72","zcra1_10":"13.72","id":"9921","name":"巨大","MA20":283.425,"MA5":282.7,"MA10":282.95,"MA60":277.8917,"UB":292.432,"LB":274.418,"BLimitP":64.29,"UBSlopeP":0.01,"signals":["gt-MA5","gt-MA10","gt-MA20"],"candlestick":[],"bandWidthP":6.56,"VMA30":1189.6968,"VLimitP":47.83,"change":4,"changePercent":1.42,"link":"https://histock.tw/stock/tv/tvchart.aspx?no=9921","link2":"https://invest.cnyes.com/twstock/TWS/9921/technical","buyiDays":"","buyfDays":"+2"},{"dv":"39.25","deal":"2023","ep":"8.5","net":"0.61","zcra12":"9.35","zcra1_12":"7.22","zch4":"40.16","zch1_4":"51.16","type":"營建","zcj1":"27.81","zcra22":"43.12","zca3":"3095","zcra1_3":"13.26","zcra3":"11.01","buyi":"0","buyf":"106","moneyt":"8207","moneyy":"8267","stockt":"522","stocky":"514","zcra10":"15.89","zcra1_10":"23.76","id":"9945","name":"潤泰新","MA20":39.85,"MA5":39.11,"MA10":39.32,"MA60":40.55,"UB":41.04,"LB":38.66,"BLimitP":24.79,"UBSlopeP":-0.23,"signals":["gt-MA5"],"candlestick":[],"bandWidthP":6.16,"VMA30":3602.8168,"VLimitP":18.04,"change":0.45,"changePercent":1.16,"link":"https://histock.tw/stock/tv/tvchart.aspx?no=9945","link2":"https://invest.cnyes.com/twstock/TWS/9945/technical","buyiDays":"","buyfDays":"+2"},{"dv":"23.95","deal":"1199","ep":"12.74","net":"1.92","zcra12":"1.81","zcra1_12":"1.61","zch4":"3.44","zch1_4":"-0.83","type":"散熱風扇馬達","zcj1":"37.6","zcra22":"45.93","zca3":"292","zcra1_3":"7.11","zcra3":"7.58","buyi":"0","buyf":"-186","moneyt":"3889","moneyy":"3942","stockt":"143","stocky":"89","zcra10":"13.8","zcra1_10":"13.24","id":"3071","name":"協禧","MA20":25.0625,"MA5":25.19,"MA10":25.3,"MA60":24.3233,"UB":26.6261,"LB":23.4989,"BLimitP":14.43,"UBSlopeP":0.03,"signals":[],"candlestick":[],"bandWidthP":13.31,"VMA30":2607.7667,"VLimitP":39.01,"change":0.05,"changePercent":0.21,"link":"https://histock.tw/stock/tv/tvchart.aspx?no=3071","link2":"https://invest.cnyes.com/twstock/TWS/3071/technical","buyiDays":"","buyfDays":""},{"dv":"42.2","deal":"1019","ep":"11.66","net":"1.95","zcra12":"2.49","zcra1_12":"2.77","zch4":"68.42","zch1_4":"84.22","type":"電源供應器","zcj1":"10.21","zcra22":"36.24","zca3":"662","zcra1_3":"11.08","zcra3":"12.68","buyi":"0","buyf":"189","moneyt":"12502","moneyy":"12549","stockt":"189","stocky":"190","zcra10":"12.5","zcra1_10":"14.47","id":"3078","name":"僑威","MA20":42.9025,"MA5":42.56,"MA10":42.065,"MA60":43.8508,"UB":45.0201,"LB":40.7849,"BLimitP":33.41,"UBSlopeP":-0.74,"signals":[],"candlestick":[],"bandWidthP":10.38,"VMA30":4217.1333,"VLimitP":32.78,"change":0.1,"changePercent":0.24,"link":"https://histock.tw/stock/tv/tvchart.aspx?no=3078","link2":"https://invest.cnyes.com/twstock/TWS/3078/technical","buyiDays":"","buyfDays":""},{"dv":"132.5","deal":"6604","ep":"20.67","net":"3.82","zcra12":"5.34","zcra1_12":"3.6","zch4":"15.21","zch1_4":"32.17","type":"硬碟相關","zcj1":"12.73","zcra22":"27.81","zca3":"572","zcra1_3":"18.73","zcra3":"24.67","buyi":"215","buyf":"-274","moneyt":"5610","moneyy":"5418","stockt":"149","stocky":"65","zcra10":"23","zcra1_10":"17.34","id":"3217","name":"優群","MA20":115,"MA5":125.2,"MA10":120.75,"MA60":112.7417,"UB":130.333,"LB":99.667,"BLimitP":107.07,"UBSlopeP":2.58,"signals":[],"candlestick":["hammer"],"bandWidthP":30.77,"VMA30":1977.8333,"VLimitP":101.75,"change":3,"changePercent":2.32,"link":"https://histock.tw/stock/tv/tvchart.aspx?no=3217","link2":"https://invest.cnyes.com/twstock/TWS/3217/technical","buyiDays":"+7","buyfDays":""},{"dv":"43.6","deal":"8673","ep":"13.8","net":"1.74","zcra12":"2.36","zcra1_12":"3.31","zch4":"34.32","zch1_4":"31.46","type":"IC測試","zcj1":"13.77","zcra22":"39.01","zca3":"3542","zcra1_3":"21.77","zcra3":"19.56","buyi":"71","buyf":"840","moneyt":"12158","moneyy":"12290","stockt":"261","stocky":"304","zcra10":"9.94","zcra1_10":"14.62","id":"3264","name":"欣銓","MA20":41.3325,"MA5":42.78,"MA10":42.73,"MA60":38.8367,"UB":44.6573,"LB":38.0077,"BLimitP":84.1,"UBSlopeP":0.67,"signals":["gt-MA5","gt-MA10"],"candlestick":[],"bandWidthP":17.5,"VMA30":8850.7333,"VLimitP":49.53,"change":2,"changePercent":4.81,"link":"https://histock.tw/stock/tv/tvchart.aspx?no=3264","link2":"https://invest.cnyes.com/twstock/TWS/3264/technical","buyiDays":"+2","buyfDays":"+3"},{"dv":"46.35","deal":"4293","ep":"13.24","net":"1.61","zcra12":"1.85","zcra1_12":"2.39","zch4":"79.72","zch1_4":"40.43","type":"電池相關","zcj1":"11.04","zcra22":"59.57","zca3":"553","zcra1_3":"2.31","zcra3":"2.13","buyi":"0","buyf":"-1329","moneyt":"8150","moneyy":"8516","stockt":"137","stocky":"281","zcra10":"6.76","zcra1_10":"8.8","id":"3323","name":"加百裕","MA20":47.6775,"MA5":48.92,"MA10":47.845,"MA60":45.92,"UB":51.1467,"LB":44.2083,"BLimitP":30.87,"UBSlopeP":0.01,"signals":[],"candlestick":[],"bandWidthP":15.69,"VMA30":6669.8667,"VLimitP":43.73,"change":0.15,"changePercent":0.32,"link":"https://histock.tw/stock/tv/tvchart.aspx?no=3323","link2":"https://invest.cnyes.com/twstock/TWS/3323/technical","buyiDays":"","buyfDays":""},{"dv":"209","deal":"1578","ep":"17.61","net":"4.39","zcra12":"11.71","zcra1_12":"2.9","zch4":"38.08","zch1_4":"30.5","type":"散熱模組","zcj1":"18.98","zcra22":"53.17","zca3":"777","zcra1_3":"2.38","zcra3":"11.6","buyi":"-541","buyf":"-246","moneyt":"10920","moneyy":"10684","stockt":"1241","stocky":"1269","zcra10":"33.24","zcra1_10":"10.27","id":"3324","name":"雙鴻","MA20":224.925,"MA5":212.4,"MA10":217.55,"MA60":226.425,"UB":248.2966,"LB":201.5534,"BLimitP":15.93,"UBSlopeP":0.19,"signals":[],"candlestick":[],"bandWidthP":23.19,"VMA30":3980.7667,"VLimitP":35.48,"change":0.5,"changePercent":0.24,"link":"https://histock.tw/stock/tv/tvchart.aspx?no=3324","link2":"https://invest.cnyes.com/twstock/TWS/3324/technical","buyiDays":"","buyfDays":""},{"dv":"98.2","deal":"1011","ep":"18.08","net":"2.2","zcra12":"3.95","zcra1_12":"4.13","zch4":"28.47","zch1_4":"9.07","type":"IC設計","zcj1":"22.12","zcra22":"36.36","zca3":"617","zcra1_3":"15.09","zcra3":"12.8","buyi":"0","buyf":"-12","moneyt":"3039","moneyy":"3041","stockt":"23","stocky":"31","zcra10":"9.06","zcra1_10":"9.62","id":"3587","name":"閎康","MA20":97.23,"MA5":99.38,"MA10":102.78,"MA60":90.8,"UB":112.185,"LB":82.275,"BLimitP":53.24,"UBSlopeP":-0.06,"signals":[],"candlestick":[],"bandWidthP":36.35,"VMA30":1842.5667,"VLimitP":39.98,"change":2.4,"changePercent":2.51,"link":"https://histock.tw/stock/tv/tvchart.aspx?no=3587","link2":"https://invest.cnyes.com/twstock/TWS/3587/technical","buyiDays":"","buyfDays":""},{"dv":"110","deal":"1926","ep":"32.26","net":"5.82","zcra12":"1.03","zcra1_12":"2.2","zch4":"69.46","zch1_4":"87.49","type":"被動元件導電漿","zcj1":"21.42","zcra22":"40.75","zca3":"29","zcra1_3":"9.52","zcra3":"6.67","buyi":"0","buyf":"4","moneyt":"3299","moneyy":"3447","stockt":"180","stocky":"140","zcra10":"6.54","zcra1_10":"13.67","id":"4760","name":"勤凱","MA20":118.045,"MA5":116.1,"MA10":118.95,"MA60":96.9483,"UB":138.5248,"LB":97.5652,"BLimitP":30.36,"UBSlopeP":-0.98,"signals":[],"candlestick":[],"bandWidthP":41.98,"VMA30":2687.7667,"VLimitP":43.37,"change":3.5,"changePercent":3.29,"link":"https://histock.tw/stock/tv/tvchart.aspx?no=4760","link2":"https://invest.cnyes.com/twstock/TWS/4760/technical","buyiDays":"","buyfDays":""},{"dv":"71","deal":"1382","ep":"12.52","net":"1.88","zcra12":"3.57","zcra1_12":"4.4","zch4":"67.59","zch1_4":"62.67","type":"筆電散熱機構件","zcj1":"44.34","zcra22":"37.65","zca3":"338","zcra1_3":"13.78","zcra3":"12.39","buyi":"0","buyf":"-34","moneyt":"3104","moneyy":"3263","stockt":"70","stocky":"71","zcra10":"10.29","zcra1_10":"13.06","id":"5223","name":"安力-KY","MA20":72.845,"MA5":74.92,"MA10":74.39,"MA60":71.32,"UB":78.4058,"LB":67.2842,"BLimitP":33.41,"UBSlopeP":0.01,"signals":["lt-MA60"],"candlestick":[],"bandWidthP":16.53,"VMA30":1631.9667,"VLimitP":47.58,"change":-1,"changePercent":-1.39,"link":"https://histock.tw/stock/tv/tvchart.aspx?no=5223","link2":"https://invest.cnyes.com/twstock/TWS/5223/technical","buyiDays":"","buyfDays":""},{"dv":"118","deal":"6965","ep":"30.65","net":"6.54","zcra12":"3.58","zcra1_12":"3.76","zch4":"15","zch1_4":"26.42","type":"專業晶圓代工","zcj1":"45.04","zcra22":"30.99","zca3":"8445","zcra1_3":"24.73","zcra3":"24.43","buyi":"228","buyf":"281","moneyt":"4118","moneyy":"4526","stockt":"353","stocky":"351","zcra10":"19.88","zcra1_10":"21.52","id":"5347","name":"世界","MA20":118.925,"MA5":116.9,"MA10":120,"MA60":112.875,"UB":127.026,"LB":110.824,"BLimitP":44.29,"UBSlopeP":-0.06,"signals":["gt-MA5"],"candlestick":[],"bandWidthP":14.62,"VMA30":7493.3,"VLimitP":47.05,"change":3,"changePercent":2.61,"link":"https://histock.tw/stock/tv/tvchart.aspx?no=5347","link2":"https://invest.cnyes.com/twstock/TWS/5347/technical","buyiDays":"+10","buyfDays":"+2"},{"dv":"55.1","deal":"10295","ep":"28.55","net":"2.36","zcra12":"2.29","zcra1_12":"3.53","zch4":"24.6","zch1_4":"-0.7","type":"二極體","zcj1":"10.97","zcra22":"47.96","zca3":"2084","zcra1_3":"17.78","zcra3":"12.36","buyi":"1716","buyf":"1310","moneyt":"9462","moneyy":"9726","stockt":"529","stocky":"547","zcra10":"13.69","zcra1_10":"17.57","id":"5425","name":"台半","MA20":55.55,"MA5":53.24,"MA10":53.49,"MA60":55.1683,"UB":60.4772,"LB":50.6228,"BLimitP":45.43,"UBSlopeP":-1.35,"signals":["gt-MA5","gt-MA10"],"candlestick":[],"bandWidthP":19.47,"VMA30":10800.5333,"VLimitP":48.68,"change":4.4,"changePercent":8.68,"link":"https://histock.tw/stock/tv/tvchart.aspx?no=5425","link2":"https://invest.cnyes.com/twstock/TWS/5425/technical","buyiDays":"","buyfDays":"+2"},{"dv":"55.2","deal":"2580","ep":"18.04","net":"2.84","zcra12":"2.58","zcra1_12":"3.41","zch4":"26.09","zch1_4":"14.15","type":"印刷電路板","zcj1":"13.83","zcra22":"29.87","zca3":"374","zcra1_3":"14.19","zcra3":"12.98","buyi":"0","buyf":"-465","moneyt":"9475","moneyy":"9324","stockt":"120","stocky":"229","zcra10":"13.3","zcra1_10":"18.13","id":"5439","name":"高技","MA20":53.925,"MA5":55.92,"MA10":54.04,"MA60":51.305,"UB":57.937,"LB":49.913,"BLimitP":65.89,"UBSlopeP":0.12,"signals":[],"candlestick":[],"bandWidthP":16.08,"VMA30":3074.2333,"VLimitP":45.78,"change":0.2,"changePercent":0.36,"link":"https://histock.tw/stock/tv/tvchart.aspx?no=5439","link2":"https://invest.cnyes.com/twstock/TWS/5439/technical","buyiDays":"","buyfDays":""},{"dv":"84.8","deal":"3765","ep":"23.04","net":"4.99","zcra12":"2.19","zcra1_12":"1","zch4":"-11.28","zch1_4":"1.47","type":"連接器","zcj1":"35.43","zcra22":"63.48","zca3":"446","zcra1_3":"6.29","zcra3":"7.53","buyi":"0","buyf":"459","moneyt":"7360","moneyy":"7400","stockt":"530","stocky":"135","zcra10":"20.23","zcra1_10":"12.31","id":"5457","name":"宣德","MA20":94.845,"MA5":86.72,"MA10":89.9,"MA60":99.2567,"UB":107.3834,"LB":82.3066,"BLimitP":9.94,"UBSlopeP":0.29,"signals":["gt-LB"],"candlestick":[],"bandWidthP":30.47,"VMA30":2559.1,"VLimitP":64.82,"change":6.5,"changePercent":8.3,"link":"https://histock.tw/stock/tv/tvchart.aspx?no=5457","link2":"https://invest.cnyes.com/twstock/TWS/5457/technical","buyiDays":"","buyfDays":"+2"},{"dv":"60.9","deal":"1006","ep":"13.78","net":"2.19","zcra12":"4.49","zcra1_12":"8.62","zch4":"40.4","zch1_4":"34.63","type":"被動元件上游","zcj1":"43.76","zcra22":"28.28","zca3":"963","zcra1_3":"33.67","zcra3":"20.52","buyi":"0","buyf":"349","moneyt":"8742","moneyy":"8837","stockt":"394","stocky":"449","zcra10":"17.23","zcra1_10":"38.58","id":"6173","name":"信昌電","MA20":64.525,"MA5":61.22,"MA10":62,"MA60":65.3467,"UB":70.2096,"LB":58.8404,"BLimitP":18.12,"UBSlopeP":-0.21,"signals":[],"candlestick":[],"bandWidthP":19.32,"VMA30":3574,"VLimitP":29.34,"change":1,"changePercent":1.67,"link":"https://histock.tw/stock/tv/tvchart.aspx?no=6173","link2":"https://invest.cnyes.com/twstock/TWS/6173/technical","buyiDays":"","buyfDays":"+2"},{"dv":"32.8","deal":"1240","ep":"19.64","net":"2.08","zcra12":"0.89","zcra1_12":"2.23","zch4":"21.14","zch1_4":"20.55","type":"被動元件上游","zcj1":"33.67","zcra22":"44.32","zca3":"816","zcra1_3":"13.34","zcra3":"8.89","buyi":"0","buyf":"247","moneyt":"3403","moneyy":"3462","stockt":"252","stocky":"257","zcra10":"6.02","zcra1_10":"14.38","id":"6175","name":"立敦","MA20":36.5225,"MA5":34.09,"MA10":34.32,"MA60":31.185,"UB":41.6921,"LB":31.3529,"BLimitP":14,"UBSlopeP":0.26,"signals":[],"candlestick":[],"bandWidthP":32.98,"VMA30":4149.6333,"VLimitP":32.87,"change":0,"changePercent":0,"link":"https://histock.tw/stock/tv/tvchart.aspx?no=6175","link2":"https://invest.cnyes.com/twstock/TWS/6175/technical","buyiDays":"","buyfDays":"+2"},{"dv":"43.5","deal":"8735","ep":"16.86","net":"2.18","zcra12":"2.3","zcra1_12":"2.11","zch4":"20.78","zch1_4":"3.64","type":"設備儀器廠商","zcj1":"16.66","zcra22":"34.01","zca3":"563","zcra1_3":"9.95","zcra3":"12.03","buyi":"0","buyf":"-631","moneyt":"7099","moneyy":"5447","stockt":"275","stocky":"100","zcra10":"13","zcra1_10":"11.44","id":"6208","name":"日揚","MA20":40.13,"MA5":41.83,"MA10":40.715,"MA60":38.72,"UB":43.0276,"LB":37.2324,"BLimitP":108.15,"UBSlopeP":1.45,"signals":["gt-UB"],"candlestick":[],"bandWidthP":15.56,"VMA30":3584.1,"VLimitP":80.97,"change":0.5,"changePercent":1.16,"link":"https://histock.tw/stock/tv/tvchart.aspx?no=6208","link2":"https://invest.cnyes.com/twstock/TWS/6208/technical","buyiDays":"","buyfDays":""},{"dv":"109.5","deal":"2622","ep":"13.57","net":"1.83","zcra12":"5.36","zcra1_12":"4.19","zch4":"10.17","zch1_4":"-10.27","type":"探針探針卡","zcj1":"10.32","zcra22":"46.45","zca3":"672","zcra1_3":"6","zcra3":"8.65","buyi":"-100","buyf":"-29","moneyt":"10992","moneyy":"10979","stockt":"347","stocky":"372","zcra10":"10.07","zcra1_10":"8.55","id":"6223","name":"旺矽","MA20":117.275,"MA5":110.5,"MA10":117.85,"MA60":114.7083,"UB":132.5344,"LB":102.0156,"BLimitP":24.52,"UBSlopeP":-0.04,"signals":[],"candlestick":[],"bandWidthP":29.92,"VMA30":6778.6333,"VLimitP":33.98,"change":3.5,"changePercent":3.3,"link":"https://histock.tw/stock/tv/tvchart.aspx?no=6223","link2":"https://invest.cnyes.com/twstock/TWS/6223/technical","buyiDays":"","buyfDays":""},{"dv":"112.5","deal":"1352","ep":"23.89","net":"2.64","zcra12":"4.78","zcra1_12":"6","zch4":"14.13","zch1_4":"6.67","type":"車用電子","zcj1":"18.4","zcra22":"36.73","zca3":"1043","zcra1_3":"18.23","zcra3":"15.6","buyi":"0","buyf":"-107","moneyt":"3476","moneyy":"3401","stockt":"122","stocky":"145","zcra10":"10.77","zcra1_10":"13.16","id":"6279","name":"胡連","MA20":115.75,"MA5":115.2,"MA10":115.05,"MA60":110.45,"UB":124.4362,"LB":107.0638,"BLimitP":31.29,"UBSlopeP":0,"signals":[],"candlestick":[],"bandWidthP":16.23,"VMA30":4799.1,"VLimitP":34.32,"change":1.5,"changePercent":1.35,"link":"https://histock.tw/stock/tv/tvchart.aspx?no=6279","link2":"https://invest.cnyes.com/twstock/TWS/6279/technical","buyiDays":"","buyfDays":""},{"dv":"37.6","deal":"1374","ep":"14.63","net":"1.59","zcra12":"2.36","zcra1_12":"2.92","zch4":"30.71","zch1_4":"13.64","type":"繞線功率電感廠","zcj1":"18.32","zcra22":"47.53","zca3":"144","zcra1_3":"5.61","zcra3":"6.28","buyi":"0","buyf":"6","moneyt":"0","moneyy":"0","stockt":"0","stocky":"0","zcra10":"10.2","zcra1_10":"13.76","id":"6432","name":"今展科","MA20":37.7725,"MA5":36.25,"MA10":36.515,"MA60":37.6142,"UB":40.7387,"LB":34.8063,"BLimitP":47.09,"UBSlopeP":-0.1,"signals":[],"candlestick":[],"bandWidthP":17.04,"VMA30":1140.3333,"VLimitP":54.74,"change":1.2,"changePercent":3.3,"link":"https://histock.tw/stock/tv/tvchart.aspx?no=6432","link2":"https://invest.cnyes.com/twstock/TWS/6432/technical","buyiDays":"","buyfDays":""},{"dv":"65","deal":"3026","ep":"31.25","net":"4.44","zcra12":"1.72","zcra1_12":"23.6","zch4":"15.47","zch1_4":"11.84","type":"LED導線架","zcj1":"60.6","zcra22":"52.71","zca3":"1466","zcra1_3":"11.18","zcra3":"8.94","buyi":"0","buyf":"12","moneyt":"7466","moneyy":"7494","stockt":"176","stocky":"154","zcra10":"12.19","zcra1_10":"16.54","id":"6548","name":"長華科","MA20":62.21,"MA5":63.42,"MA10":64.07,"MA60":56.4792,"UB":67.581,"LB":56.839,"BLimitP":75.97,"UBSlopeP":0.38,"signals":["gt-MA10"],"candlestick":[],"bandWidthP":18.9,"VMA30":5716.8,"VLimitP":37.27,"change":1.5,"changePercent":2.36,"link":"https://histock.tw/stock/tv/tvchart.aspx?no=6548","link2":"https://invest.cnyes.com/twstock/TWS/6548/technical","buyiDays":"","buyfDays":"+2"},{"dv":"259","deal":"1145","ep":"42.11","net":"9.61","zcra12":"4.06","zcra1_12":"2.94","zch4":"48.78","zch1_4":"49.12","type":"數位及類比微機電","zcj1":"11.37","zcra22":"16.08","zca3":"156","zcra1_3":"10.92","zcra3":"14.27","buyi":"183","buyf":"-102","moneyt":"2173","moneyy":"2189","stockt":"143","stocky":"145","zcra10":"18.6","zcra1_10":"18.58","id":"6679","name":"鈺太","MA20":254.425,"MA5":249.8,"MA10":254.85,"MA60":223.125,"UB":279.4894,"LB":229.3606,"BLimitP":59.13,"UBSlopeP":0.02,"signals":["gt-MA10","gt-MA20"],"candlestick":[],"bandWidthP":21.86,"VMA30":1736.8667,"VLimitP":40.5,"change":13,"changePercent":5.28,"link":"https://histock.tw/stock/tv/tvchart.aspx?no=6679","link2":"https://invest.cnyes.com/twstock/TWS/6679/technical","buyiDays":"","buyfDays":""},{"dv":"22.4","deal":"3136","ep":"20.93","net":"1.39","zcra12":"1.35","zcra1_12":"1.19","zch4":"23.55","zch1_4":"-4.84","type":"專業代工","zcj1":"33.71","zcra22":"43.06","zca3":"449","zcra1_3":"5","zcra3":"5.98","buyi":"0","buyf":"47","moneyt":"4908","moneyy":"5122","stockt":"76","stocky":"177","zcra10":"8.56","zcra1_10":"7.95","id":"8183","name":"精星","MA20":23.035,"MA5":22.9,"MA10":22.96,"MA60":20.3725,"UB":25.5686,"LB":20.5014,"BLimitP":37.47,"UBSlopeP":-0.62,"signals":[],"candlestick":[],"bandWidthP":24.72,"VMA30":6604.5667,"VLimitP":36.43,"change":1.2,"changePercent":5.66,"link":"https://histock.tw/stock/tv/tvchart.aspx?no=8183","link2":"https://invest.cnyes.com/twstock/TWS/8183/technical","buyiDays":"","buyfDays":""},{"dv":"55.2","deal":"34911","ep":"25.79","net":"2.7","zcra12":"1.57","zcra1_12":"2.93","zch4":"0.03","zch1_4":"0.33","type":"銅箔基板","zcj1":"10.93","zcra22":"25.17","zca3":"618","zcra1_3":"15.6","zcra3":"11.2","buyi":"137","buyf":"-2922","moneyt":"17295","moneyy":"17526","stockt":"1395","stocky":"1109","zcra10":"7.42","zcra1_10":"13.81","id":"8358","name":"金居","MA20":51.8175,"MA5":53.48,"MA10":52.5,"MA60":47.9775,"UB":56.1497,"LB":47.4853,"BLimitP":89.04,"UBSlopeP":0.55,"signals":[],"candlestick":[],"bandWidthP":18.25,"VMA30":22436.7667,"VLimitP":67.7,"change":1.5,"changePercent":2.79,"link":"https://histock.tw/stock/tv/tvchart.aspx?no=8358","link2":"https://invest.cnyes.com/twstock/TWS/8358/technical","buyiDays":"+8","buyfDays":""}],"date":"20210202","length":85}